Workbook

Sheet Маҳаллий банклар
B1: Mamlakat va hamkor banklarga joylashtirilishi mumkin bo‘lgan mablag‘larga limit o‘rnatish tartibiga ilova | C1: Mahalliy banklarga joylashtirilishi mumkin bo‘lgan mablag‘larga limit o‘rnatish modeli
B2: 45839 | C2: ming. so‘m
C3: 1 | D3: 2 | E3: 3 | F3: 4 | G3: 5 | H3: 6 | I3: 7 | J3: 8 | K3: 9 | L3: 10 | M3: 11 | N3: 12 | O3: 13 | P3: 14 | Q3: 15 | R3: 16 | S3: 17 | T3: 18 | U3: 19 | V3: 20 | W3: 21 | X3: 22 | Y3: 23 | Z3: 24 | AA3: 25 | AB3: 26 | AC3: 27 | AD3: 28 | AE3: 29 | AF3: 30 | AG3: 31 | AH3: 32 | AI3: 33 | AJ3: 34 | AK3: 35
A4: № | B4: АКТИВЛАР | C4: АКБ "ASIA ALLIANCE BANK" | D4: АТБ "АГРОБАНК" | E4: АК "Алокабанк" | F4: Anorbank | G4: "Асака" банк | H4: ЧАКБ"ДАВР БАНК" | I4: АКБ Hamkorbank | J4: АКБ "InFinBank" | K4: АИКБ "Ипак Йули" | L4: ИПОТЕКА-БАНК АТИБ | M4: АКБ "Капиталбанк" | N4: АО "КДБ Банк Узбекистан" | O4: АКБ "Мадад Инвест Банк" | P4: АО "Национальный банк ВЭД РУ" | Q4: ЧАКБ "Ориент Финанс" | R4: АО "Пойтахт банк" | S4: АТБ Biznesni rivojlantirish banki | T4: Octobank | U4: Садерат банк | V4: "Гарант банк" АЖ | W4: АКБ "Тибиси банк" | X4: АКБ "Tenge Bank" | Y4: ЧАБ "Трастбанк" | Z4: АКБ "ТУРОНБАНК" | AA4: AVO bank | AB4: АКБ УНИВЕРСАЛ БАНК | AC4: АК УЗПРОМСТРОЙБАНК | AD4: АК Народный банк | AE4: АО "Ziraat Bank Uzbekistan" | AF4: "UZUM BANK" AJ | AG4: Smart bank | AH4: Apex bank | AI4: Hayot bank | AJ4: Yangi bank | AK4: MKBank
A5: 1 | B5: Кассадаги нақд пул ва бошқа тўлов ҳужжатлари | C5: =+IFERROR(VLOOKUP($A5,[1]Лист1!$A$5:$E$1048576,3,0),0) | D5: =+IFERROR(VLOOKUP($A5,'[2]1'!$A$5:$E$1048576,3,0),0) | E5: =+IFERROR(VLOOKUP($A5,'[3]1'!$A$5:$E$1048576,3,0),0) | F5: =+IFERROR(VLOOKUP($A5,[4]Balance!$A$5:$E$1048576,3,0),0) | G5: =+IFERROR(VLOOKUP($A5,'[5]1'!$A$5:$E$1048576,3,0),0) | H5: =+IFERROR(VLOOKUP($A5,[6]Balance!$A$5:$E$1048576,3,0),0) | I5: =+IFERROR(VLOOKUP($A5,[7]Balance!$A$5:$E$1048576,3,0),0) | J5: =+IFERROR(VLOOKUP($A5,'[8]1'!$A$5:$E$1048576,3,0),0) | K5: =+IFERROR(VLOOKUP($A5,'[9]1'!$A$5:$E$1048576,3,0),0) | L5: =+IFERROR(VLOOKUP($A5,'[10]1'!$A$5:$E$1048576,3,0),0) | M5: =+IFERROR(VLOOKUP($A5,'[11]1'!$A$5:$E$1048576,3,0),0) | N5: =+IFERROR(VLOOKUP($A5,[12]Balance!$A$5:$E$1048576,3,0),0) | O5: =+IFERROR(VLOOKUP($A5,'[13]1 т'!$A$5:$E$1048576,3,0),0) | P5: =+IFERROR(VLOOKUP($A5,[14]Balance!$A$5:$E$1048576,3,0),0) | Q5: =+IFERROR(VLOOKUP($A5,[15]Balance!$A$5:$E$1048576,3,0),0) | R5: =+IFERROR(VLOOKUP($A5,'[16]1'!$A$5:$E$1048576,3,0),0) | S5: =+IFERROR(VLOOKUP($A5,'[17]1'!$A$5:$E$1048576,3,0),0) | T5: =+IFERROR(VLOOKUP($A5,'[18]1'!$A$5:$E$1048576,3,0),0) | U5: =+IFERROR(VLOOKUP($A5,[19]Balans!$A$5:$E$1048576,3,0),0) | V5: =+IFERROR(VLOOKUP($A5,'[20]1'!$A$5:$E$1048576,3,0),0) | W5: =+IFERROR(VLOOKUP($A5,[21]Balance!$A$5:$E$1048576,3,0),0) | X5: =+IFERROR(VLOOKUP($A5,'[22]1'!$A$5:$E$1048576,3,0),0) | Y5: =+IFERROR(VLOOKUP($A5,[23]Лист1!$A$5:$E$1048576,3,0),0) | Z5: =+IFERROR(VLOOKUP($A5,'[24]1'!$A$5:$E$1048576,3,0),0) | AA5: =+IFERROR(VLOOKUP($A5,[25]Balance!$A$5:$E$1048576,3,0),0) | AB5: =+IFERROR(VLOOKUP($A5,'[26]1'!$A$5:$E$1048576,3,0),0) | AC5: =+IFERROR(VLOOKUP($A5,'[27]1'!$A$5:$E$1048576,3,0),0) | AD5: =+IFERROR(VLOOKUP($A5,'[28]1'!$A$5:$E$1048576,3,0),0) | AE5: =+IFERROR(VLOOKUP($A5,[29]Лист1!$A$5:$E$1048576,3,0),0) | AF5: =+IFERROR(VLOOKUP($A5,'[30]1'!$A$5:$E$1048576,3,0),0) | AG5: =+IFERROR(VLOOKUP($A5,'[31]1'!$A$5:$E$1048576,3,0),0) | AH5: =+IFERROR(VLOOKUP($A5,'[32]1-жадвал'!$A$5:$E$1048576,3,0),0) | AI5: =+IFERROR(VLOOKUP($A5,[33]Balance!$A$5:$E$1048576,3,0),0) | AJ5: =+IFERROR(VLOOKUP($A5,[34]Balance!$A$5:$E$1048576,3,0),0) | AK5: =+IFERROR(VLOOKUP($A5,'[35]1'!$A$5:$E$1048576,3,0),0)
A6: 2 | B6: Банкнинг Марказий банкдаги маблағлари | C6: =+IFERROR(VLOOKUP($A6,[1]Лист1!$A$5:$E$1048576,3,0),0) | D6: =+IFERROR(VLOOKUP($A6,'[2]1'!$A$5:$E$1048576,3,0),0) | E6: =+IFERROR(VLOOKUP($A6,'[3]1'!$A$5:$E$1048576,3,0),0) | F6: =+IFERROR(VLOOKUP($A6,[4]Balance!$A$5:$E$1048576,3,0),0) | G6: =+IFERROR(VLOOKUP($A6,'[5]1'!$A$5:$E$1048576,3,0),0) | H6: =+IFERROR(VLOOKUP($A6,[6]Balance!$A$5:$E$1048576,3,0),0) | I6: =+IFERROR(VLOOKUP($A6,[7]Balance!$A$5:$E$1048576,3,0),0) | J6: =+IFERROR(VLOOKUP($A6,'[8]1'!$A$5:$E$1048576,3,0),0) | K6: =+IFERROR(VLOOKUP($A6,'[9]1'!$A$5:$E$1048576,3,0),0) | L6: =+IFERROR(VLOOKUP($A6,'[10]1'!$A$5:$E$1048576,3,0),0) | M6: =+IFERROR(VLOOKUP($A6,'[11]1'!$A$5:$E$1048576,3,0),0) | N6: =+IFERROR(VLOOKUP($A6,[12]Balance!$A$5:$E$1048576,3,0),0) | O6: =+IFERROR(VLOOKUP($A6,'[13]1 т'!$A$5:$E$1048576,3,0),0) | P6: =+IFERROR(VLOOKUP($A6,[14]Balance!$A$5:$E$1048576,3,0),0) | Q6: =+IFERROR(VLOOKUP($A6,[15]Balance!$A$5:$E$1048576,3,0),0) | R6: =+IFERROR(VLOOKUP($A6,'[16]1'!$A$5:$E$1048576,3,0),0) | S6: =+IFERROR(VLOOKUP($A6,'[17]1'!$A$5:$E$1048576,3,0),0) | T6: =+IFERROR(VLOOKUP($A6,'[18]1'!$A$5:$E$1048576,3,0),0) | U6: =+IFERROR(VLOOKUP($A6,[19]Balans!$A$5:$E$1048576,3,0),0) | V6: =+IFERROR(VLOOKUP($A6,'[20]1'!$A$5:$E$1048576,3,0),0) | W6: =+IFERROR(VLOOKUP($A6,[21]Balance!$A$5:$E$1048576,3,0),0) | X6: =+IFERROR(VLOOKUP($A6,'[22]1'!$A$5:$E$1048576,3,0),0) | Y6: =+IFERROR(VLOOKUP($A6,[23]Лист1!$A$5:$E$1048576,3,0),0) | Z6: =+IFERROR(VLOOKUP($A6,'[24]1'!$A$5:$E$1048576,3,0),0) | AA6: =+IFERROR(VLOOKUP($A6,[25]Balance!$A$5:$E$1048576,3,0),0) | AB6: =+IFERROR(VLOOKUP($A6,'[26]1'!$A$5:$E$1048576,3,0),0) | AC6: =+IFERROR(VLOOKUP($A6,'[27]1'!$A$5:$E$1048576,3,0),0) | AD6: =+IFERROR(VLOOKUP($A6,'[28]1'!$A$5:$E$1048576,3,0),0) | AE6: =+IFERROR(VLOOKUP($A6,[29]Лист1!$A$5:$E$1048576,3,0),0) | AF6: =+IFERROR(VLOOKUP($A6,'[30]1'!$A$5:$E$1048576,3,0),0) | AG6: =+IFERROR(VLOOKUP($A6,'[31]1'!$A$5:$E$1048576,3,0),0) | AH6: =+IFERROR(VLOOKUP($A6,'[32]1-жадвал'!$A$5:$E$1048576,3,0),0) | AI6: =+IFERROR(VLOOKUP($A6,[33]Balance!$A$5:$E$1048576,3,0),0) | AJ6: =+IFERROR(VLOOKUP($A6,[34]Balance!$A$5:$E$1048576,3,0),0) | AK6: =+IFERROR(VLOOKUP($A6,'[35]1'!$A$5:$E$1048576,3,0),0)
A7: 3 | B7: Бошқа банклар ва молиявий ташкилотлардан олиниши лозим бўлган маблағлар, соф | C7: =+IFERROR(VLOOKUP($A7,[1]Лист1!$A$5:$E$1048576,3,0),0) | D7: =+IFERROR(VLOOKUP($A7,'[2]1'!$A$5:$E$1048576,3,0),0) | E7: =+IFERROR(VLOOKUP($A7,'[3]1'!$A$5:$E$1048576,3,0),0) | F7: =+IFERROR(VLOOKUP($A7,[4]Balance!$A$5:$E$1048576,3,0),0) | G7: =+IFERROR(VLOOKUP($A7,'[5]1'!$A$5:$E$1048576,3,0),0) | H7: =+IFERROR(VLOOKUP($A7,[6]Balance!$A$5:$E$1048576,3,0),0) | I7: =+IFERROR(VLOOKUP($A7,[7]Balance!$A$5:$E$1048576,3,0),0) | J7: =+IFERROR(VLOOKUP($A7,'[8]1'!$A$5:$E$1048576,3,0),0) | K7: =+IFERROR(VLOOKUP($A7,'[9]1'!$A$5:$E$1048576,3,0),0) | L7: =+IFERROR(VLOOKUP($A7,'[10]1'!$A$5:$E$1048576,3,0),0) | M7: =+IFERROR(VLOOKUP($A7,'[11]1'!$A$5:$E$1048576,3,0),0) | N7: =+IFERROR(VLOOKUP($A7,[12]Balance!$A$5:$E$1048576,3,0),0) | O7: =+IFERROR(VLOOKUP($A7,'[13]1 т'!$A$5:$E$1048576,3,0),0) | P7: =+IFERROR(VLOOKUP($A7,[14]Balance!$A$5:$E$1048576,3,0),0) | Q7: =+IFERROR(VLOOKUP($A7,[15]Balance!$A$5:$E$1048576,3,0),0) | R7: =+IFERROR(VLOOKUP($A7,'[16]1'!$A$5:$E$1048576,3,0),0) | S7: =+IFERROR(VLOOKUP($A7,'[17]1'!$A$5:$E$1048576,3,0),0) | T7: =+IFERROR(VLOOKUP($A7,'[18]1'!$A$5:$E$1048576,3,0),0) | U7: =+IFERROR(VLOOKUP($A7,[19]Balans!$A$5:$E$1048576,3,0),0) | V7: =+IFERROR(VLOOKUP($A7,'[20]1'!$A$5:$E$1048576,3,0),0) | W7: =+IFERROR(VLOOKUP($A7,[21]Balance!$A$5:$E$1048576,3,0),0) | X7: =+IFERROR(VLOOKUP($A7,'[22]1'!$A$5:$E$1048576,3,0),0) | Y7: =+IFERROR(VLOOKUP($A7,[23]Лист1!$A$5:$E$1048576,3,0),0) | Z7: =+IFERROR(VLOOKUP($A7,'[24]1'!$A$5:$E$1048576,3,0),0) | AA7: =+IFERROR(VLOOKUP($A7,[25]Balance!$A$5:$E$1048576,3,0),0) | AB7: =+IFERROR(VLOOKUP($A7,'[26]1'!$A$5:$E$1048576,3,0),0) | AC7: =+IFERROR(VLOOKUP($A7,'[27]1'!$A$5:$E$1048576,3,0),0) | AD7: =+IFERROR(VLOOKUP($A7,'[28]1'!$A$5:$E$1048576,3,0),0) | AE7: =+IFERROR(VLOOKUP($A7,[29]Лист1!$A$5:$E$1048576,3,0),0) | AF7: =+IFERROR(VLOOKUP($A7,'[30]1'!$A$5:$E$1048576,3,0),0) | AG7: =+IFERROR(VLOOKUP($A7,'[31]1'!$A$5:$E$1048576,3,0),0) | AH7: =+IFERROR(VLOOKUP($A7,'[32]1-жадвал'!$A$5:$E$1048576,3,0),0) | AI7: =+IFERROR(VLOOKUP($A7,[33]Balance!$A$5:$E$1048576,3,0),0) | AJ7: =+IFERROR(VLOOKUP($A7,[34]Balance!$A$5:$E$1048576,3,0),0) | AK7: =+IFERROR(VLOOKUP($A7,'[35]1'!$A$5:$E$1048576,3,0),0)
A8: 3.1 | B8: Бошқа банклар ва молиявий ташкилотлардан олиниши лозим бўлган маблағлар, брутто | C8: =+IFERROR(VLOOKUP($A8,[1]Лист1!$A$5:$E$1048576,3,0),0) | D8: =+IFERROR(VLOOKUP($A8,'[2]1'!$A$5:$E$1048576,3,0),0) | E8: =+IFERROR(VLOOKUP($A8,'[3]1'!$A$5:$E$1048576,3,0),0) | F8: =+IFERROR(VLOOKUP($A8,[4]Balance!$A$5:$E$1048576,3,0),0) | G8: =+IFERROR(VLOOKUP($A8,'[5]1'!$A$5:$E$1048576,3,0),0) | H8: =+IFERROR(VLOOKUP($A8,[6]Balance!$A$5:$E$1048576,3,0),0) | I8: =+IFERROR(VLOOKUP($A8,[7]Balance!$A$5:$E$1048576,3,0),0) | J8: =+IFERROR(VLOOKUP($A8,'[8]1'!$A$5:$E$1048576,3,0),0) | K8: =+IFERROR(VLOOKUP($A8,'[9]1'!$A$5:$E$1048576,3,0),0) | L8: =+IFERROR(VLOOKUP($A8,'[10]1'!$A$5:$E$1048576,3,0),0) | M8: =+IFERROR(VLOOKUP($A8,'[11]1'!$A$5:$E$1048576,3,0),0) | N8: =+IFERROR(VLOOKUP($A8,[12]Balance!$A$5:$E$1048576,3,0),0) | O8: =+IFERROR(VLOOKUP($A8,'[13]1 т'!$A$5:$E$1048576,3,0),0) | P8: =+IFERROR(VLOOKUP($A8,[14]Balance!$A$5:$E$1048576,3,0),0) | Q8: =+IFERROR(VLOOKUP($A8,[15]Balance!$A$5:$E$1048576,3,0),0) | R8: =+IFERROR(VLOOKUP($A8,'[16]1'!$A$5:$E$1048576,3,0),0) | S8: =+IFERROR(VLOOKUP($A8,'[17]1'!$A$5:$E$1048576,3,0),0) | T8: =+IFERROR(VLOOKUP($A8,'[18]1'!$A$5:$E$1048576,3,0),0) | U8: =+IFERROR(VLOOKUP($A8,[19]Balans!$A$5:$E$1048576,3,0),0) | V8: =+IFERROR(VLOOKUP($A8,'[20]1'!$A$5:$E$1048576,3,0),0) | W8: =+IFERROR(VLOOKUP($A8,[21]Balance!$A$5:$E$1048576,3,0),0) | X8: =+IFERROR(VLOOKUP($A8,'[22]1'!$A$5:$E$1048576,3,0),0) | Y8: =+IFERROR(VLOOKUP($A8,[23]Лист1!$A$5:$E$1048576,3,0),0) | Z8: =+IFERROR(VLOOKUP($A8,'[24]1'!$A$5:$E$1048576,3,0),0) | AA8: =+IFERROR(VLOOKUP($A8,[25]Balance!$A$5:$E$1048576,3,0),0) | AB8: =+IFERROR(VLOOKUP($A8,'[26]1'!$A$5:$E$1048576,3,0),0) | AC8: =+IFERROR(VLOOKUP($A8,'[27]1'!$A$5:$E$1048576,3,0),0) | AD8: =+IFERROR(VLOOKUP($A8,'[28]1'!$A$5:$E$1048576,3,0),0) | AE8: =+IFERROR(VLOOKUP($A8,[29]Лист1!$A$5:$E$1048576,3,0),0) | AF8: =+IFERROR(VLOOKUP($A8,'[30]1'!$A$5:$E$1048576,3,0),0) | AG8: =+IFERROR(VLOOKUP($A8,'[31]1'!$A$5:$E$1048576,3,0),0) | AH8: =+IFERROR(VLOOKUP($A8,'[32]1-жадвал'!$A$5:$E$1048576,3,0),0) | AI8: =+IFERROR(VLOOKUP($A8,[33]Balance!$A$5:$E$1048576,3,0),0) | AJ8: =+IFERROR(VLOOKUP($A8,[34]Balance!$A$5:$E$1048576,3,0),0) | AK8: =+IFERROR(VLOOKUP($A8,'[35]1'!$A$5:$E$1048576,3,0),0)
A9: 3.2 | B9: Минус: Кўрилиши мумкин бўлган зарарларни қоплаш захираси | C9: =+IFERROR(VLOOKUP($A9,[1]Лист1!$A$5:$E$1048576,3,0),0) | D9: =+IFERROR(VLOOKUP($A9,'[2]1'!$A$5:$E$1048576,3,0),0) | E9: =+IFERROR(VLOOKUP($A9,'[3]1'!$A$5:$E$1048576,3,0),0) | F9: =+IFERROR(VLOOKUP($A9,[4]Balance!$A$5:$E$1048576,3,0),0) | G9: =+IFERROR(VLOOKUP($A9,'[5]1'!$A$5:$E$1048576,3,0),0) | H9: =+IFERROR(VLOOKUP($A9,[6]Balance!$A$5:$E$1048576,3,0),0) | I9: =+IFERROR(VLOOKUP($A9,[7]Balance!$A$5:$E$1048576,3,0),0) | J9: =+IFERROR(VLOOKUP($A9,'[8]1'!$A$5:$E$1048576,3,0),0) | K9: =+IFERROR(VLOOKUP($A9,'[9]1'!$A$5:$E$1048576,3,0),0) | L9: =+IFERROR(VLOOKUP($A9,'[10]1'!$A$5:$E$1048576,3,0),0) | M9: =+IFERROR(VLOOKUP($A9,'[11]1'!$A$5:$E$1048576,3,0),0) | N9: =+IFERROR(VLOOKUP($A9,[12]Balance!$A$5:$E$1048576,3,0),0) | O9: =+IFERROR(VLOOKUP($A9,'[13]1 т'!$A$5:$E$1048576,3,0),0) | P9: =+IFERROR(VLOOKUP($A9,[14]Balance!$A$5:$E$1048576,3,0),0) | Q9: =+IFERROR(VLOOKUP($A9,[15]Balance!$A$5:$E$1048576,3,0),0) | R9: =+IFERROR(VLOOKUP($A9,'[16]1'!$A$5:$E$1048576,3,0),0) | S9: =+IFERROR(VLOOKUP($A9,'[17]1'!$A$5:$E$1048576,3,0),0) | T9: =+IFERROR(VLOOKUP($A9,'[18]1'!$A$5:$E$1048576,3,0),0) | U9: =+IFERROR(VLOOKUP($A9,[19]Balans!$A$5:$E$1048576,3,0),0) | V9: =+IFERROR(VLOOKUP($A9,'[20]1'!$A$5:$E$1048576,3,0),0) | W9: =+IFERROR(VLOOKUP($A9,[21]Balance!$A$5:$E$1048576,3,0),0) | X9: =+IFERROR(VLOOKUP($A9,'[22]1'!$A$5:$E$1048576,3,0),0) | Y9: =+IFERROR(VLOOKUP($A9,[23]Лист1!$A$5:$E$1048576,3,0),0) | Z9: =+IFERROR(VLOOKUP($A9,'[24]1'!$A$5:$E$1048576,3,0),0) | AA9: =+IFERROR(VLOOKUP($A9,[25]Balance!$A$5:$E$1048576,3,0),0) | AB9: =+IFERROR(VLOOKUP($A9,'[26]1'!$A$5:$E$1048576,3,0),0) | AC9: =+IFERROR(VLOOKUP($A9,'[27]1'!$A$5:$E$1048576,3,0),0) | AD9: =+IFERROR(VLOOKUP($A9,'[28]1'!$A$5:$E$1048576,3,0),0) | AE9: =+IFERROR(VLOOKUP($A9,[29]Лист1!$A$5:$E$1048576,3,0),0) | AF9: =+IFERROR(VLOOKUP($A9,'[30]1'!$A$5:$E$1048576,3,0),0) | AG9: =+IFERROR(VLOOKUP($A9,'[31]1'!$A$5:$E$1048576,3,0),0) | AH9: =+IFERROR(VLOOKUP($A9,'[32]1-жадвал'!$A$5:$E$1048576,3,0),0) | AI9: =+IFERROR(VLOOKUP($A9,[33]Balance!$A$5:$E$1048576,3,0),0) | AJ9: =+IFERROR(VLOOKUP($A9,[34]Balance!$A$5:$E$1048576,3,0),0) | AK9: =+IFERROR(VLOOKUP($A9,'[35]1'!$A$5:$E$1048576,3,0),0)
A10: 4 | B10: Қимматли қоғозлар ва уларга қилинган инвестициялар, соф | C10: =+IFERROR(VLOOKUP($A10,[1]Лист1!$A$5:$E$1048576,3,0),0) | D10: =+IFERROR(VLOOKUP($A10,'[2]1'!$A$5:$E$1048576,3,0),0) | E10: =+IFERROR(VLOOKUP($A10,'[3]1'!$A$5:$E$1048576,3,0),0) | F10: =+IFERROR(VLOOKUP($A10,[4]Balance!$A$5:$E$1048576,3,0),0) | G10: =+IFERROR(VLOOKUP($A10,'[5]1'!$A$5:$E$1048576,3,0),0) | H10: =+IFERROR(VLOOKUP($A10,[6]Balance!$A$5:$E$1048576,3,0),0) | I10: =+IFERROR(VLOOKUP($A10,[7]Balance!$A$5:$E$1048576,3,0),0) | J10: =+IFERROR(VLOOKUP($A10,'[8]1'!$A$5:$E$1048576,3,0),0) | K10: =+IFERROR(VLOOKUP($A10,'[9]1'!$A$5:$E$1048576,3,0),0) | L10: =+IFERROR(VLOOKUP($A10,'[10]1'!$A$5:$E$1048576,3,0),0) | M10: =+IFERROR(VLOOKUP($A10,'[11]1'!$A$5:$E$1048576,3,0),0) | N10: =+IFERROR(VLOOKUP($A10,[12]Balance!$A$5:$E$1048576,3,0),0) | O10: =+IFERROR(VLOOKUP($A10,'[13]1 т'!$A$5:$E$1048576,3,0),0) | P10: =+IFERROR(VLOOKUP($A10,[14]Balance!$A$5:$E$1048576,3,0),0) | Q10: =+IFERROR(VLOOKUP($A10,[15]Balance!$A$5:$E$1048576,3,0),0) | R10: =+IFERROR(VLOOKUP($A10,'[16]1'!$A$5:$E$1048576,3,0),0) | S10: =+IFERROR(VLOOKUP($A10,'[17]1'!$A$5:$E$1048576,3,0),0) | T10: =+IFERROR(VLOOKUP($A10,'[18]1'!$A$5:$E$1048576,3,0),0) | U10: =+IFERROR(VLOOKUP($A10,[19]Balans!$A$5:$E$1048576,3,0),0) | V10: =+IFERROR(VLOOKUP($A10,'[20]1'!$A$5:$E$1048576,3,0),0) | W10: =+IFERROR(VLOOKUP($A10,[21]Balance!$A$5:$E$1048576,3,0),0) | X10: =+IFERROR(VLOOKUP($A10,'[22]1'!$A$5:$E$1048576,3,0),0) | Y10: =+IFERROR(VLOOKUP($A10,[23]Лист1!$A$5:$E$1048576,3,0),0) | Z10: =+IFERROR(VLOOKUP($A10,'[24]1'!$A$5:$E$1048576,3,0),0) | AA10: =+IFERROR(VLOOKUP($A10,[25]Balance!$A$5:$E$1048576,3,0),0) | AB10: =+IFERROR(VLOOKUP($A10,'[26]1'!$A$5:$E$1048576,3,0),0) | AC10: =+IFERROR(VLOOKUP($A10,'[27]1'!$A$5:$E$1048576,3,0),0) | AD10: =+IFERROR(VLOOKUP($A10,'[28]1'!$A$5:$E$1048576,3,0),0) | AE10: =+IFERROR(VLOOKUP($A10,[29]Лист1!$A$5:$E$1048576,3,0),0) | AF10: =+IFERROR(VLOOKUP($A10,'[30]1'!$A$5:$E$1048576,3,0),0) | AG10: =+IFERROR(VLOOKUP($A10,'[31]1'!$A$5:$E$1048576,3,0),0) | AH10: =+IFERROR(VLOOKUP($A10,'[32]1-жадвал'!$A$5:$E$1048576,3,0),0) | AI10: =+IFERROR(VLOOKUP($A10,[33]Balance!$A$5:$E$1048576,3,0),0) | AJ10: =+IFERROR(VLOOKUP($A10,[34]Balance!$A$5:$E$1048576,3,0),0) | AK10: =+IFERROR(VLOOKUP($A10,'[35]1'!$A$5:$E$1048576,3,0),0)
A11: 4.1 | B11: Қимматли қоғозлар ва уларга қилинган инвестициялар, брутто | C11: =+IFERROR(VLOOKUP($A11,[1]Лист1!$A$5:$E$1048576,3,0),0) | D11: =+IFERROR(VLOOKUP($A11,'[2]1'!$A$5:$E$1048576,3,0),0) | E11: =+IFERROR(VLOOKUP($A11,'[3]1'!$A$5:$E$1048576,3,0),0) | F11: =+IFERROR(VLOOKUP($A11,[4]Balance!$A$5:$E$1048576,3,0),0) | G11: =+IFERROR(VLOOKUP($A11,'[5]1'!$A$5:$E$1048576,3,0),0) | H11: =+IFERROR(VLOOKUP($A11,[6]Balance!$A$5:$E$1048576,3,0),0) | I11: =+IFERROR(VLOOKUP($A11,[7]Balance!$A$5:$E$1048576,3,0),0) | J11: =+IFERROR(VLOOKUP($A11,'[8]1'!$A$5:$E$1048576,3,0),0) | K11: =+IFERROR(VLOOKUP($A11,'[9]1'!$A$5:$E$1048576,3,0),0) | L11: =+IFERROR(VLOOKUP($A11,'[10]1'!$A$5:$E$1048576,3,0),0) | M11: =+IFERROR(VLOOKUP($A11,'[11]1'!$A$5:$E$1048576,3,0),0) | N11: =+IFERROR(VLOOKUP($A11,[12]Balance!$A$5:$E$1048576,3,0),0) | O11: =+IFERROR(VLOOKUP($A11,'[13]1 т'!$A$5:$E$1048576,3,0),0) | P11: =+IFERROR(VLOOKUP($A11,[14]Balance!$A$5:$E$1048576,3,0),0) | Q11: =+IFERROR(VLOOKUP($A11,[15]Balance!$A$5:$E$1048576,3,0),0) | R11: =+IFERROR(VLOOKUP($A11,'[16]1'!$A$5:$E$1048576,3,0),0) | S11: =+IFERROR(VLOOKUP($A11,'[17]1'!$A$5:$E$1048576,3,0),0) | T11: =+IFERROR(VLOOKUP($A11,'[18]1'!$A$5:$E$1048576,3,0),0) | U11: =+IFERROR(VLOOKUP($A11,[19]Balans!$A$5:$E$1048576,3,0),0) | V11: =+IFERROR(VLOOKUP($A11,'[20]1'!$A$5:$E$1048576,3,0),0) | W11: =+IFERROR(VLOOKUP($A11,[21]Balance!$A$5:$E$1048576,3,0),0) | X11: =+IFERROR(VLOOKUP($A11,'[22]1'!$A$5:$E$1048576,3,0),0) | Y11: =+IFERROR(VLOOKUP($A11,[23]Лист1!$A$5:$E$1048576,3,0),0) | Z11: =+IFERROR(VLOOKUP($A11,'[24]1'!$A$5:$E$1048576,3,0),0) | AA11: =+IFERROR(VLOOKUP($A11,[25]Balance!$A$5:$E$1048576,3,0),0) | AB11: =+IFERROR(VLOOKUP($A11,'[26]1'!$A$5:$E$1048576,3,0),0) | AC11: =+IFERROR(VLOOKUP($A11,'[27]1'!$A$5:$E$1048576,3,0),0) | AD11: =+IFERROR(VLOOKUP($A11,'[28]1'!$A$5:$E$1048576,3,0),0) | AE11: =+IFERROR(VLOOKUP($A11,[29]Лист1!$A$5:$E$1048576,3,0),0) | AF11: =+IFERROR(VLOOKUP($A11,'[30]1'!$A$5:$E$1048576,3,0),0) | AG11: =+IFERROR(VLOOKUP($A11,'[31]1'!$A$5:$E$1048576,3,0),0) | AH11: =+IFERROR(VLOOKUP($A11,'[32]1-жадвал'!$A$5:$E$1048576,3,0),0) | AI11: =+IFERROR(VLOOKUP($A11,[33]Balance!$A$5:$E$1048576,3,0),0) | AJ11: =+IFERROR(VLOOKUP($A11,[34]Balance!$A$5:$E$1048576,3,0),0) | AK11: =+IFERROR(VLOOKUP($A11,'[35]1'!$A$5:$E$1048576,3,0),0)
A12: 4.2 | B12: Қимматли қоғозлар бўйича харажатлар, дисконт, мукофот ва уларнинг ҳаққоний қийматининг ўзгариши | C12: =+IFERROR(VLOOKUP($A12,[1]Лист1!$A$5:$E$1048576,3,0),0) | D12: =+IFERROR(VLOOKUP($A12,'[2]1'!$A$5:$E$1048576,3,0),0) | E12: =+IFERROR(VLOOKUP($A12,'[3]1'!$A$5:$E$1048576,3,0),0) | F12: =+IFERROR(VLOOKUP($A12,[4]Balance!$A$5:$E$1048576,3,0),0) | G12: =+IFERROR(VLOOKUP($A12,'[5]1'!$A$5:$E$1048576,3,0),0) | H12: =+IFERROR(VLOOKUP($A12,[6]Balance!$A$5:$E$1048576,3,0),0) | I12: =+IFERROR(VLOOKUP($A12,[7]Balance!$A$5:$E$1048576,3,0),0) | J12: =+IFERROR(VLOOKUP($A12,'[8]1'!$A$5:$E$1048576,3,0),0) | K12: =+IFERROR(VLOOKUP($A12,'[9]1'!$A$5:$E$1048576,3,0),0) | L12: =+IFERROR(VLOOKUP($A12,'[10]1'!$A$5:$E$1048576,3,0),0) | M12: =+IFERROR(VLOOKUP($A12,'[11]1'!$A$5:$E$1048576,3,0),0) | N12: =+IFERROR(VLOOKUP($A12,[12]Balance!$A$5:$E$1048576,3,0),0) | O12: =+IFERROR(VLOOKUP($A12,'[13]1 т'!$A$5:$E$1048576,3,0),0) | P12: =+IFERROR(VLOOKUP($A12,[14]Balance!$A$5:$E$1048576,3,0),0) | Q12: =+IFERROR(VLOOKUP($A12,[15]Balance!$A$5:$E$1048576,3,0),0) | R12: =+IFERROR(VLOOKUP($A12,'[16]1'!$A$5:$E$1048576,3,0),0) | S12: =+IFERROR(VLOOKUP($A12,'[17]1'!$A$5:$E$1048576,3,0),0) | T12: =+IFERROR(VLOOKUP($A12,'[18]1'!$A$5:$E$1048576,3,0),0) | U12: =+IFERROR(VLOOKUP($A12,[19]Balans!$A$5:$E$1048576,3,0),0) | V12: =+IFERROR(VLOOKUP($A12,'[20]1'!$A$5:$E$1048576,3,0),0) | W12: =+IFERROR(VLOOKUP($A12,[21]Balance!$A$5:$E$1048576,3,0),0) | X12: =+IFERROR(VLOOKUP($A12,'[22]1'!$A$5:$E$1048576,3,0),0) | Y12: =+IFERROR(VLOOKUP($A12,[23]Лист1!$A$5:$E$1048576,3,0),0) | Z12: =+IFERROR(VLOOKUP($A12,'[24]1'!$A$5:$E$1048576,3,0),0) | AA12: =+IFERROR(VLOOKUP($A12,[25]Balance!$A$5:$E$1048576,3,0),0) | AB12: =+IFERROR(VLOOKUP($A12,'[26]1'!$A$5:$E$1048576,3,0),0) | AC12: =+IFERROR(VLOOKUP($A12,'[27]1'!$A$5:$E$1048576,3,0),0) | AD12: =+IFERROR(VLOOKUP($A12,'[28]1'!$A$5:$E$1048576,3,0),0) | AE12: =+IFERROR(VLOOKUP($A12,[29]Лист1!$A$5:$E$1048576,3,0),0) | AF12: =+IFERROR(VLOOKUP($A12,'[30]1'!$A$5:$E$1048576,3,0),0) | AG12: =+IFERROR(VLOOKUP($A12,'[31]1'!$A$5:$E$1048576,3,0),0) | AH12: =+IFERROR(VLOOKUP($A12,'[32]1-жадвал'!$A$5:$E$1048576,3,0),0) | AI12: =+IFERROR(VLOOKUP($A12,[33]Balance!$A$5:$E$1048576,3,0),0) | AJ12: =+IFERROR(VLOOKUP($A12,[34]Balance!$A$5:$E$1048576,3,0),0) | AK12: =+IFERROR(VLOOKUP($A12,'[35]1'!$A$5:$E$1048576,3,0),0)
A13: 4.3 | B13: Минус: Кўрилиши мумкин бўлган зарарларни қоплаш захираси | C13: =+IFERROR(VLOOKUP($A13,[1]Лист1!$A$5:$E$1048576,3,0),0) | D13: =+IFERROR(VLOOKUP($A13,'[2]1'!$A$5:$E$1048576,3,0),0) | E13: =+IFERROR(VLOOKUP($A13,'[3]1'!$A$5:$E$1048576,3,0),0) | F13: =+IFERROR(VLOOKUP($A13,[4]Balance!$A$5:$E$1048576,3,0),0) | G13: =+IFERROR(VLOOKUP($A13,'[5]1'!$A$5:$E$1048576,3,0),0) | H13: =+IFERROR(VLOOKUP($A13,[6]Balance!$A$5:$E$1048576,3,0),0) | I13: =+IFERROR(VLOOKUP($A13,[7]Balance!$A$5:$E$1048576,3,0),0) | J13: =+IFERROR(VLOOKUP($A13,'[8]1'!$A$5:$E$1048576,3,0),0) | K13: =+IFERROR(VLOOKUP($A13,'[9]1'!$A$5:$E$1048576,3,0),0) | L13: =+IFERROR(VLOOKUP($A13,'[10]1'!$A$5:$E$1048576,3,0),0) | M13: =+IFERROR(VLOOKUP($A13,'[11]1'!$A$5:$E$1048576,3,0),0) | N13: =+IFERROR(VLOOKUP($A13,[12]Balance!$A$5:$E$1048576,3,0),0) | O13: =+IFERROR(VLOOKUP($A13,'[13]1 т'!$A$5:$E$1048576,3,0),0) | P13: =+IFERROR(VLOOKUP($A13,[14]Balance!$A$5:$E$1048576,3,0),0) | Q13: =+IFERROR(VLOOKUP($A13,[15]Balance!$A$5:$E$1048576,3,0),0) | R13: =+IFERROR(VLOOKUP($A13,'[16]1'!$A$5:$E$1048576,3,0),0) | S13: =+IFERROR(VLOOKUP($A13,'[17]1'!$A$5:$E$1048576,3,0),0) | T13: =+IFERROR(VLOOKUP($A13,'[18]1'!$A$5:$E$1048576,3,0),0) | U13: =+IFERROR(VLOOKUP($A13,[19]Balans!$A$5:$E$1048576,3,0),0) | V13: =+IFERROR(VLOOKUP($A13,'[20]1'!$A$5:$E$1048576,3,0),0) | W13: =+IFERROR(VLOOKUP($A13,[21]Balance!$A$5:$E$1048576,3,0),0) | X13: =+IFERROR(VLOOKUP($A13,'[22]1'!$A$5:$E$1048576,3,0),0) | Y13: =+IFERROR(VLOOKUP($A13,[23]Лист1!$A$5:$E$1048576,3,0),0) | Z13: =+IFERROR(VLOOKUP($A13,'[24]1'!$A$5:$E$1048576,3,0),0) | AA13: =+IFERROR(VLOOKUP($A13,[25]Balance!$A$5:$E$1048576,3,0),0) | AB13: =+IFERROR(VLOOKUP($A13,'[26]1'!$A$5:$E$1048576,3,0),0) | AC13: =+IFERROR(VLOOKUP($A13,'[27]1'!$A$5:$E$1048576,3,0),0) | AD13: =+IFERROR(VLOOKUP($A13,'[28]1'!$A$5:$E$1048576,3,0),0) | AE13: =+IFERROR(VLOOKUP($A13,[29]Лист1!$A$5:$E$1048576,3,0),0) | AF13: =+IFERROR(VLOOKUP($A13,'[30]1'!$A$5:$E$1048576,3,0),0) | AG13: =+IFERROR(VLOOKUP($A13,'[31]1'!$A$5:$E$1048576,3,0),0) | AH13: =+IFERROR(VLOOKUP($A13,'[32]1-жадвал'!$A$5:$E$1048576,3,0),0) | AI13: =+IFERROR(VLOOKUP($A13,[33]Balance!$A$5:$E$1048576,3,0),0) | AJ13: =+IFERROR(VLOOKUP($A13,[34]Balance!$A$5:$E$1048576,3,0),0) | AK13: =+IFERROR(VLOOKUP($A13,'[35]1'!$A$5:$E$1048576,3,0),0)
A14: 5 | B14: Қимматбаҳо металлар, тошлар ва тангалар, соф | C14: =+IFERROR(VLOOKUP($A14,[1]Лист1!$A$5:$E$1048576,3,0),0) | D14: =+IFERROR(VLOOKUP($A14,'[2]1'!$A$5:$E$1048576,3,0),0) | E14: =+IFERROR(VLOOKUP($A14,'[3]1'!$A$5:$E$1048576,3,0),0) | F14: =+IFERROR(VLOOKUP($A14,[4]Balance!$A$5:$E$1048576,3,0),0) | G14: =+IFERROR(VLOOKUP($A14,'[5]1'!$A$5:$E$1048576,3,0),0) | H14: =+IFERROR(VLOOKUP($A14,[6]Balance!$A$5:$E$1048576,3,0),0) | I14: =+IFERROR(VLOOKUP($A14,[7]Balance!$A$5:$E$1048576,3,0),0) | J14: =+IFERROR(VLOOKUP($A14,'[8]1'!$A$5:$E$1048576,3,0),0) | K14: =+IFERROR(VLOOKUP($A14,'[9]1'!$A$5:$E$1048576,3,0),0) | L14: =+IFERROR(VLOOKUP($A14,'[10]1'!$A$5:$E$1048576,3,0),0) | M14: =+IFERROR(VLOOKUP($A14,'[11]1'!$A$5:$E$1048576,3,0),0) | N14: =+IFERROR(VLOOKUP($A14,[12]Balance!$A$5:$E$1048576,3,0),0) | O14: =+IFERROR(VLOOKUP($A14,'[13]1 т'!$A$5:$E$1048576,3,0),0) | P14: =+IFERROR(VLOOKUP($A14,[14]Balance!$A$5:$E$1048576,3,0),0) | Q14: =+IFERROR(VLOOKUP($A14,[15]Balance!$A$5:$E$1048576,3,0),0) | R14: =+IFERROR(VLOOKUP($A14,'[16]1'!$A$5:$E$1048576,3,0),0) | S14: =+IFERROR(VLOOKUP($A14,'[17]1'!$A$5:$E$1048576,3,0),0) | T14: =+IFERROR(VLOOKUP($A14,'[18]1'!$A$5:$E$1048576,3,0),0) | U14: =+IFERROR(VLOOKUP($A14,[19]Balans!$A$5:$E$1048576,3,0),0) | V14: =+IFERROR(VLOOKUP($A14,'[20]1'!$A$5:$E$1048576,3,0),0) | W14: =+IFERROR(VLOOKUP($A14,[21]Balance!$A$5:$E$1048576,3,0),0) | X14: =+IFERROR(VLOOKUP($A14,'[22]1'!$A$5:$E$1048576,3,0),0) | Y14: =+IFERROR(VLOOKUP($A14,[23]Лист1!$A$5:$E$1048576,3,0),0) | Z14: =+IFERROR(VLOOKUP($A14,'[24]1'!$A$5:$E$1048576,3,0),0) | AA14: =+IFERROR(VLOOKUP($A14,[25]Balance!$A$5:$E$1048576,3,0),0) | AB14: =+IFERROR(VLOOKUP($A14,'[26]1'!$A$5:$E$1048576,3,0),0) | AC14: =+IFERROR(VLOOKUP($A14,'[27]1'!$A$5:$E$1048576,3,0),0) | AD14: =+IFERROR(VLOOKUP($A14,'[28]1'!$A$5:$E$1048576,3,0),0) | AE14: =+IFERROR(VLOOKUP($A14,[29]Лист1!$A$5:$E$1048576,3,0),0) | AF14: =+IFERROR(VLOOKUP($A14,'[30]1'!$A$5:$E$1048576,3,0),0) | AG14: =+IFERROR(VLOOKUP($A14,'[31]1'!$A$5:$E$1048576,3,0),0) | AH14: =+IFERROR(VLOOKUP($A14,'[32]1-жадвал'!$A$5:$E$1048576,3,0),0) | AI14: =+IFERROR(VLOOKUP($A14,[33]Balance!$A$5:$E$1048576,3,0),0) | AJ14: =+IFERROR(VLOOKUP($A14,[34]Balance!$A$5:$E$1048576,3,0),0) | AK14: =+IFERROR(VLOOKUP($A14,'[35]1'!$A$5:$E$1048576,3,0),0)
A15: 5.1 | B15: Қимматбаҳо металлар, тошлар ва тангалар, брутто | C15: =+IFERROR(VLOOKUP($A15,[1]Лист1!$A$5:$E$1048576,3,0),0) | D15: =+IFERROR(VLOOKUP($A15,'[2]1'!$A$5:$E$1048576,3,0),0) | E15: =+IFERROR(VLOOKUP($A15,'[3]1'!$A$5:$E$1048576,3,0),0) | F15: =+IFERROR(VLOOKUP($A15,[4]Balance!$A$5:$E$1048576,3,0),0) | G15: =+IFERROR(VLOOKUP($A15,'[5]1'!$A$5:$E$1048576,3,0),0) | H15: =+IFERROR(VLOOKUP($A15,[6]Balance!$A$5:$E$1048576,3,0),0) | I15: =+IFERROR(VLOOKUP($A15,[7]Balance!$A$5:$E$1048576,3,0),0) | J15: =+IFERROR(VLOOKUP($A15,'[8]1'!$A$5:$E$1048576,3,0),0) | K15: =+IFERROR(VLOOKUP($A15,'[9]1'!$A$5:$E$1048576,3,0),0) | L15: =+IFERROR(VLOOKUP($A15,'[10]1'!$A$5:$E$1048576,3,0),0) | M15: =+IFERROR(VLOOKUP($A15,'[11]1'!$A$5:$E$1048576,3,0),0) | N15: =+IFERROR(VLOOKUP($A15,[12]Balance!$A$5:$E$1048576,3,0),0) | O15: =+IFERROR(VLOOKUP($A15,'[13]1 т'!$A$5:$E$1048576,3,0),0) | P15: =+IFERROR(VLOOKUP($A15,[14]Balance!$A$5:$E$1048576,3,0),0) | Q15: =+IFERROR(VLOOKUP($A15,[15]Balance!$A$5:$E$1048576,3,0),0) | R15: =+IFERROR(VLOOKUP($A15,'[16]1'!$A$5:$E$1048576,3,0),0) | S15: =+IFERROR(VLOOKUP($A15,'[17]1'!$A$5:$E$1048576,3,0),0) | T15: =+IFERROR(VLOOKUP($A15,'[18]1'!$A$5:$E$1048576,3,0),0) | U15: =+IFERROR(VLOOKUP($A15,[19]Balans!$A$5:$E$1048576,3,0),0) | V15: =+IFERROR(VLOOKUP($A15,'[20]1'!$A$5:$E$1048576,3,0),0) | W15: =+IFERROR(VLOOKUP($A15,[21]Balance!$A$5:$E$1048576,3,0),0) | X15: =+IFERROR(VLOOKUP($A15,'[22]1'!$A$5:$E$1048576,3,0),0) | Y15: =+IFERROR(VLOOKUP($A15,[23]Лист1!$A$5:$E$1048576,3,0),0) | Z15: =+IFERROR(VLOOKUP($A15,'[24]1'!$A$5:$E$1048576,3,0),0) | AA15: =+IFERROR(VLOOKUP($A15,[25]Balance!$A$5:$E$1048576,3,0),0) | AB15: =+IFERROR(VLOOKUP($A15,'[26]1'!$A$5:$E$1048576,3,0),0) | AC15: =+IFERROR(VLOOKUP($A15,'[27]1'!$A$5:$E$1048576,3,0),0) | AD15: =+IFERROR(VLOOKUP($A15,'[28]1'!$A$5:$E$1048576,3,0),0) | AE15: =+IFERROR(VLOOKUP($A15,[29]Лист1!$A$5:$E$1048576,3,0),0) | AF15: =+IFERROR(VLOOKUP($A15,'[30]1'!$A$5:$E$1048576,3,0),0) | AG15: =+IFERROR(VLOOKUP($A15,'[31]1'!$A$5:$E$1048576,3,0),0) | AH15: =+IFERROR(VLOOKUP($A15,'[32]1-жадвал'!$A$5:$E$1048576,3,0),0) | AI15: =+IFERROR(VLOOKUP($A15,[33]Balance!$A$5:$E$1048576,3,0),0) | AJ15: =+IFERROR(VLOOKUP($A15,[34]Balance!$A$5:$E$1048576,3,0),0) | AK15: =+IFERROR(VLOOKUP($A15,'[35]1'!$A$5:$E$1048576,3,0),0)
A16: 5.2 | B16: Минус: Кўрилиши мумкин бўлган зарарларни қоплаш захираси | C16: =+IFERROR(VLOOKUP($A16,[1]Лист1!$A$5:$E$1048576,3,0),0) | D16: =+IFERROR(VLOOKUP($A16,'[2]1'!$A$5:$E$1048576,3,0),0) | E16: =+IFERROR(VLOOKUP($A16,'[3]1'!$A$5:$E$1048576,3,0),0) | F16: =+IFERROR(VLOOKUP($A16,[4]Balance!$A$5:$E$1048576,3,0),0) | G16: =+IFERROR(VLOOKUP($A16,'[5]1'!$A$5:$E$1048576,3,0),0) | H16: =+IFERROR(VLOOKUP($A16,[6]Balance!$A$5:$E$1048576,3,0),0) | I16: =+IFERROR(VLOOKUP($A16,[7]Balance!$A$5:$E$1048576,3,0),0) | J16: =+IFERROR(VLOOKUP($A16,'[8]1'!$A$5:$E$1048576,3,0),0) | K16: =+IFERROR(VLOOKUP($A16,'[9]1'!$A$5:$E$1048576,3,0),0) | L16: =+IFERROR(VLOOKUP($A16,'[10]1'!$A$5:$E$1048576,3,0),0) | M16: =+IFERROR(VLOOKUP($A16,'[11]1'!$A$5:$E$1048576,3,0),0) | N16: =+IFERROR(VLOOKUP($A16,[12]Balance!$A$5:$E$1048576,3,0),0) | O16: =+IFERROR(VLOOKUP($A16,'[13]1 т'!$A$5:$E$1048576,3,0),0) | P16: =+IFERROR(VLOOKUP($A16,[14]Balance!$A$5:$E$1048576,3,0),0) | Q16: =+IFERROR(VLOOKUP($A16,[15]Balance!$A$5:$E$1048576,3,0),0) | R16: =+IFERROR(VLOOKUP($A16,'[16]1'!$A$5:$E$1048576,3,0),0) | S16: =+IFERROR(VLOOKUP($A16,'[17]1'!$A$5:$E$1048576,3,0),0) | T16: =+IFERROR(VLOOKUP($A16,'[18]1'!$A$5:$E$1048576,3,0),0) | U16: =+IFERROR(VLOOKUP($A16,[19]Balans!$A$5:$E$1048576,3,0),0) | V16: =+IFERROR(VLOOKUP($A16,'[20]1'!$A$5:$E$1048576,3,0),0) | W16: =+IFERROR(VLOOKUP($A16,[21]Balance!$A$5:$E$1048576,3,0),0) | X16: =+IFERROR(VLOOKUP($A16,'[22]1'!$A$5:$E$1048576,3,0),0) | Y16: =+IFERROR(VLOOKUP($A16,[23]Лист1!$A$5:$E$1048576,3,0),0) | Z16: =+IFERROR(VLOOKUP($A16,'[24]1'!$A$5:$E$1048576,3,0),0) | AA16: =+IFERROR(VLOOKUP($A16,[25]Balance!$A$5:$E$1048576,3,0),0) | AB16: =+IFERROR(VLOOKUP($A16,'[26]1'!$A$5:$E$1048576,3,0),0) | AC16: =+IFERROR(VLOOKUP($A16,'[27]1'!$A$5:$E$1048576,3,0),0) | AD16: =+IFERROR(VLOOKUP($A16,'[28]1'!$A$5:$E$1048576,3,0),0) | AE16: =+IFERROR(VLOOKUP($A16,[29]Лист1!$A$5:$E$1048576,3,0),0) | AF16: =+IFERROR(VLOOKUP($A16,'[30]1'!$A$5:$E$1048576,3,0),0) | AG16: =+IFERROR(VLOOKUP($A16,'[31]1'!$A$5:$E$1048576,3,0),0) | AH16: =+IFERROR(VLOOKUP($A16,'[32]1-жадвал'!$A$5:$E$1048576,3,0),0) | AI16: =+IFERROR(VLOOKUP($A16,[33]Balance!$A$5:$E$1048576,3,0),0) | AJ16: =+IFERROR(VLOOKUP($A16,[34]Balance!$A$5:$E$1048576,3,0),0) | AK16: =+IFERROR(VLOOKUP($A16,'[35]1'!$A$5:$E$1048576,3,0),0)
A17: 6 | B17: Инвестициялар, соф | C17: =+IFERROR(VLOOKUP($A17,[1]Лист1!$A$5:$E$1048576,3,0),0) | D17: =+IFERROR(VLOOKUP($A17,'[2]1'!$A$5:$E$1048576,3,0),0) | E17: =+IFERROR(VLOOKUP($A17,'[3]1'!$A$5:$E$1048576,3,0),0) | F17: =+IFERROR(VLOOKUP($A17,[4]Balance!$A$5:$E$1048576,3,0),0) | G17: =+IFERROR(VLOOKUP($A17,'[5]1'!$A$5:$E$1048576,3,0),0) | H17: =+IFERROR(VLOOKUP($A17,[6]Balance!$A$5:$E$1048576,3,0),0) | I17: =+IFERROR(VLOOKUP($A17,[7]Balance!$A$5:$E$1048576,3,0),0) | J17: =+IFERROR(VLOOKUP($A17,'[8]1'!$A$5:$E$1048576,3,0),0) | K17: =+IFERROR(VLOOKUP($A17,'[9]1'!$A$5:$E$1048576,3,0),0) | L17: =+IFERROR(VLOOKUP($A17,'[10]1'!$A$5:$E$1048576,3,0),0) | M17: =+IFERROR(VLOOKUP($A17,'[11]1'!$A$5:$E$1048576,3,0),0) | N17: =+IFERROR(VLOOKUP($A17,[12]Balance!$A$5:$E$1048576,3,0),0) | O17: =+IFERROR(VLOOKUP($A17,'[13]1 т'!$A$5:$E$1048576,3,0),0) | P17: =+IFERROR(VLOOKUP($A17,[14]Balance!$A$5:$E$1048576,3,0),0) | Q17: =+IFERROR(VLOOKUP($A17,[15]Balance!$A$5:$E$1048576,3,0),0) | R17: =+IFERROR(VLOOKUP($A17,'[16]1'!$A$5:$E$1048576,3,0),0) | S17: =+IFERROR(VLOOKUP($A17,'[17]1'!$A$5:$E$1048576,3,0),0) | T17: =+IFERROR(VLOOKUP($A17,'[18]1'!$A$5:$E$1048576,3,0),0) | U17: =+IFERROR(VLOOKUP($A17,[19]Balans!$A$5:$E$1048576,3,0),0) | V17: =+IFERROR(VLOOKUP($A17,'[20]1'!$A$5:$E$1048576,3,0),0) | W17: =+IFERROR(VLOOKUP($A17,[21]Balance!$A$5:$E$1048576,3,0),0) | X17: =+IFERROR(VLOOKUP($A17,'[22]1'!$A$5:$E$1048576,3,0),0) | Y17: =+IFERROR(VLOOKUP($A17,[23]Лист1!$A$5:$E$1048576,3,0),0) | Z17: =+IFERROR(VLOOKUP($A17,'[24]1'!$A$5:$E$1048576,3,0),0) | AA17: =+IFERROR(VLOOKUP($A17,[25]Balance!$A$5:$E$1048576,3,0),0) | AB17: =+IFERROR(VLOOKUP($A17,'[26]1'!$A$5:$E$1048576,3,0),0) | AC17: =+IFERROR(VLOOKUP($A17,'[27]1'!$A$5:$E$1048576,3,0),0) | AD17: =+IFERROR(VLOOKUP($A17,'[28]1'!$A$5:$E$1048576,3,0),0) | AE17: =+IFERROR(VLOOKUP($A17,[29]Лист1!$A$5:$E$1048576,3,0),0) | AF17: =+IFERROR(VLOOKUP($A17,'[30]1'!$A$5:$E$1048576,3,0),0) | AG17: =+IFERROR(VLOOKUP($A17,'[31]1'!$A$5:$E$1048576,3,0),0) | AH17: =+IFERROR(VLOOKUP($A17,'[32]1-жадвал'!$A$5:$E$1048576,3,0),0) | AI17: =+IFERROR(VLOOKUP($A17,[33]Balance!$A$5:$E$1048576,3,0),0) | AJ17: =+IFERROR(VLOOKUP($A17,[34]Balance!$A$5:$E$1048576,3,0),0) | AK17: =+IFERROR(VLOOKUP($A17,'[35]1'!$A$5:$E$1048576,3,0),0)
A18: 6.1 | B18: Инвестициялар, брутто | C18: =+IFERROR(VLOOKUP($A18,[1]Лист1!$A$5:$E$1048576,3,0),0) | D18: =+IFERROR(VLOOKUP($A18,'[2]1'!$A$5:$E$1048576,3,0),0) | E18: =+IFERROR(VLOOKUP($A18,'[3]1'!$A$5:$E$1048576,3,0),0) | F18: =+IFERROR(VLOOKUP($A18,[4]Balance!$A$5:$E$1048576,3,0),0) | G18: =+IFERROR(VLOOKUP($A18,'[5]1'!$A$5:$E$1048576,3,0),0) | H18: =+IFERROR(VLOOKUP($A18,[6]Balance!$A$5:$E$1048576,3,0),0) | I18: =+IFERROR(VLOOKUP($A18,[7]Balance!$A$5:$E$1048576,3,0),0) | J18: =+IFERROR(VLOOKUP($A18,'[8]1'!$A$5:$E$1048576,3,0),0) | K18: =+IFERROR(VLOOKUP($A18,'[9]1'!$A$5:$E$1048576,3,0),0) | L18: =+IFERROR(VLOOKUP($A18,'[10]1'!$A$5:$E$1048576,3,0),0) | M18: =+IFERROR(VLOOKUP($A18,'[11]1'!$A$5:$E$1048576,3,0),0) | N18: =+IFERROR(VLOOKUP($A18,[12]Balance!$A$5:$E$1048576,3,0),0) | O18: =+IFERROR(VLOOKUP($A18,'[13]1 т'!$A$5:$E$1048576,3,0),0) | P18: =+IFERROR(VLOOKUP($A18,[14]Balance!$A$5:$E$1048576,3,0),0) | Q18: =+IFERROR(VLOOKUP($A18,[15]Balance!$A$5:$E$1048576,3,0),0) | R18: =+IFERROR(VLOOKUP($A18,'[16]1'!$A$5:$E$1048576,3,0),0) | S18: =+IFERROR(VLOOKUP($A18,'[17]1'!$A$5:$E$1048576,3,0),0) | T18: =+IFERROR(VLOOKUP($A18,'[18]1'!$A$5:$E$1048576,3,0),0) | U18: =+IFERROR(VLOOKUP($A18,[19]Balans!$A$5:$E$1048576,3,0),0) | V18: =+IFERROR(VLOOKUP($A18,'[20]1'!$A$5:$E$1048576,3,0),0) | W18: =+IFERROR(VLOOKUP($A18,[21]Balance!$A$5:$E$1048576,3,0),0) | X18: =+IFERROR(VLOOKUP($A18,'[22]1'!$A$5:$E$1048576,3,0),0) | Y18: =+IFERROR(VLOOKUP($A18,[23]Лист1!$A$5:$E$1048576,3,0),0) | Z18: =+IFERROR(VLOOKUP($A18,'[24]1'!$A$5:$E$1048576,3,0),0) | AA18: =+IFERROR(VLOOKUP($A18,[25]Balance!$A$5:$E$1048576,3,0),0) | AB18: =+IFERROR(VLOOKUP($A18,'[26]1'!$A$5:$E$1048576,3,0),0) | AC18: =+IFERROR(VLOOKUP($A18,'[27]1'!$A$5:$E$1048576,3,0),0) | AD18: =+IFERROR(VLOOKUP($A18,'[28]1'!$A$5:$E$1048576,3,0),0) | AE18: =+IFERROR(VLOOKUP($A18,[29]Лист1!$A$5:$E$1048576,3,0),0) | AF18: =+IFERROR(VLOOKUP($A18,'[30]1'!$A$5:$E$1048576,3,0),0) | AG18: =+IFERROR(VLOOKUP($A18,'[31]1'!$A$5:$E$1048576,3,0),0) | AH18: =+IFERROR(VLOOKUP($A18,'[32]1-жадвал'!$A$5:$E$1048576,3,0),0) | AI18: =+IFERROR(VLOOKUP($A18,[33]Balance!$A$5:$E$1048576,3,0),0) | AJ18: =+IFERROR(VLOOKUP($A18,[34]Balance!$A$5:$E$1048576,3,0),0) | AK18: =+IFERROR(VLOOKUP($A18,'[35]1'!$A$5:$E$1048576,3,0),0)
A19: 6.2 | B19: Инвестициялар бўйича харажатлар, дисконт ва мукофот | C19: =+IFERROR(VLOOKUP($A19,[1]Лист1!$A$5:$E$1048576,3,0),0) | D19: =+IFERROR(VLOOKUP($A19,'[2]1'!$A$5:$E$1048576,3,0),0) | E19: =+IFERROR(VLOOKUP($A19,'[3]1'!$A$5:$E$1048576,3,0),0) | F19: =+IFERROR(VLOOKUP($A19,[4]Balance!$A$5:$E$1048576,3,0),0) | G19: =+IFERROR(VLOOKUP($A19,'[5]1'!$A$5:$E$1048576,3,0),0) | H19: =+IFERROR(VLOOKUP($A19,[6]Balance!$A$5:$E$1048576,3,0),0) | I19: =+IFERROR(VLOOKUP($A19,[7]Balance!$A$5:$E$1048576,3,0),0) | J19: =+IFERROR(VLOOKUP($A19,'[8]1'!$A$5:$E$1048576,3,0),0) | K19: =+IFERROR(VLOOKUP($A19,'[9]1'!$A$5:$E$1048576,3,0),0) | L19: =+IFERROR(VLOOKUP($A19,'[10]1'!$A$5:$E$1048576,3,0),0) | M19: =+IFERROR(VLOOKUP($A19,'[11]1'!$A$5:$E$1048576,3,0),0) | N19: =+IFERROR(VLOOKUP($A19,[12]Balance!$A$5:$E$1048576,3,0),0) | O19: =+IFERROR(VLOOKUP($A19,'[13]1 т'!$A$5:$E$1048576,3,0),0) | P19: =+IFERROR(VLOOKUP($A19,[14]Balance!$A$5:$E$1048576,3,0),0) | Q19: =+IFERROR(VLOOKUP($A19,[15]Balance!$A$5:$E$1048576,3,0),0) | R19: =+IFERROR(VLOOKUP($A19,'[16]1'!$A$5:$E$1048576,3,0),0) | S19: =+IFERROR(VLOOKUP($A19,'[17]1'!$A$5:$E$1048576,3,0),0) | T19: =+IFERROR(VLOOKUP($A19,'[18]1'!$A$5:$E$1048576,3,0),0) | U19: =+IFERROR(VLOOKUP($A19,[19]Balans!$A$5:$E$1048576,3,0),0) | V19: =+IFERROR(VLOOKUP($A19,'[20]1'!$A$5:$E$1048576,3,0),0) | W19: =+IFERROR(VLOOKUP($A19,[21]Balance!$A$5:$E$1048576,3,0),0) | X19: =+IFERROR(VLOOKUP($A19,'[22]1'!$A$5:$E$1048576,3,0),0) | Y19: =+IFERROR(VLOOKUP($A19,[23]Лист1!$A$5:$E$1048576,3,0),0) | Z19: =+IFERROR(VLOOKUP($A19,'[24]1'!$A$5:$E$1048576,3,0),0) | AA19: =+IFERROR(VLOOKUP($A19,[25]Balance!$A$5:$E$1048576,3,0),0) | AB19: =+IFERROR(VLOOKUP($A19,'[26]1'!$A$5:$E$1048576,3,0),0) | AC19: =+IFERROR(VLOOKUP($A19,'[27]1'!$A$5:$E$1048576,3,0),0) | AD19: =+IFERROR(VLOOKUP($A19,'[28]1'!$A$5:$E$1048576,3,0),0) | AE19: =+IFERROR(VLOOKUP($A19,[29]Лист1!$A$5:$E$1048576,3,0),0) | AF19: =+IFERROR(VLOOKUP($A19,'[30]1'!$A$5:$E$1048576,3,0),0) | AG19: =+IFERROR(VLOOKUP($A19,'[31]1'!$A$5:$E$1048576,3,0),0) | AH19: =+IFERROR(VLOOKUP($A19,'[32]1-жадвал'!$A$5:$E$1048576,3,0),0) | AI19: =+IFERROR(VLOOKUP($A19,[33]Balance!$A$5:$E$1048576,3,0),0) | AJ19: =+IFERROR(VLOOKUP($A19,[34]Balance!$A$5:$E$1048576,3,0),0) | AK19: =+IFERROR(VLOOKUP($A19,'[35]1'!$A$5:$E$1048576,3,0),0)
A20: 6.3 | B20: Минус: Кўрилиши мумкин бўлган зарарларни қоплаш захираси | C20: =+IFERROR(VLOOKUP($A20,[1]Лист1!$A$5:$E$1048576,3,0),0) | D20: =+IFERROR(VLOOKUP($A20,'[2]1'!$A$5:$E$1048576,3,0),0) | E20: =+IFERROR(VLOOKUP($A20,'[3]1'!$A$5:$E$1048576,3,0),0) | F20: =+IFERROR(VLOOKUP($A20,[4]Balance!$A$5:$E$1048576,3,0),0) | G20: =+IFERROR(VLOOKUP($A20,'[5]1'!$A$5:$E$1048576,3,0),0) | H20: =+IFERROR(VLOOKUP($A20,[6]Balance!$A$5:$E$1048576,3,0),0) | I20: =+IFERROR(VLOOKUP($A20,[7]Balance!$A$5:$E$1048576,3,0),0) | J20: =+IFERROR(VLOOKUP($A20,'[8]1'!$A$5:$E$1048576,3,0),0) | K20: =+IFERROR(VLOOKUP($A20,'[9]1'!$A$5:$E$1048576,3,0),0) | L20: =+IFERROR(VLOOKUP($A20,'[10]1'!$A$5:$E$1048576,3,0),0) | M20: =+IFERROR(VLOOKUP($A20,'[11]1'!$A$5:$E$1048576,3,0),0) | N20: =+IFERROR(VLOOKUP($A20,[12]Balance!$A$5:$E$1048576,3,0),0) | O20: =+IFERROR(VLOOKUP($A20,'[13]1 т'!$A$5:$E$1048576,3,0),0) | P20: =+IFERROR(VLOOKUP($A20,[14]Balance!$A$5:$E$1048576,3,0),0) | Q20: =+IFERROR(VLOOKUP($A20,[15]Balance!$A$5:$E$1048576,3,0),0) | R20: =+IFERROR(VLOOKUP($A20,'[16]1'!$A$5:$E$1048576,3,0),0) | S20: =+IFERROR(VLOOKUP($A20,'[17]1'!$A$5:$E$1048576,3,0),0) | T20: =+IFERROR(VLOOKUP($A20,'[18]1'!$A$5:$E$1048576,3,0),0) | U20: =+IFERROR(VLOOKUP($A20,[19]Balans!$A$5:$E$1048576,3,0),0) | V20: =+IFERROR(VLOOKUP($A20,'[20]1'!$A$5:$E$1048576,3,0),0) | W20: =+IFERROR(VLOOKUP($A20,[21]Balance!$A$5:$E$1048576,3,0),0) | X20: =+IFERROR(VLOOKUP($A20,'[22]1'!$A$5:$E$1048576,3,0),0) | Y20: =+IFERROR(VLOOKUP($A20,[23]Лист1!$A$5:$E$1048576,3,0),0) | Z20: =+IFERROR(VLOOKUP($A20,'[24]1'!$A$5:$E$1048576,3,0),0) | AA20: =+IFERROR(VLOOKUP($A20,[25]Balance!$A$5:$E$1048576,3,0),0) | AB20: =+IFERROR(VLOOKUP($A20,'[26]1'!$A$5:$E$1048576,3,0),0) | AC20: =+IFERROR(VLOOKUP($A20,'[27]1'!$A$5:$E$1048576,3,0),0) | AD20: =+IFERROR(VLOOKUP($A20,'[28]1'!$A$5:$E$1048576,3,0),0) | AE20: =+IFERROR(VLOOKUP($A20,[29]Лист1!$A$5:$E$1048576,3,0),0) | AF20: =+IFERROR(VLOOKUP($A20,'[30]1'!$A$5:$E$1048576,3,0),0) | AG20: =+IFERROR(VLOOKUP($A20,'[31]1'!$A$5:$E$1048576,3,0),0) | AH20: =+IFERROR(VLOOKUP($A20,'[32]1-жадвал'!$A$5:$E$1048576,3,0),0) | AI20: =+IFERROR(VLOOKUP($A20,[33]Balance!$A$5:$E$1048576,3,0),0) | AJ20: =+IFERROR(VLOOKUP($A20,[34]Balance!$A$5:$E$1048576,3,0),0) | AK20: =+IFERROR(VLOOKUP($A20,'[35]1'!$A$5:$E$1048576,3,0),0)
A21: 7 | B21: РЕПО битимлари бўйича сотиб олинган қимматли қоғозлар, соф | C21: =+IFERROR(VLOOKUP($A21,[1]Лист1!$A$5:$E$1048576,3,0),0) | D21: =+IFERROR(VLOOKUP($A21,'[2]1'!$A$5:$E$1048576,3,0),0) | E21: =+IFERROR(VLOOKUP($A21,'[3]1'!$A$5:$E$1048576,3,0),0) | F21: =+IFERROR(VLOOKUP($A21,[4]Balance!$A$5:$E$1048576,3,0),0) | G21: =+IFERROR(VLOOKUP($A21,'[5]1'!$A$5:$E$1048576,3,0),0) | H21: =+IFERROR(VLOOKUP($A21,[6]Balance!$A$5:$E$1048576,3,0),0) | I21: =+IFERROR(VLOOKUP($A21,[7]Balance!$A$5:$E$1048576,3,0),0) | J21: =+IFERROR(VLOOKUP($A21,'[8]1'!$A$5:$E$1048576,3,0),0) | K21: =+IFERROR(VLOOKUP($A21,'[9]1'!$A$5:$E$1048576,3,0),0) | L21: =+IFERROR(VLOOKUP($A21,'[10]1'!$A$5:$E$1048576,3,0),0) | M21: =+IFERROR(VLOOKUP($A21,'[11]1'!$A$5:$E$1048576,3,0),0) | N21: =+IFERROR(VLOOKUP($A21,[12]Balance!$A$5:$E$1048576,3,0),0) | O21: =+IFERROR(VLOOKUP($A21,'[13]1 т'!$A$5:$E$1048576,3,0),0) | P21: =+IFERROR(VLOOKUP($A21,[14]Balance!$A$5:$E$1048576,3,0),0) | Q21: =+IFERROR(VLOOKUP($A21,[15]Balance!$A$5:$E$1048576,3,0),0) | R21: =+IFERROR(VLOOKUP($A21,'[16]1'!$A$5:$E$1048576,3,0),0) | S21: =+IFERROR(VLOOKUP($A21,'[17]1'!$A$5:$E$1048576,3,0),0) | T21: =+IFERROR(VLOOKUP($A21,'[18]1'!$A$5:$E$1048576,3,0),0) | U21: =+IFERROR(VLOOKUP($A21,[19]Balans!$A$5:$E$1048576,3,0),0) | V21: =+IFERROR(VLOOKUP($A21,'[20]1'!$A$5:$E$1048576,3,0),0) | W21: =+IFERROR(VLOOKUP($A21,[21]Balance!$A$5:$E$1048576,3,0),0) | X21: =+IFERROR(VLOOKUP($A21,'[22]1'!$A$5:$E$1048576,3,0),0) | Y21: =+IFERROR(VLOOKUP($A21,[23]Лист1!$A$5:$E$1048576,3,0),0) | Z21: =+IFERROR(VLOOKUP($A21,'[24]1'!$A$5:$E$1048576,3,0),0) | AA21: =+IFERROR(VLOOKUP($A21,[25]Balance!$A$5:$E$1048576,3,0),0) | AB21: =+IFERROR(VLOOKUP($A21,'[26]1'!$A$5:$E$1048576,3,0),0) | AC21: =+IFERROR(VLOOKUP($A21,'[27]1'!$A$5:$E$1048576,3,0),0) | AD21: =+IFERROR(VLOOKUP($A21,'[28]1'!$A$5:$E$1048576,3,0),0) | AE21: =+IFERROR(VLOOKUP($A21,[29]Лист1!$A$5:$E$1048576,3,0),0) | AF21: =+IFERROR(VLOOKUP($A21,'[30]1'!$A$5:$E$1048576,3,0),0) | AG21: =+IFERROR(VLOOKUP($A21,'[31]1'!$A$5:$E$1048576,3,0),0) | AH21: =+IFERROR(VLOOKUP($A21,'[32]1-жадвал'!$A$5:$E$1048576,3,0),0) | AI21: =+IFERROR(VLOOKUP($A21,[33]Balance!$A$5:$E$1048576,3,0),0) | AJ21: =+IFERROR(VLOOKUP($A21,[34]Balance!$A$5:$E$1048576,3,0),0) | AK21: =+IFERROR(VLOOKUP($A21,'[35]1'!$A$5:$E$1048576,3,0),0)
A22: 7.1 | B22: РЕПО битимлари бўйича сотиб олинган қимматли қоғозлар, брутто | C22: =+IFERROR(VLOOKUP($A22,[1]Лист1!$A$5:$E$1048576,3,0),0) | D22: =+IFERROR(VLOOKUP($A22,'[2]1'!$A$5:$E$1048576,3,0),0) | E22: =+IFERROR(VLOOKUP($A22,'[3]1'!$A$5:$E$1048576,3,0),0) | F22: =+IFERROR(VLOOKUP($A22,[4]Balance!$A$5:$E$1048576,3,0),0) | G22: =+IFERROR(VLOOKUP($A22,'[5]1'!$A$5:$E$1048576,3,0),0) | H22: =+IFERROR(VLOOKUP($A22,[6]Balance!$A$5:$E$1048576,3,0),0) | I22: =+IFERROR(VLOOKUP($A22,[7]Balance!$A$5:$E$1048576,3,0),0) | J22: =+IFERROR(VLOOKUP($A22,'[8]1'!$A$5:$E$1048576,3,0),0) | K22: =+IFERROR(VLOOKUP($A22,'[9]1'!$A$5:$E$1048576,3,0),0) | L22: =+IFERROR(VLOOKUP($A22,'[10]1'!$A$5:$E$1048576,3,0),0) | M22: =+IFERROR(VLOOKUP($A22,'[11]1'!$A$5:$E$1048576,3,0),0) | N22: =+IFERROR(VLOOKUP($A22,[12]Balance!$A$5:$E$1048576,3,0),0) | O22: =+IFERROR(VLOOKUP($A22,'[13]1 т'!$A$5:$E$1048576,3,0),0) | P22: =+IFERROR(VLOOKUP($A22,[14]Balance!$A$5:$E$1048576,3,0),0) | Q22: =+IFERROR(VLOOKUP($A22,[15]Balance!$A$5:$E$1048576,3,0),0) | R22: =+IFERROR(VLOOKUP($A22,'[16]1'!$A$5:$E$1048576,3,0),0) | S22: =+IFERROR(VLOOKUP($A22,'[17]1'!$A$5:$E$1048576,3,0),0) | T22: =+IFERROR(VLOOKUP($A22,'[18]1'!$A$5:$E$1048576,3,0),0) | U22: =+IFERROR(VLOOKUP($A22,[19]Balans!$A$5:$E$1048576,3,0),0) | V22: =+IFERROR(VLOOKUP($A22,'[20]1'!$A$5:$E$1048576,3,0),0) | W22: =+IFERROR(VLOOKUP($A22,[21]Balance!$A$5:$E$1048576,3,0),0) | X22: =+IFERROR(VLOOKUP($A22,'[22]1'!$A$5:$E$1048576,3,0),0) | Y22: =+IFERROR(VLOOKUP($A22,[23]Лист1!$A$5:$E$1048576,3,0),0) | Z22: =+IFERROR(VLOOKUP($A22,'[24]1'!$A$5:$E$1048576,3,0),0) | AA22: =+IFERROR(VLOOKUP($A22,[25]Balance!$A$5:$E$1048576,3,0),0) | AB22: =+IFERROR(VLOOKUP($A22,'[26]1'!$A$5:$E$1048576,3,0),0) | AC22: =+IFERROR(VLOOKUP($A22,'[27]1'!$A$5:$E$1048576,3,0),0) | AD22: =+IFERROR(VLOOKUP($A22,'[28]1'!$A$5:$E$1048576,3,0),0) | AE22: =+IFERROR(VLOOKUP($A22,[29]Лист1!$A$5:$E$1048576,3,0),0) | AF22: =+IFERROR(VLOOKUP($A22,'[30]1'!$A$5:$E$1048576,3,0),0) | AG22: =+IFERROR(VLOOKUP($A22,'[31]1'!$A$5:$E$1048576,3,0),0) | AH22: =+IFERROR(VLOOKUP($A22,'[32]1-жадвал'!$A$5:$E$1048576,3,0),0) | AI22: =+IFERROR(VLOOKUP($A22,[33]Balance!$A$5:$E$1048576,3,0),0) | AJ22: =+IFERROR(VLOOKUP($A22,[34]Balance!$A$5:$E$1048576,3,0),0) | AK22: =+IFERROR(VLOOKUP($A22,'[35]1'!$A$5:$E$1048576,3,0),0)
A23: 7.2 | B23: Минус: Кўрилиши мумкин бўлган зарарларни қоплаш захираси | C23: =+IFERROR(VLOOKUP($A23,[1]Лист1!$A$5:$E$1048576,3,0),0) | D23: =+IFERROR(VLOOKUP($A23,'[2]1'!$A$5:$E$1048576,3,0),0) | E23: =+IFERROR(VLOOKUP($A23,'[3]1'!$A$5:$E$1048576,3,0),0) | F23: =+IFERROR(VLOOKUP($A23,[4]Balance!$A$5:$E$1048576,3,0),0) | G23: =+IFERROR(VLOOKUP($A23,'[5]1'!$A$5:$E$1048576,3,0),0) | H23: =+IFERROR(VLOOKUP($A23,[6]Balance!$A$5:$E$1048576,3,0),0) | I23: =+IFERROR(VLOOKUP($A23,[7]Balance!$A$5:$E$1048576,3,0),0) | J23: =+IFERROR(VLOOKUP($A23,'[8]1'!$A$5:$E$1048576,3,0),0) | K23: =+IFERROR(VLOOKUP($A23,'[9]1'!$A$5:$E$1048576,3,0),0) | L23: =+IFERROR(VLOOKUP($A23,'[10]1'!$A$5:$E$1048576,3,0),0) | M23: =+IFERROR(VLOOKUP($A23,'[11]1'!$A$5:$E$1048576,3,0),0) | N23: =+IFERROR(VLOOKUP($A23,[12]Balance!$A$5:$E$1048576,3,0),0) | O23: =+IFERROR(VLOOKUP($A23,'[13]1 т'!$A$5:$E$1048576,3,0),0) | P23: =+IFERROR(VLOOKUP($A23,[14]Balance!$A$5:$E$1048576,3,0),0) | Q23: =+IFERROR(VLOOKUP($A23,[15]Balance!$A$5:$E$1048576,3,0),0) | R23: =+IFERROR(VLOOKUP($A23,'[16]1'!$A$5:$E$1048576,3,0),0) | S23: =+IFERROR(VLOOKUP($A23,'[17]1'!$A$5:$E$1048576,3,0),0) | T23: =+IFERROR(VLOOKUP($A23,'[18]1'!$A$5:$E$1048576,3,0),0) | U23: =+IFERROR(VLOOKUP($A23,[19]Balans!$A$5:$E$1048576,3,0),0) | V23: =+IFERROR(VLOOKUP($A23,'[20]1'!$A$5:$E$1048576,3,0),0) | W23: =+IFERROR(VLOOKUP($A23,[21]Balance!$A$5:$E$1048576,3,0),0) | X23: =+IFERROR(VLOOKUP($A23,'[22]1'!$A$5:$E$1048576,3,0),0) | Y23: =+IFERROR(VLOOKUP($A23,[23]Лист1!$A$5:$E$1048576,3,0),0) | Z23: =+IFERROR(VLOOKUP($A23,'[24]1'!$A$5:$E$1048576,3,0),0) | AA23: =+IFERROR(VLOOKUP($A23,[25]Balance!$A$5:$E$1048576,3,0),0) | AB23: =+IFERROR(VLOOKUP($A23,'[26]1'!$A$5:$E$1048576,3,0),0) | AC23: =+IFERROR(VLOOKUP($A23,'[27]1'!$A$5:$E$1048576,3,0),0) | AD23: =+IFERROR(VLOOKUP($A23,'[28]1'!$A$5:$E$1048576,3,0),0) | AE23: =+IFERROR(VLOOKUP($A23,[29]Лист1!$A$5:$E$1048576,3,0),0) | AF23: =+IFERROR(VLOOKUP($A23,'[30]1'!$A$5:$E$1048576,3,0),0) | AG23: =+IFERROR(VLOOKUP($A23,'[31]1'!$A$5:$E$1048576,3,0),0) | AH23: =+IFERROR(VLOOKUP($A23,'[32]1-жадвал'!$A$5:$E$1048576,3,0),0) | AI23: =+IFERROR(VLOOKUP($A23,[33]Balance!$A$5:$E$1048576,3,0),0) | AJ23: =+IFERROR(VLOOKUP($A23,[34]Balance!$A$5:$E$1048576,3,0),0) | AK23: =+IFERROR(VLOOKUP($A23,'[35]1'!$A$5:$E$1048576,3,0),0)
A24: 8 | B24: Кредит ва лизинг операциялари, соф | C24: =+IFERROR(VLOOKUP($A24,[1]Лист1!$A$5:$E$1048576,3,0),0) | D24: =+IFERROR(VLOOKUP($A24,'[2]1'!$A$5:$E$1048576,3,0),0) | E24: =+IFERROR(VLOOKUP($A24,'[3]1'!$A$5:$E$1048576,3,0),0) | F24: =+IFERROR(VLOOKUP($A24,[4]Balance!$A$5:$E$1048576,3,0),0) | G24: =+IFERROR(VLOOKUP($A24,'[5]1'!$A$5:$E$1048576,3,0),0) | H24: =+IFERROR(VLOOKUP($A24,[6]Balance!$A$5:$E$1048576,3,0),0) | I24: =+IFERROR(VLOOKUP($A24,[7]Balance!$A$5:$E$1048576,3,0),0) | J24: =+IFERROR(VLOOKUP($A24,'[8]1'!$A$5:$E$1048576,3,0),0) | K24: =+IFERROR(VLOOKUP($A24,'[9]1'!$A$5:$E$1048576,3,0),0) | L24: =+IFERROR(VLOOKUP($A24,'[10]1'!$A$5:$E$1048576,3,0),0) | M24: =+IFERROR(VLOOKUP($A24,'[11]1'!$A$5:$E$1048576,3,0),0) | N24: =+IFERROR(VLOOKUP($A24,[12]Balance!$A$5:$E$1048576,3,0),0) | O24: =+IFERROR(VLOOKUP($A24,'[13]1 т'!$A$5:$E$1048576,3,0),0) | P24: =+IFERROR(VLOOKUP($A24,[14]Balance!$A$5:$E$1048576,3,0),0) | Q24: =+IFERROR(VLOOKUP($A24,[15]Balance!$A$5:$E$1048576,3,0),0) | R24: =+IFERROR(VLOOKUP($A24,'[16]1'!$A$5:$E$1048576,3,0),0) | S24: =+IFERROR(VLOOKUP($A24,'[17]1'!$A$5:$E$1048576,3,0),0) | T24: =+IFERROR(VLOOKUP($A24,'[18]1'!$A$5:$E$1048576,3,0),0) | U24: =+IFERROR(VLOOKUP($A24,[19]Balans!$A$5:$E$1048576,3,0),0) | V24: =+IFERROR(VLOOKUP($A24,'[20]1'!$A$5:$E$1048576,3,0),0) | W24: =+IFERROR(VLOOKUP($A24,[21]Balance!$A$5:$E$1048576,3,0),0) | X24: =+IFERROR(VLOOKUP($A24,'[22]1'!$A$5:$E$1048576,3,0),0) | Y24: =+IFERROR(VLOOKUP($A24,[23]Лист1!$A$5:$E$1048576,3,0),0) | Z24: =+IFERROR(VLOOKUP($A24,'[24]1'!$A$5:$E$1048576,3,0),0) | AA24: =+IFERROR(VLOOKUP($A24,[25]Balance!$A$5:$E$1048576,3,0),0) | AB24: =+IFERROR(VLOOKUP($A24,'[26]1'!$A$5:$E$1048576,3,0),0) | AC24: =+IFERROR(VLOOKUP($A24,'[27]1'!$A$5:$E$1048576,3,0),0) | AD24: =+IFERROR(VLOOKUP($A24,'[28]1'!$A$5:$E$1048576,3,0),0) | AE24: =+IFERROR(VLOOKUP($A24,[29]Лист1!$A$5:$E$1048576,3,0),0) | AF24: =+IFERROR(VLOOKUP($A24,'[30]1'!$A$5:$E$1048576,3,0),0) | AG24: =+IFERROR(VLOOKUP($A24,'[31]1'!$A$5:$E$1048576,3,0),0) | AH24: =+IFERROR(VLOOKUP($A24,'[32]1-жадвал'!$A$5:$E$1048576,3,0),0) | AI24: =+IFERROR(VLOOKUP($A24,[33]Balance!$A$5:$E$1048576,3,0),0) | AJ24: =+IFERROR(VLOOKUP($A24,[34]Balance!$A$5:$E$1048576,3,0),0) | AK24: =+IFERROR(VLOOKUP($A24,'[35]1'!$A$5:$E$1048576,3,0),0)
A25: 8.1 | B25: Кредит ва лизинг операциялари, брутто | C25: =+IFERROR(VLOOKUP($A25,[1]Лист1!$A$5:$E$1048576,3,0),0) | D25: =+IFERROR(VLOOKUP($A25,'[2]1'!$A$5:$E$1048576,3,0),0) | E25: =+IFERROR(VLOOKUP($A25,'[3]1'!$A$5:$E$1048576,3,0),0) | F25: =+IFERROR(VLOOKUP($A25,[4]Balance!$A$5:$E$1048576,3,0),0) | G25: =+IFERROR(VLOOKUP($A25,'[5]1'!$A$5:$E$1048576,3,0),0) | H25: =+IFERROR(VLOOKUP($A25,[6]Balance!$A$5:$E$1048576,3,0),0) | I25: =+IFERROR(VLOOKUP($A25,[7]Balance!$A$5:$E$1048576,3,0),0) | J25: =+IFERROR(VLOOKUP($A25,'[8]1'!$A$5:$E$1048576,3,0),0) | K25: =+IFERROR(VLOOKUP($A25,'[9]1'!$A$5:$E$1048576,3,0),0) | L25: =+IFERROR(VLOOKUP($A25,'[10]1'!$A$5:$E$1048576,3,0),0) | M25: =+IFERROR(VLOOKUP($A25,'[11]1'!$A$5:$E$1048576,3,0),0) | N25: =+IFERROR(VLOOKUP($A25,[12]Balance!$A$5:$E$1048576,3,0),0) | O25: =+IFERROR(VLOOKUP($A25,'[13]1 т'!$A$5:$E$1048576,3,0),0) | P25: =+IFERROR(VLOOKUP($A25,[14]Balance!$A$5:$E$1048576,3,0),0) | Q25: =+IFERROR(VLOOKUP($A25,[15]Balance!$A$5:$E$1048576,3,0),0) | R25: =+IFERROR(VLOOKUP($A25,'[16]1'!$A$5:$E$1048576,3,0),0) | S25: =+IFERROR(VLOOKUP($A25,'[17]1'!$A$5:$E$1048576,3,0),0) | T25: =+IFERROR(VLOOKUP($A25,'[18]1'!$A$5:$E$1048576,3,0),0) | U25: =+IFERROR(VLOOKUP($A25,[19]Balans!$A$5:$E$1048576,3,0),0) | V25: =+IFERROR(VLOOKUP($A25,'[20]1'!$A$5:$E$1048576,3,0),0) | W25: =+IFERROR(VLOOKUP($A25,[21]Balance!$A$5:$E$1048576,3,0),0) | X25: =+IFERROR(VLOOKUP($A25,'[22]1'!$A$5:$E$1048576,3,0),0) | Y25: =+IFERROR(VLOOKUP($A25,[23]Лист1!$A$5:$E$1048576,3,0),0) | Z25: =+IFERROR(VLOOKUP($A25,'[24]1'!$A$5:$E$1048576,3,0),0) | AA25: =+IFERROR(VLOOKUP($A25,[25]Balance!$A$5:$E$1048576,3,0),0) | AB25: =+IFERROR(VLOOKUP($A25,'[26]1'!$A$5:$E$1048576,3,0),0) | AC25: =+IFERROR(VLOOKUP($A25,'[27]1'!$A$5:$E$1048576,3,0),0) | AD25: =+IFERROR(VLOOKUP($A25,'[28]1'!$A$5:$E$1048576,3,0),0) | AE25: =+IFERROR(VLOOKUP($A25,[29]Лист1!$A$5:$E$1048576,3,0),0) | AF25: =+IFERROR(VLOOKUP($A25,'[30]1'!$A$5:$E$1048576,3,0),0) | AG25: =+IFERROR(VLOOKUP($A25,'[31]1'!$A$5:$E$1048576,3,0),0) | AH25: =+IFERROR(VLOOKUP($A25,'[32]1-жадвал'!$A$5:$E$1048576,3,0),0) | AI25: =+IFERROR(VLOOKUP($A25,[33]Balance!$A$5:$E$1048576,3,0),0) | AJ25: =+IFERROR(VLOOKUP($A25,[34]Balance!$A$5:$E$1048576,3,0),0) | AK25: =+IFERROR(VLOOKUP($A25,'[35]1'!$A$5:$E$1048576,3,0),0)
A26: 8.2 | B26: Минус: Кўрилиши мумкин бўлган зарарларни қоплаш захираси | C26: =+IFERROR(VLOOKUP($A26,[1]Лист1!$A$5:$E$1048576,3,0),0) | D26: =+IFERROR(VLOOKUP($A26,'[2]1'!$A$5:$E$1048576,3,0),0) | E26: =+IFERROR(VLOOKUP($A26,'[3]1'!$A$5:$E$1048576,3,0),0) | F26: =+IFERROR(VLOOKUP($A26,[4]Balance!$A$5:$E$1048576,3,0),0) | G26: =+IFERROR(VLOOKUP($A26,'[5]1'!$A$5:$E$1048576,3,0),0) | H26: =+IFERROR(VLOOKUP($A26,[6]Balance!$A$5:$E$1048576,3,0),0) | I26: =+IFERROR(VLOOKUP($A26,[7]Balance!$A$5:$E$1048576,3,0),0) | J26: =+IFERROR(VLOOKUP($A26,'[8]1'!$A$5:$E$1048576,3,0),0) | K26: =+IFERROR(VLOOKUP($A26,'[9]1'!$A$5:$E$1048576,3,0),0) | L26: =+IFERROR(VLOOKUP($A26,'[10]1'!$A$5:$E$1048576,3,0),0) | M26: =+IFERROR(VLOOKUP($A26,'[11]1'!$A$5:$E$1048576,3,0),0) | N26: =+IFERROR(VLOOKUP($A26,[12]Balance!$A$5:$E$1048576,3,0),0) | O26: =+IFERROR(VLOOKUP($A26,'[13]1 т'!$A$5:$E$1048576,3,0),0) | P26: =+IFERROR(VLOOKUP($A26,[14]Balance!$A$5:$E$1048576,3,0),0) | Q26: =+IFERROR(VLOOKUP($A26,[15]Balance!$A$5:$E$1048576,3,0),0) | R26: =+IFERROR(VLOOKUP($A26,'[16]1'!$A$5:$E$1048576,3,0),0) | S26: =+IFERROR(VLOOKUP($A26,'[17]1'!$A$5:$E$1048576,3,0),0) | T26: =+IFERROR(VLOOKUP($A26,'[18]1'!$A$5:$E$1048576,3,0),0) | U26: =+IFERROR(VLOOKUP($A26,[19]Balans!$A$5:$E$1048576,3,0),0) | V26: =+IFERROR(VLOOKUP($A26,'[20]1'!$A$5:$E$1048576,3,0),0) | W26: =+IFERROR(VLOOKUP($A26,[21]Balance!$A$5:$E$1048576,3,0),0) | X26: =+IFERROR(VLOOKUP($A26,'[22]1'!$A$5:$E$1048576,3,0),0) | Y26: =+IFERROR(VLOOKUP($A26,[23]Лист1!$A$5:$E$1048576,3,0),0) | Z26: =+IFERROR(VLOOKUP($A26,'[24]1'!$A$5:$E$1048576,3,0),0) | AA26: =+IFERROR(VLOOKUP($A26,[25]Balance!$A$5:$E$1048576,3,0),0) | AB26: =+IFERROR(VLOOKUP($A26,'[26]1'!$A$5:$E$1048576,3,0),0) | AC26: =+IFERROR(VLOOKUP($A26,'[27]1'!$A$5:$E$1048576,3,0),0) | AD26: =+IFERROR(VLOOKUP($A26,'[28]1'!$A$5:$E$1048576,3,0),0) | AE26: =+IFERROR(VLOOKUP($A26,[29]Лист1!$A$5:$E$1048576,3,0),0) | AF26: =+IFERROR(VLOOKUP($A26,'[30]1'!$A$5:$E$1048576,3,0),0) | AG26: =+IFERROR(VLOOKUP($A26,'[31]1'!$A$5:$E$1048576,3,0),0) | AH26: =+IFERROR(VLOOKUP($A26,'[32]1-жадвал'!$A$5:$E$1048576,3,0),0) | AI26: =+IFERROR(VLOOKUP($A26,[33]Balance!$A$5:$E$1048576,3,0),0) | AJ26: =+IFERROR(VLOOKUP($A26,[34]Balance!$A$5:$E$1048576,3,0),0) | AK26: =+IFERROR(VLOOKUP($A26,'[35]1'!$A$5:$E$1048576,3,0),0)
A27: 9 | B27: Молиявий инструментлар бўйича мижозларнинг мажбуриятлари, соф | C27: =+IFERROR(VLOOKUP($A27,[1]Лист1!$A$5:$E$1048576,3,0),0) | D27: =+IFERROR(VLOOKUP($A27,'[2]1'!$A$5:$E$1048576,3,0),0) | E27: =+IFERROR(VLOOKUP($A27,'[3]1'!$A$5:$E$1048576,3,0),0) | F27: =+IFERROR(VLOOKUP($A27,[4]Balance!$A$5:$E$1048576,3,0),0) | G27: =+IFERROR(VLOOKUP($A27,'[5]1'!$A$5:$E$1048576,3,0),0) | H27: =+IFERROR(VLOOKUP($A27,[6]Balance!$A$5:$E$1048576,3,0),0) | I27: =+IFERROR(VLOOKUP($A27,[7]Balance!$A$5:$E$1048576,3,0),0) | J27: =+IFERROR(VLOOKUP($A27,'[8]1'!$A$5:$E$1048576,3,0),0) | K27: =+IFERROR(VLOOKUP($A27,'[9]1'!$A$5:$E$1048576,3,0),0) | L27: =+IFERROR(VLOOKUP($A27,'[10]1'!$A$5:$E$1048576,3,0),0) | M27: =+IFERROR(VLOOKUP($A27,'[11]1'!$A$5:$E$1048576,3,0),0) | N27: =+IFERROR(VLOOKUP($A27,[12]Balance!$A$5:$E$1048576,3,0),0) | O27: =+IFERROR(VLOOKUP($A27,'[13]1 т'!$A$5:$E$1048576,3,0),0) | P27: =+IFERROR(VLOOKUP($A27,[14]Balance!$A$5:$E$1048576,3,0),0) | Q27: =+IFERROR(VLOOKUP($A27,[15]Balance!$A$5:$E$1048576,3,0),0) | R27: =+IFERROR(VLOOKUP($A27,'[16]1'!$A$5:$E$1048576,3,0),0) | S27: =+IFERROR(VLOOKUP($A27,'[17]1'!$A$5:$E$1048576,3,0),0) | T27: =+IFERROR(VLOOKUP($A27,'[18]1'!$A$5:$E$1048576,3,0),0) | U27: =+IFERROR(VLOOKUP($A27,[19]Balans!$A$5:$E$1048576,3,0),0) | V27: =+IFERROR(VLOOKUP($A27,'[20]1'!$A$5:$E$1048576,3,0),0) | W27: =+IFERROR(VLOOKUP($A27,[21]Balance!$A$5:$E$1048576,3,0),0) | X27: =+IFERROR(VLOOKUP($A27,'[22]1'!$A$5:$E$1048576,3,0),0) | Y27: =+IFERROR(VLOOKUP($A27,[23]Лист1!$A$5:$E$1048576,3,0),0) | Z27: =+IFERROR(VLOOKUP($A27,'[24]1'!$A$5:$E$1048576,3,0),0) | AA27: =+IFERROR(VLOOKUP($A27,[25]Balance!$A$5:$E$1048576,3,0),0) | AB27: =+IFERROR(VLOOKUP($A27,'[26]1'!$A$5:$E$1048576,3,0),0) | AC27: =+IFERROR(VLOOKUP($A27,'[27]1'!$A$5:$E$1048576,3,0),0) | AD27: =+IFERROR(VLOOKUP($A27,'[28]1'!$A$5:$E$1048576,3,0),0) | AE27: =+IFERROR(VLOOKUP($A27,[29]Лист1!$A$5:$E$1048576,3,0),0) | AF27: =+IFERROR(VLOOKUP($A27,'[30]1'!$A$5:$E$1048576,3,0),0) | AG27: =+IFERROR(VLOOKUP($A27,'[31]1'!$A$5:$E$1048576,3,0),0) | AH27: =+IFERROR(VLOOKUP($A27,'[32]1-жадвал'!$A$5:$E$1048576,3,0),0) | AI27: =+IFERROR(VLOOKUP($A27,[33]Balance!$A$5:$E$1048576,3,0),0) | AJ27: =+IFERROR(VLOOKUP($A27,[34]Balance!$A$5:$E$1048576,3,0),0) | AK27: =+IFERROR(VLOOKUP($A27,'[35]1'!$A$5:$E$1048576,3,0),0)
A28: 9.1 | B28: Молиявий инструментлар бўйича мижозларнинг мажбуриятлари, брутто | C28: =+IFERROR(VLOOKUP($A28,[1]Лист1!$A$5:$E$1048576,3,0),0) | D28: =+IFERROR(VLOOKUP($A28,'[2]1'!$A$5:$E$1048576,3,0),0) | E28: =+IFERROR(VLOOKUP($A28,'[3]1'!$A$5:$E$1048576,3,0),0) | F28: =+IFERROR(VLOOKUP($A28,[4]Balance!$A$5:$E$1048576,3,0),0) | G28: =+IFERROR(VLOOKUP($A28,'[5]1'!$A$5:$E$1048576,3,0),0) | H28: =+IFERROR(VLOOKUP($A28,[6]Balance!$A$5:$E$1048576,3,0),0) | I28: =+IFERROR(VLOOKUP($A28,[7]Balance!$A$5:$E$1048576,3,0),0) | J28: =+IFERROR(VLOOKUP($A28,'[8]1'!$A$5:$E$1048576,3,0),0) | K28: =+IFERROR(VLOOKUP($A28,'[9]1'!$A$5:$E$1048576,3,0),0) | L28: =+IFERROR(VLOOKUP($A28,'[10]1'!$A$5:$E$1048576,3,0),0) | M28: =+IFERROR(VLOOKUP($A28,'[11]1'!$A$5:$E$1048576,3,0),0) | N28: =+IFERROR(VLOOKUP($A28,[12]Balance!$A$5:$E$1048576,3,0),0) | O28: =+IFERROR(VLOOKUP($A28,'[13]1 т'!$A$5:$E$1048576,3,0),0) | P28: =+IFERROR(VLOOKUP($A28,[14]Balance!$A$5:$E$1048576,3,0),0) | Q28: =+IFERROR(VLOOKUP($A28,[15]Balance!$A$5:$E$1048576,3,0),0) | R28: =+IFERROR(VLOOKUP($A28,'[16]1'!$A$5:$E$1048576,3,0),0) | S28: =+IFERROR(VLOOKUP($A28,'[17]1'!$A$5:$E$1048576,3,0),0) | T28: =+IFERROR(VLOOKUP($A28,'[18]1'!$A$5:$E$1048576,3,0),0) | U28: =+IFERROR(VLOOKUP($A28,[19]Balans!$A$5:$E$1048576,3,0),0) | V28: =+IFERROR(VLOOKUP($A28,'[20]1'!$A$5:$E$1048576,3,0),0) | W28: =+IFERROR(VLOOKUP($A28,[21]Balance!$A$5:$E$1048576,3,0),0) | X28: =+IFERROR(VLOOKUP($A28,'[22]1'!$A$5:$E$1048576,3,0),0) | Y28: =+IFERROR(VLOOKUP($A28,[23]Лист1!$A$5:$E$1048576,3,0),0) | Z28: =+IFERROR(VLOOKUP($A28,'[24]1'!$A$5:$E$1048576,3,0),0) | AA28: =+IFERROR(VLOOKUP($A28,[25]Balance!$A$5:$E$1048576,3,0),0) | AB28: =+IFERROR(VLOOKUP($A28,'[26]1'!$A$5:$E$1048576,3,0),0) | AC28: =+IFERROR(VLOOKUP($A28,'[27]1'!$A$5:$E$1048576,3,0),0) | AD28: =+IFERROR(VLOOKUP($A28,'[28]1'!$A$5:$E$1048576,3,0),0) | AE28: =+IFERROR(VLOOKUP($A28,[29]Лист1!$A$5:$E$1048576,3,0),0) | AF28: =+IFERROR(VLOOKUP($A28,'[30]1'!$A$5:$E$1048576,3,0),0) | AG28: =+IFERROR(VLOOKUP($A28,'[31]1'!$A$5:$E$1048576,3,0),0) | AH28: =+IFERROR(VLOOKUP($A28,'[32]1-жадвал'!$A$5:$E$1048576,3,0),0) | AI28: =+IFERROR(VLOOKUP($A28,[33]Balance!$A$5:$E$1048576,3,0),0) | AJ28: =+IFERROR(VLOOKUP($A28,[34]Balance!$A$5:$E$1048576,3,0),0) | AK28: =+IFERROR(VLOOKUP($A28,'[35]1'!$A$5:$E$1048576,3,0),0)
A29: 9.2 | B29: Минус: Кўрилиши мумкин бўлган зарарларни қоплаш захираси | C29: =+IFERROR(VLOOKUP($A29,[1]Лист1!$A$5:$E$1048576,3,0),0) | D29: =+IFERROR(VLOOKUP($A29,'[2]1'!$A$5:$E$1048576,3,0),0) | E29: =+IFERROR(VLOOKUP($A29,'[3]1'!$A$5:$E$1048576,3,0),0) | F29: =+IFERROR(VLOOKUP($A29,[4]Balance!$A$5:$E$1048576,3,0),0) | G29: =+IFERROR(VLOOKUP($A29,'[5]1'!$A$5:$E$1048576,3,0),0) | H29: =+IFERROR(VLOOKUP($A29,[6]Balance!$A$5:$E$1048576,3,0),0) | I29: =+IFERROR(VLOOKUP($A29,[7]Balance!$A$5:$E$1048576,3,0),0) | J29: =+IFERROR(VLOOKUP($A29,'[8]1'!$A$5:$E$1048576,3,0),0) | K29: =+IFERROR(VLOOKUP($A29,'[9]1'!$A$5:$E$1048576,3,0),0) | L29: =+IFERROR(VLOOKUP($A29,'[10]1'!$A$5:$E$1048576,3,0),0) | M29: =+IFERROR(VLOOKUP($A29,'[11]1'!$A$5:$E$1048576,3,0),0) | N29: =+IFERROR(VLOOKUP($A29,[12]Balance!$A$5:$E$1048576,3,0),0) | O29: =+IFERROR(VLOOKUP($A29,'[13]1 т'!$A$5:$E$1048576,3,0),0) | P29: =+IFERROR(VLOOKUP($A29,[14]Balance!$A$5:$E$1048576,3,0),0) | Q29: =+IFERROR(VLOOKUP($A29,[15]Balance!$A$5:$E$1048576,3,0),0) | R29: =+IFERROR(VLOOKUP($A29,'[16]1'!$A$5:$E$1048576,3,0),0) | S29: =+IFERROR(VLOOKUP($A29,'[17]1'!$A$5:$E$1048576,3,0),0) | T29: =+IFERROR(VLOOKUP($A29,'[18]1'!$A$5:$E$1048576,3,0),0) | U29: =+IFERROR(VLOOKUP($A29,[19]Balans!$A$5:$E$1048576,3,0),0) | V29: =+IFERROR(VLOOKUP($A29,'[20]1'!$A$5:$E$1048576,3,0),0) | W29: =+IFERROR(VLOOKUP($A29,[21]Balance!$A$5:$E$1048576,3,0),0) | X29: =+IFERROR(VLOOKUP($A29,'[22]1'!$A$5:$E$1048576,3,0),0) | Y29: =+IFERROR(VLOOKUP($A29,[23]Лист1!$A$5:$E$1048576,3,0),0) | Z29: =+IFERROR(VLOOKUP($A29,'[24]1'!$A$5:$E$1048576,3,0),0) | AA29: =+IFERROR(VLOOKUP($A29,[25]Balance!$A$5:$E$1048576,3,0),0) | AB29: =+IFERROR(VLOOKUP($A29,'[26]1'!$A$5:$E$1048576,3,0),0) | AC29: =+IFERROR(VLOOKUP($A29,'[27]1'!$A$5:$E$1048576,3,0),0) | AD29: =+IFERROR(VLOOKUP($A29,'[28]1'!$A$5:$E$1048576,3,0),0) | AE29: =+IFERROR(VLOOKUP($A29,[29]Лист1!$A$5:$E$1048576,3,0),0) | AF29: =+IFERROR(VLOOKUP($A29,'[30]1'!$A$5:$E$1048576,3,0),0) | AG29: =+IFERROR(VLOOKUP($A29,'[31]1'!$A$5:$E$1048576,3,0),0) | AH29: =+IFERROR(VLOOKUP($A29,'[32]1-жадвал'!$A$5:$E$1048576,3,0),0) | AI29: =+IFERROR(VLOOKUP($A29,[33]Balance!$A$5:$E$1048576,3,0),0) | AJ29: =+IFERROR(VLOOKUP($A29,[34]Balance!$A$5:$E$1048576,3,0),0) | AK29: =+IFERROR(VLOOKUP($A29,'[35]1'!$A$5:$E$1048576,3,0),0)
A30: 10 | B30: Асосий воситалар, соф | C30: =+IFERROR(VLOOKUP($A30,[1]Лист1!$A$5:$E$1048576,3,0),0) | D30: =+IFERROR(VLOOKUP($A30,'[2]1'!$A$5:$E$1048576,3,0),0) | E30: =+IFERROR(VLOOKUP($A30,'[3]1'!$A$5:$E$1048576,3,0),0) | F30: =+IFERROR(VLOOKUP($A30,[4]Balance!$A$5:$E$1048576,3,0),0) | G30: =+IFERROR(VLOOKUP($A30,'[5]1'!$A$5:$E$1048576,3,0),0) | H30: =+IFERROR(VLOOKUP($A30,[6]Balance!$A$5:$E$1048576,3,0),0) | I30: =+IFERROR(VLOOKUP($A30,[7]Balance!$A$5:$E$1048576,3,0),0) | J30: =+IFERROR(VLOOKUP($A30,'[8]1'!$A$5:$E$1048576,3,0),0) | K30: =+IFERROR(VLOOKUP($A30,'[9]1'!$A$5:$E$1048576,3,0),0) | L30: =+IFERROR(VLOOKUP($A30,'[10]1'!$A$5:$E$1048576,3,0),0) | M30: =+IFERROR(VLOOKUP($A30,'[11]1'!$A$5:$E$1048576,3,0),0) | N30: =+IFERROR(VLOOKUP($A30,[12]Balance!$A$5:$E$1048576,3,0),0) | O30: =+IFERROR(VLOOKUP($A30,'[13]1 т'!$A$5:$E$1048576,3,0),0) | P30: =+IFERROR(VLOOKUP($A30,[14]Balance!$A$5:$E$1048576,3,0),0) | Q30: =+IFERROR(VLOOKUP($A30,[15]Balance!$A$5:$E$1048576,3,0),0) | R30: =+IFERROR(VLOOKUP($A30,'[16]1'!$A$5:$E$1048576,3,0),0) | S30: =+IFERROR(VLOOKUP($A30,'[17]1'!$A$5:$E$1048576,3,0),0) | T30: =+IFERROR(VLOOKUP($A30,'[18]1'!$A$5:$E$1048576,3,0),0) | U30: =+IFERROR(VLOOKUP($A30,[19]Balans!$A$5:$E$1048576,3,0),0) | V30: =+IFERROR(VLOOKUP($A30,'[20]1'!$A$5:$E$1048576,3,0),0) | W30: =+IFERROR(VLOOKUP($A30,[21]Balance!$A$5:$E$1048576,3,0),0) | X30: =+IFERROR(VLOOKUP($A30,'[22]1'!$A$5:$E$1048576,3,0),0) | Y30: =+IFERROR(VLOOKUP($A30,[23]Лист1!$A$5:$E$1048576,3,0),0) | Z30: =+IFERROR(VLOOKUP($A30,'[24]1'!$A$5:$E$1048576,3,0),0) | AA30: =+IFERROR(VLOOKUP($A30,[25]Balance!$A$5:$E$1048576,3,0),0) | AB30: =+IFERROR(VLOOKUP($A30,'[26]1'!$A$5:$E$1048576,3,0),0) | AC30: =+IFERROR(VLOOKUP($A30,'[27]1'!$A$5:$E$1048576,3,0),0) | AD30: =+IFERROR(VLOOKUP($A30,'[28]1'!$A$5:$E$1048576,3,0),0) | AE30: =+IFERROR(VLOOKUP($A30,[29]Лист1!$A$5:$E$1048576,3,0),0) | AF30: =+IFERROR(VLOOKUP($A30,'[30]1'!$A$5:$E$1048576,3,0),0) | AG30: =+IFERROR(VLOOKUP($A30,'[31]1'!$A$5:$E$1048576,3,0),0) | AH30: =+IFERROR(VLOOKUP($A30,'[32]1-жадвал'!$A$5:$E$1048576,3,0),0) | AI30: =+IFERROR(VLOOKUP($A30,[33]Balance!$A$5:$E$1048576,3,0),0) | AJ30: =+IFERROR(VLOOKUP($A30,[34]Balance!$A$5:$E$1048576,3,0),0) | AK30: =+IFERROR(VLOOKUP($A30,'[35]1'!$A$5:$E$1048576,3,0),0)
A31: 11 | B31: Жами ҳисобланган фоизли ва фоизсиз даромадлар, соф | C31: =+IFERROR(VLOOKUP($A31,[1]Лист1!$A$5:$E$1048576,3,0),0) | D31: =+IFERROR(VLOOKUP($A31,'[2]1'!$A$5:$E$1048576,3,0),0) | E31: =+IFERROR(VLOOKUP($A31,'[3]1'!$A$5:$E$1048576,3,0),0) | F31: =+IFERROR(VLOOKUP($A31,[4]Balance!$A$5:$E$1048576,3,0),0) | G31: =+IFERROR(VLOOKUP($A31,'[5]1'!$A$5:$E$1048576,3,0),0) | H31: =+IFERROR(VLOOKUP($A31,[6]Balance!$A$5:$E$1048576,3,0),0) | I31: =+IFERROR(VLOOKUP($A31,[7]Balance!$A$5:$E$1048576,3,0),0) | J31: =+IFERROR(VLOOKUP($A31,'[8]1'!$A$5:$E$1048576,3,0),0) | K31: =+IFERROR(VLOOKUP($A31,'[9]1'!$A$5:$E$1048576,3,0),0) | L31: =+IFERROR(VLOOKUP($A31,'[10]1'!$A$5:$E$1048576,3,0),0) | M31: =+IFERROR(VLOOKUP($A31,'[11]1'!$A$5:$E$1048576,3,0),0) | N31: =+IFERROR(VLOOKUP($A31,[12]Balance!$A$5:$E$1048576,3,0),0) | O31: =+IFERROR(VLOOKUP($A31,'[13]1 т'!$A$5:$E$1048576,3,0),0) | P31: =+IFERROR(VLOOKUP($A31,[14]Balance!$A$5:$E$1048576,3,0),0) | Q31: =+IFERROR(VLOOKUP($A31,[15]Balance!$A$5:$E$1048576,3,0),0) | R31: =+IFERROR(VLOOKUP($A31,'[16]1'!$A$5:$E$1048576,3,0),0) | S31: =+IFERROR(VLOOKUP($A31,'[17]1'!$A$5:$E$1048576,3,0),0) | T31: =+IFERROR(VLOOKUP($A31,'[18]1'!$A$5:$E$1048576,3,0),0) | U31: =+IFERROR(VLOOKUP($A31,[19]Balans!$A$5:$E$1048576,3,0),0) | V31: =+IFERROR(VLOOKUP($A31,'[20]1'!$A$5:$E$1048576,3,0),0) | W31: =+IFERROR(VLOOKUP($A31,[21]Balance!$A$5:$E$1048576,3,0),0) | X31: =+IFERROR(VLOOKUP($A31,'[22]1'!$A$5:$E$1048576,3,0),0) | Y31: =+IFERROR(VLOOKUP($A31,[23]Лист1!$A$5:$E$1048576,3,0),0) | Z31: =+IFERROR(VLOOKUP($A31,'[24]1'!$A$5:$E$1048576,3,0),0) | AA31: =+IFERROR(VLOOKUP($A31,[25]Balance!$A$5:$E$1048576,3,0),0) | AB31: =+IFERROR(VLOOKUP($A31,'[26]1'!$A$5:$E$1048576,3,0),0) | AC31: =+IFERROR(VLOOKUP($A31,'[27]1'!$A$5:$E$1048576,3,0),0) | AD31: =+IFERROR(VLOOKUP($A31,'[28]1'!$A$5:$E$1048576,3,0),0) | AE31: =+IFERROR(VLOOKUP($A31,[29]Лист1!$A$5:$E$1048576,3,0),0) | AF31: =+IFERROR(VLOOKUP($A31,'[30]1'!$A$5:$E$1048576,3,0),0) | AG31: =+IFERROR(VLOOKUP($A31,'[31]1'!$A$5:$E$1048576,3,0),0) | AH31: =+IFERROR(VLOOKUP($A31,'[32]1-жадвал'!$A$5:$E$1048576,3,0),0) | AI31: =+IFERROR(VLOOKUP($A31,[33]Balance!$A$5:$E$1048576,3,0),0) | AJ31: =+IFERROR(VLOOKUP($A31,[34]Balance!$A$5:$E$1048576,3,0),0) | AK31: =+IFERROR(VLOOKUP($A31,'[35]1'!$A$5:$E$1048576,3,0),0)
A32: 11.1 | B32: Ҳисобланган фоизли даромадлар, брутто | C32: =+IFERROR(VLOOKUP($A32,[1]Лист1!$A$5:$E$1048576,3,0),0) | D32: =+IFERROR(VLOOKUP($A32,'[2]1'!$A$5:$E$1048576,3,0),0) | E32: =+IFERROR(VLOOKUP($A32,'[3]1'!$A$5:$E$1048576,3,0),0) | F32: =+IFERROR(VLOOKUP($A32,[4]Balance!$A$5:$E$1048576,3,0),0) | G32: =+IFERROR(VLOOKUP($A32,'[5]1'!$A$5:$E$1048576,3,0),0) | H32: =+IFERROR(VLOOKUP($A32,[6]Balance!$A$5:$E$1048576,3,0),0) | I32: =+IFERROR(VLOOKUP($A32,[7]Balance!$A$5:$E$1048576,3,0),0) | J32: =+IFERROR(VLOOKUP($A32,'[8]1'!$A$5:$E$1048576,3,0),0) | K32: =+IFERROR(VLOOKUP($A32,'[9]1'!$A$5:$E$1048576,3,0),0) | L32: =+IFERROR(VLOOKUP($A32,'[10]1'!$A$5:$E$1048576,3,0),0) | M32: =+IFERROR(VLOOKUP($A32,'[11]1'!$A$5:$E$1048576,3,0),0) | N32: =+IFERROR(VLOOKUP($A32,[12]Balance!$A$5:$E$1048576,3,0),0) | O32: =+IFERROR(VLOOKUP($A32,'[13]1 т'!$A$5:$E$1048576,3,0),0) | P32: =+IFERROR(VLOOKUP($A32,[14]Balance!$A$5:$E$1048576,3,0),0) | Q32: =+IFERROR(VLOOKUP($A32,[15]Balance!$A$5:$E$1048576,3,0),0) | R32: =+IFERROR(VLOOKUP($A32,'[16]1'!$A$5:$E$1048576,3,0),0) | S32: =+IFERROR(VLOOKUP($A32,'[17]1'!$A$5:$E$1048576,3,0),0) | T32: =+IFERROR(VLOOKUP($A32,'[18]1'!$A$5:$E$1048576,3,0),0) | U32: =+IFERROR(VLOOKUP($A32,[19]Balans!$A$5:$E$1048576,3,0),0) | V32: =+IFERROR(VLOOKUP($A32,'[20]1'!$A$5:$E$1048576,3,0),0) | W32: =+IFERROR(VLOOKUP($A32,[21]Balance!$A$5:$E$1048576,3,0),0) | X32: =+IFERROR(VLOOKUP($A32,'[22]1'!$A$5:$E$1048576,3,0),0) | Y32: =+IFERROR(VLOOKUP($A32,[23]Лист1!$A$5:$E$1048576,3,0),0) | Z32: =+IFERROR(VLOOKUP($A32,'[24]1'!$A$5:$E$1048576,3,0),0) | AA32: =+IFERROR(VLOOKUP($A32,[25]Balance!$A$5:$E$1048576,3,0),0) | AB32: =+IFERROR(VLOOKUP($A32,'[26]1'!$A$5:$E$1048576,3,0),0) | AC32: =+IFERROR(VLOOKUP($A32,'[27]1'!$A$5:$E$1048576,3,0),0) | AD32: =+IFERROR(VLOOKUP($A32,'[28]1'!$A$5:$E$1048576,3,0),0) | AE32: =+IFERROR(VLOOKUP($A32,[29]Лист1!$A$5:$E$1048576,3,0),0) | AF32: =+IFERROR(VLOOKUP($A32,'[30]1'!$A$5:$E$1048576,3,0),0) | AG32: =+IFERROR(VLOOKUP($A32,'[31]1'!$A$5:$E$1048576,3,0),0) | AH32: =+IFERROR(VLOOKUP($A32,'[32]1-жадвал'!$A$5:$E$1048576,3,0),0) | AI32: =+IFERROR(VLOOKUP($A32,[33]Balance!$A$5:$E$1048576,3,0),0) | AJ32: =+IFERROR(VLOOKUP($A32,[34]Balance!$A$5:$E$1048576,3,0),0) | AK32: =+IFERROR(VLOOKUP($A32,'[35]1'!$A$5:$E$1048576,3,0),0)
A33: 11.2 | B33: Ҳисобланган фоизсиз даромадлар, брутто | C33: =+IFERROR(VLOOKUP($A33,[1]Лист1!$A$5:$E$1048576,3,0),0) | D33: =+IFERROR(VLOOKUP($A33,'[2]1'!$A$5:$E$1048576,3,0),0) | E33: =+IFERROR(VLOOKUP($A33,'[3]1'!$A$5:$E$1048576,3,0),0) | F33: =+IFERROR(VLOOKUP($A33,[4]Balance!$A$5:$E$1048576,3,0),0) | G33: =+IFERROR(VLOOKUP($A33,'[5]1'!$A$5:$E$1048576,3,0),0) | H33: =+IFERROR(VLOOKUP($A33,[6]Balance!$A$5:$E$1048576,3,0),0) | I33: =+IFERROR(VLOOKUP($A33,[7]Balance!$A$5:$E$1048576,3,0),0) | J33: =+IFERROR(VLOOKUP($A33,'[8]1'!$A$5:$E$1048576,3,0),0) | K33: =+IFERROR(VLOOKUP($A33,'[9]1'!$A$5:$E$1048576,3,0),0) | L33: =+IFERROR(VLOOKUP($A33,'[10]1'!$A$5:$E$1048576,3,0),0) | M33: =+IFERROR(VLOOKUP($A33,'[11]1'!$A$5:$E$1048576,3,0),0) | N33: =+IFERROR(VLOOKUP($A33,[12]Balance!$A$5:$E$1048576,3,0),0) | O33: =+IFERROR(VLOOKUP($A33,'[13]1 т'!$A$5:$E$1048576,3,0),0) | P33: =+IFERROR(VLOOKUP($A33,[14]Balance!$A$5:$E$1048576,3,0),0) | Q33: =+IFERROR(VLOOKUP($A33,[15]Balance!$A$5:$E$1048576,3,0),0) | R33: =+IFERROR(VLOOKUP($A33,'[16]1'!$A$5:$E$1048576,3,0),0) | S33: =+IFERROR(VLOOKUP($A33,'[17]1'!$A$5:$E$1048576,3,0),0) | T33: =+IFERROR(VLOOKUP($A33,'[18]1'!$A$5:$E$1048576,3,0),0) | U33: =+IFERROR(VLOOKUP($A33,[19]Balans!$A$5:$E$1048576,3,0),0) | V33: =+IFERROR(VLOOKUP($A33,'[20]1'!$A$5:$E$1048576,3,0),0) | W33: =+IFERROR(VLOOKUP($A33,[21]Balance!$A$5:$E$1048576,3,0),0) | X33: =+IFERROR(VLOOKUP($A33,'[22]1'!$A$5:$E$1048576,3,0),0) | Y33: =+IFERROR(VLOOKUP($A33,[23]Лист1!$A$5:$E$1048576,3,0),0) | Z33: =+IFERROR(VLOOKUP($A33,'[24]1'!$A$5:$E$1048576,3,0),0) | AA33: =+IFERROR(VLOOKUP($A33,[25]Balance!$A$5:$E$1048576,3,0),0) | AB33: =+IFERROR(VLOOKUP($A33,'[26]1'!$A$5:$E$1048576,3,0),0) | AC33: =+IFERROR(VLOOKUP($A33,'[27]1'!$A$5:$E$1048576,3,0),0) | AD33: =+IFERROR(VLOOKUP($A33,'[28]1'!$A$5:$E$1048576,3,0),0) | AE33: =+IFERROR(VLOOKUP($A33,[29]Лист1!$A$5:$E$1048576,3,0),0) | AF33: =+IFERROR(VLOOKUP($A33,'[30]1'!$A$5:$E$1048576,3,0),0) | AG33: =+IFERROR(VLOOKUP($A33,'[31]1'!$A$5:$E$1048576,3,0),0) | AH33: =+IFERROR(VLOOKUP($A33,'[32]1-жадвал'!$A$5:$E$1048576,3,0),0) | AI33: =+IFERROR(VLOOKUP($A33,[33]Balance!$A$5:$E$1048576,3,0),0) | AJ33: =+IFERROR(VLOOKUP($A33,[34]Balance!$A$5:$E$1048576,3,0),0) | AK33: =+IFERROR(VLOOKUP($A33,'[35]1'!$A$5:$E$1048576,3,0),0)
A34: 11.2.1 | B34: Минус: Кўрилиши мумкин бўлган зарарларни қоплаш захираси | C34: =+IFERROR(VLOOKUP($A34,[1]Лист1!$A$5:$E$1048576,3,0),0) | D34: =+IFERROR(VLOOKUP($A34,'[2]1'!$A$5:$E$1048576,3,0),0) | E34: =+IFERROR(VLOOKUP($A34,'[3]1'!$A$5:$E$1048576,3,0),0) | F34: =+IFERROR(VLOOKUP($A34,[4]Balance!$A$5:$E$1048576,3,0),0) | G34: =+IFERROR(VLOOKUP($A34,'[5]1'!$A$5:$E$1048576,3,0),0) | H34: =+IFERROR(VLOOKUP($A34,[6]Balance!$A$5:$E$1048576,3,0),0) | I34: =+IFERROR(VLOOKUP($A34,[7]Balance!$A$5:$E$1048576,3,0),0) | J34: =+IFERROR(VLOOKUP($A34,'[8]1'!$A$5:$E$1048576,3,0),0) | K34: =+IFERROR(VLOOKUP($A34,'[9]1'!$A$5:$E$1048576,3,0),0) | L34: =+IFERROR(VLOOKUP($A34,'[10]1'!$A$5:$E$1048576,3,0),0) | M34: =+IFERROR(VLOOKUP($A34,'[11]1'!$A$5:$E$1048576,3,0),0) | N34: =+IFERROR(VLOOKUP($A34,[12]Balance!$A$5:$E$1048576,3,0),0) | O34: =+IFERROR(VLOOKUP($A34,'[13]1 т'!$A$5:$E$1048576,3,0),0) | P34: =+IFERROR(VLOOKUP($A34,[14]Balance!$A$5:$E$1048576,3,0),0) | Q34: =+IFERROR(VLOOKUP($A34,[15]Balance!$A$5:$E$1048576,3,0),0) | R34: =+IFERROR(VLOOKUP($A34,'[16]1'!$A$5:$E$1048576,3,0),0) | S34: =+IFERROR(VLOOKUP($A34,'[17]1'!$A$5:$E$1048576,3,0),0) | T34: =+IFERROR(VLOOKUP($A34,'[18]1'!$A$5:$E$1048576,3,0),0) | U34: =+IFERROR(VLOOKUP($A34,[19]Balans!$A$5:$E$1048576,3,0),0) | V34: =+IFERROR(VLOOKUP($A34,'[20]1'!$A$5:$E$1048576,3,0),0) | W34: =+IFERROR(VLOOKUP($A34,[21]Balance!$A$5:$E$1048576,3,0),0) | X34: =+IFERROR(VLOOKUP($A34,'[22]1'!$A$5:$E$1048576,3,0),0) | Y34: =+IFERROR(VLOOKUP($A34,[23]Лист1!$A$5:$E$1048576,3,0),0) | Z34: =+IFERROR(VLOOKUP($A34,'[24]1'!$A$5:$E$1048576,3,0),0) | AA34: =+IFERROR(VLOOKUP($A34,[25]Balance!$A$5:$E$1048576,3,0),0) | AB34: =+IFERROR(VLOOKUP($A34,'[26]1'!$A$5:$E$1048576,3,0),0) | AC34: =+IFERROR(VLOOKUP($A34,'[27]1'!$A$5:$E$1048576,3,0),0) | AD34: =+IFERROR(VLOOKUP($A34,'[28]1'!$A$5:$E$1048576,3,0),0) | AE34: =+IFERROR(VLOOKUP($A34,[29]Лист1!$A$5:$E$1048576,3,0),0) | AF34: =+IFERROR(VLOOKUP($A34,'[30]1'!$A$5:$E$1048576,3,0),0) | AG34: =+IFERROR(VLOOKUP($A34,'[31]1'!$A$5:$E$1048576,3,0),0) | AH34: =+IFERROR(VLOOKUP($A34,'[32]1-жадвал'!$A$5:$E$1048576,3,0),0) | AI34: =+IFERROR(VLOOKUP($A34,[33]Balance!$A$5:$E$1048576,3,0),0) | AJ34: =+IFERROR(VLOOKUP($A34,[34]Balance!$A$5:$E$1048576,3,0),0) | AK34: =+IFERROR(VLOOKUP($A34,'[35]1'!$A$5:$E$1048576,3,0),0)
A35: 12 | B35: Банкнинг бошқа хусусий мулклари, соф | C35: =+IFERROR(VLOOKUP($A35,[1]Лист1!$A$5:$E$1048576,3,0),0) | D35: =+IFERROR(VLOOKUP($A35,'[2]1'!$A$5:$E$1048576,3,0),0) | E35: =+IFERROR(VLOOKUP($A35,'[3]1'!$A$5:$E$1048576,3,0),0) | F35: =+IFERROR(VLOOKUP($A35,[4]Balance!$A$5:$E$1048576,3,0),0) | G35: =+IFERROR(VLOOKUP($A35,'[5]1'!$A$5:$E$1048576,3,0),0) | H35: =+IFERROR(VLOOKUP($A35,[6]Balance!$A$5:$E$1048576,3,0),0) | I35: =+IFERROR(VLOOKUP($A35,[7]Balance!$A$5:$E$1048576,3,0),0) | J35: =+IFERROR(VLOOKUP($A35,'[8]1'!$A$5:$E$1048576,3,0),0) | K35: =+IFERROR(VLOOKUP($A35,'[9]1'!$A$5:$E$1048576,3,0),0) | L35: =+IFERROR(VLOOKUP($A35,'[10]1'!$A$5:$E$1048576,3,0),0) | M35: =+IFERROR(VLOOKUP($A35,'[11]1'!$A$5:$E$1048576,3,0),0) | N35: =+IFERROR(VLOOKUP($A35,[12]Balance!$A$5:$E$1048576,3,0),0) | O35: =+IFERROR(VLOOKUP($A35,'[13]1 т'!$A$5:$E$1048576,3,0),0) | P35: =+IFERROR(VLOOKUP($A35,[14]Balance!$A$5:$E$1048576,3,0),0) | Q35: =+IFERROR(VLOOKUP($A35,[15]Balance!$A$5:$E$1048576,3,0),0) | R35: =+IFERROR(VLOOKUP($A35,'[16]1'!$A$5:$E$1048576,3,0),0) | S35: =+IFERROR(VLOOKUP($A35,'[17]1'!$A$5:$E$1048576,3,0),0) | T35: =+IFERROR(VLOOKUP($A35,'[18]1'!$A$5:$E$1048576,3,0),0) | U35: =+IFERROR(VLOOKUP($A35,[19]Balans!$A$5:$E$1048576,3,0),0) | V35: =+IFERROR(VLOOKUP($A35,'[20]1'!$A$5:$E$1048576,3,0),0) | W35: =+IFERROR(VLOOKUP($A35,[21]Balance!$A$5:$E$1048576,3,0),0) | X35: =+IFERROR(VLOOKUP($A35,'[22]1'!$A$5:$E$1048576,3,0),0) | Y35: =+IFERROR(VLOOKUP($A35,[23]Лист1!$A$5:$E$1048576,3,0),0) | Z35: =+IFERROR(VLOOKUP($A35,'[24]1'!$A$5:$E$1048576,3,0),0) | AA35: =+IFERROR(VLOOKUP($A35,[25]Balance!$A$5:$E$1048576,3,0),0) | AB35: =+IFERROR(VLOOKUP($A35,'[26]1'!$A$5:$E$1048576,3,0),0) | AC35: =+IFERROR(VLOOKUP($A35,'[27]1'!$A$5:$E$1048576,3,0),0) | AD35: =+IFERROR(VLOOKUP($A35,'[28]1'!$A$5:$E$1048576,3,0),0) | AE35: =+IFERROR(VLOOKUP($A35,[29]Лист1!$A$5:$E$1048576,3,0),0) | AF35: =+IFERROR(VLOOKUP($A35,'[30]1'!$A$5:$E$1048576,3,0),0) | AG35: =+IFERROR(VLOOKUP($A35,'[31]1'!$A$5:$E$1048576,3,0),0) | AH35: =+IFERROR(VLOOKUP($A35,'[32]1-жадвал'!$A$5:$E$1048576,3,0),0) | AI35: =+IFERROR(VLOOKUP($A35,[33]Balance!$A$5:$E$1048576,3,0),0) | AJ35: =+IFERROR(VLOOKUP($A35,[34]Balance!$A$5:$E$1048576,3,0),0) | AK35: =+IFERROR(VLOOKUP($A35,'[35]1'!$A$5:$E$1048576,3,0),0)
A36: 12.1 | B36: Кредит ва лизинг бўйича гаров ҳисобидан ундирилган бошқа мулклар, брутто | C36: =+IFERROR(VLOOKUP($A36,[1]Лист1!$A$5:$E$1048576,3,0),0) | D36: =+IFERROR(VLOOKUP($A36,'[2]1'!$A$5:$E$1048576,3,0),0) | E36: =+IFERROR(VLOOKUP($A36,'[3]1'!$A$5:$E$1048576,3,0),0) | F36: =+IFERROR(VLOOKUP($A36,[4]Balance!$A$5:$E$1048576,3,0),0) | G36: =+IFERROR(VLOOKUP($A36,'[5]1'!$A$5:$E$1048576,3,0),0) | H36: =+IFERROR(VLOOKUP($A36,[6]Balance!$A$5:$E$1048576,3,0),0) | I36: =+IFERROR(VLOOKUP($A36,[7]Balance!$A$5:$E$1048576,3,0),0) | J36: =+IFERROR(VLOOKUP($A36,'[8]1'!$A$5:$E$1048576,3,0),0) | K36: =+IFERROR(VLOOKUP($A36,'[9]1'!$A$5:$E$1048576,3,0),0) | L36: =+IFERROR(VLOOKUP($A36,'[10]1'!$A$5:$E$1048576,3,0),0) | M36: =+IFERROR(VLOOKUP($A36,'[11]1'!$A$5:$E$1048576,3,0),0) | N36: =+IFERROR(VLOOKUP($A36,[12]Balance!$A$5:$E$1048576,3,0),0) | O36: =+IFERROR(VLOOKUP($A36,'[13]1 т'!$A$5:$E$1048576,3,0),0) | P36: =+IFERROR(VLOOKUP($A36,[14]Balance!$A$5:$E$1048576,3,0),0) | Q36: =+IFERROR(VLOOKUP($A36,[15]Balance!$A$5:$E$1048576,3,0),0) | R36: =+IFERROR(VLOOKUP($A36,'[16]1'!$A$5:$E$1048576,3,0),0) | S36: =+IFERROR(VLOOKUP($A36,'[17]1'!$A$5:$E$1048576,3,0),0) | T36: =+IFERROR(VLOOKUP($A36,'[18]1'!$A$5:$E$1048576,3,0),0) | U36: =+IFERROR(VLOOKUP($A36,[19]Balans!$A$5:$E$1048576,3,0),0) | V36: =+IFERROR(VLOOKUP($A36,'[20]1'!$A$5:$E$1048576,3,0),0) | W36: =+IFERROR(VLOOKUP($A36,[21]Balance!$A$5:$E$1048576,3,0),0) | X36: =+IFERROR(VLOOKUP($A36,'[22]1'!$A$5:$E$1048576,3,0),0) | Y36: =+IFERROR(VLOOKUP($A36,[23]Лист1!$A$5:$E$1048576,3,0),0) | Z36: =+IFERROR(VLOOKUP($A36,'[24]1'!$A$5:$E$1048576,3,0),0) | AA36: =+IFERROR(VLOOKUP($A36,[25]Balance!$A$5:$E$1048576,3,0),0) | AB36: =+IFERROR(VLOOKUP($A36,'[26]1'!$A$5:$E$1048576,3,0),0) | AC36: =+IFERROR(VLOOKUP($A36,'[27]1'!$A$5:$E$1048576,3,0),0) | AD36: =+IFERROR(VLOOKUP($A36,'[28]1'!$A$5:$E$1048576,3,0),0) | AE36: =+IFERROR(VLOOKUP($A36,[29]Лист1!$A$5:$E$1048576,3,0),0) | AF36: =+IFERROR(VLOOKUP($A36,'[30]1'!$A$5:$E$1048576,3,0),0) | AG36: =+IFERROR(VLOOKUP($A36,'[31]1'!$A$5:$E$1048576,3,0),0) | AH36: =+IFERROR(VLOOKUP($A36,'[32]1-жадвал'!$A$5:$E$1048576,3,0),0) | AI36: =+IFERROR(VLOOKUP($A36,[33]Balance!$A$5:$E$1048576,3,0),0) | AJ36: =+IFERROR(VLOOKUP($A36,[34]Balance!$A$5:$E$1048576,3,0),0) | AK36: =+IFERROR(VLOOKUP($A36,'[35]1'!$A$5:$E$1048576,3,0),0)
A37: 12.2 | B37: Банкнинг бошқа хусусий мулклари, брутто | C37: =+IFERROR(VLOOKUP($A37,[1]Лист1!$A$5:$E$1048576,3,0),0) | D37: =+IFERROR(VLOOKUP($A37,'[2]1'!$A$5:$E$1048576,3,0),0) | E37: =+IFERROR(VLOOKUP($A37,'[3]1'!$A$5:$E$1048576,3,0),0) | F37: =+IFERROR(VLOOKUP($A37,[4]Balance!$A$5:$E$1048576,3,0),0) | G37: =+IFERROR(VLOOKUP($A37,'[5]1'!$A$5:$E$1048576,3,0),0) | H37: =+IFERROR(VLOOKUP($A37,[6]Balance!$A$5:$E$1048576,3,0),0) | I37: =+IFERROR(VLOOKUP($A37,[7]Balance!$A$5:$E$1048576,3,0),0) | J37: =+IFERROR(VLOOKUP($A37,'[8]1'!$A$5:$E$1048576,3,0),0) | K37: =+IFERROR(VLOOKUP($A37,'[9]1'!$A$5:$E$1048576,3,0),0) | L37: =+IFERROR(VLOOKUP($A37,'[10]1'!$A$5:$E$1048576,3,0),0) | M37: =+IFERROR(VLOOKUP($A37,'[11]1'!$A$5:$E$1048576,3,0),0) | N37: =+IFERROR(VLOOKUP($A37,[12]Balance!$A$5:$E$1048576,3,0),0) | O37: =+IFERROR(VLOOKUP($A37,'[13]1 т'!$A$5:$E$1048576,3,0),0) | P37: =+IFERROR(VLOOKUP($A37,[14]Balance!$A$5:$E$1048576,3,0),0) | Q37: =+IFERROR(VLOOKUP($A37,[15]Balance!$A$5:$E$1048576,3,0),0) | R37: =+IFERROR(VLOOKUP($A37,'[16]1'!$A$5:$E$1048576,3,0),0) | S37: =+IFERROR(VLOOKUP($A37,'[17]1'!$A$5:$E$1048576,3,0),0) | T37: =+IFERROR(VLOOKUP($A37,'[18]1'!$A$5:$E$1048576,3,0),0) | U37: =+IFERROR(VLOOKUP($A37,[19]Balans!$A$5:$E$1048576,3,0),0) | V37: =+IFERROR(VLOOKUP($A37,'[20]1'!$A$5:$E$1048576,3,0),0) | W37: =+IFERROR(VLOOKUP($A37,[21]Balance!$A$5:$E$1048576,3,0),0) | X37: =+IFERROR(VLOOKUP($A37,'[22]1'!$A$5:$E$1048576,3,0),0) | Y37: =+IFERROR(VLOOKUP($A37,[23]Лист1!$A$5:$E$1048576,3,0),0) | Z37: =+IFERROR(VLOOKUP($A37,'[24]1'!$A$5:$E$1048576,3,0),0) | AA37: =+IFERROR(VLOOKUP($A37,[25]Balance!$A$5:$E$1048576,3,0),0) | AB37: =+IFERROR(VLOOKUP($A37,'[26]1'!$A$5:$E$1048576,3,0),0) | AC37: =+IFERROR(VLOOKUP($A37,'[27]1'!$A$5:$E$1048576,3,0),0) | AD37: =+IFERROR(VLOOKUP($A37,'[28]1'!$A$5:$E$1048576,3,0),0) | AE37: =+IFERROR(VLOOKUP($A37,[29]Лист1!$A$5:$E$1048576,3,0),0) | AF37: =+IFERROR(VLOOKUP($A37,'[30]1'!$A$5:$E$1048576,3,0),0) | AG37: =+IFERROR(VLOOKUP($A37,'[31]1'!$A$5:$E$1048576,3,0),0) | AH37: =+IFERROR(VLOOKUP($A37,'[32]1-жадвал'!$A$5:$E$1048576,3,0),0) | AI37: =+IFERROR(VLOOKUP($A37,[33]Balance!$A$5:$E$1048576,3,0),0) | AJ37: =+IFERROR(VLOOKUP($A37,[34]Balance!$A$5:$E$1048576,3,0),0) | AK37: =+IFERROR(VLOOKUP($A37,'[35]1'!$A$5:$E$1048576,3,0),0)
A38: 12.3 | B38: Минус: Йиғилган эскириш суммаси ва кўрилиши мумкин бўлган зарарларни қоплаш захираси | C38: =+IFERROR(VLOOKUP($A38,[1]Лист1!$A$5:$E$1048576,3,0),0) | D38: =+IFERROR(VLOOKUP($A38,'[2]1'!$A$5:$E$1048576,3,0),0) | E38: =+IFERROR(VLOOKUP($A38,'[3]1'!$A$5:$E$1048576,3,0),0) | F38: =+IFERROR(VLOOKUP($A38,[4]Balance!$A$5:$E$1048576,3,0),0) | G38: =+IFERROR(VLOOKUP($A38,'[5]1'!$A$5:$E$1048576,3,0),0) | H38: =+IFERROR(VLOOKUP($A38,[6]Balance!$A$5:$E$1048576,3,0),0) | I38: =+IFERROR(VLOOKUP($A38,[7]Balance!$A$5:$E$1048576,3,0),0) | J38: =+IFERROR(VLOOKUP($A38,'[8]1'!$A$5:$E$1048576,3,0),0) | K38: =+IFERROR(VLOOKUP($A38,'[9]1'!$A$5:$E$1048576,3,0),0) | L38: =+IFERROR(VLOOKUP($A38,'[10]1'!$A$5:$E$1048576,3,0),0) | M38: =+IFERROR(VLOOKUP($A38,'[11]1'!$A$5:$E$1048576,3,0),0) | N38: =+IFERROR(VLOOKUP($A38,[12]Balance!$A$5:$E$1048576,3,0),0) | O38: =+IFERROR(VLOOKUP($A38,'[13]1 т'!$A$5:$E$1048576,3,0),0) | P38: =+IFERROR(VLOOKUP($A38,[14]Balance!$A$5:$E$1048576,3,0),0) | Q38: =+IFERROR(VLOOKUP($A38,[15]Balance!$A$5:$E$1048576,3,0),0) | R38: =+IFERROR(VLOOKUP($A38,'[16]1'!$A$5:$E$1048576,3,0),0) | S38: =+IFERROR(VLOOKUP($A38,'[17]1'!$A$5:$E$1048576,3,0),0) | T38: =+IFERROR(VLOOKUP($A38,'[18]1'!$A$5:$E$1048576,3,0),0) | U38: =+IFERROR(VLOOKUP($A38,[19]Balans!$A$5:$E$1048576,3,0),0) | V38: =+IFERROR(VLOOKUP($A38,'[20]1'!$A$5:$E$1048576,3,0),0) | W38: =+IFERROR(VLOOKUP($A38,[21]Balance!$A$5:$E$1048576,3,0),0) | X38: =+IFERROR(VLOOKUP($A38,'[22]1'!$A$5:$E$1048576,3,0),0) | Y38: =+IFERROR(VLOOKUP($A38,[23]Лист1!$A$5:$E$1048576,3,0),0) | Z38: =+IFERROR(VLOOKUP($A38,'[24]1'!$A$5:$E$1048576,3,0),0) | AA38: =+IFERROR(VLOOKUP($A38,[25]Balance!$A$5:$E$1048576,3,0),0) | AB38: =+IFERROR(VLOOKUP($A38,'[26]1'!$A$5:$E$1048576,3,0),0) | AC38: =+IFERROR(VLOOKUP($A38,'[27]1'!$A$5:$E$1048576,3,0),0) | AD38: =+IFERROR(VLOOKUP($A38,'[28]1'!$A$5:$E$1048576,3,0),0) | AE38: =+IFERROR(VLOOKUP($A38,[29]Лист1!$A$5:$E$1048576,3,0),0) | AF38: =+IFERROR(VLOOKUP($A38,'[30]1'!$A$5:$E$1048576,3,0),0) | AG38: =+IFERROR(VLOOKUP($A38,'[31]1'!$A$5:$E$1048576,3,0),0) | AH38: =+IFERROR(VLOOKUP($A38,'[32]1-жадвал'!$A$5:$E$1048576,3,0),0) | AI38: =+IFERROR(VLOOKUP($A38,[33]Balance!$A$5:$E$1048576,3,0),0) | AJ38: =+IFERROR(VLOOKUP($A38,[34]Balance!$A$5:$E$1048576,3,0),0) | AK38: =+IFERROR(VLOOKUP($A38,'[35]1'!$A$5:$E$1048576,3,0),0)
A39: 13 | B39: Стандарт деб таснифланган активлар бўйича яратилган захиралар | C39: =+IFERROR(VLOOKUP($A39,[1]Лист1!$A$5:$E$1048576,3,0),0) | D39: =+IFERROR(VLOOKUP($A39,'[2]1'!$A$5:$E$1048576,3,0),0) | E39: =+IFERROR(VLOOKUP($A39,'[3]1'!$A$5:$E$1048576,3,0),0) | F39: =+IFERROR(VLOOKUP($A39,[4]Balance!$A$5:$E$1048576,3,0),0) | G39: =+IFERROR(VLOOKUP($A39,'[5]1'!$A$5:$E$1048576,3,0),0) | H39: =+IFERROR(VLOOKUP($A39,[6]Balance!$A$5:$E$1048576,3,0),0) | I39: =+IFERROR(VLOOKUP($A39,[7]Balance!$A$5:$E$1048576,3,0),0) | J39: =+IFERROR(VLOOKUP($A39,'[8]1'!$A$5:$E$1048576,3,0),0) | K39: =+IFERROR(VLOOKUP($A39,'[9]1'!$A$5:$E$1048576,3,0),0) | L39: =+IFERROR(VLOOKUP($A39,'[10]1'!$A$5:$E$1048576,3,0),0) | M39: =+IFERROR(VLOOKUP($A39,'[11]1'!$A$5:$E$1048576,3,0),0) | N39: =+IFERROR(VLOOKUP($A39,[12]Balance!$A$5:$E$1048576,3,0),0) | O39: =+IFERROR(VLOOKUP($A39,'[13]1 т'!$A$5:$E$1048576,3,0),0) | P39: =+IFERROR(VLOOKUP($A39,[14]Balance!$A$5:$E$1048576,3,0),0) | Q39: =+IFERROR(VLOOKUP($A39,[15]Balance!$A$5:$E$1048576,3,0),0) | R39: =+IFERROR(VLOOKUP($A39,'[16]1'!$A$5:$E$1048576,3,0),0) | S39: =+IFERROR(VLOOKUP($A39,'[17]1'!$A$5:$E$1048576,3,0),0) | T39: =+IFERROR(VLOOKUP($A39,'[18]1'!$A$5:$E$1048576,3,0),0) | U39: =+IFERROR(VLOOKUP($A39,[19]Balans!$A$5:$E$1048576,3,0),0) | V39: =+IFERROR(VLOOKUP($A39,'[20]1'!$A$5:$E$1048576,3,0),0) | W39: =+IFERROR(VLOOKUP($A39,[21]Balance!$A$5:$E$1048576,3,0),0) | X39: =+IFERROR(VLOOKUP($A39,'[22]1'!$A$5:$E$1048576,3,0),0) | Y39: =+IFERROR(VLOOKUP($A39,[23]Лист1!$A$5:$E$1048576,3,0),0) | Z39: =+IFERROR(VLOOKUP($A39,'[24]1'!$A$5:$E$1048576,3,0),0) | AA39: =+IFERROR(VLOOKUP($A39,[25]Balance!$A$5:$E$1048576,3,0),0) | AB39: =+IFERROR(VLOOKUP($A39,'[26]1'!$A$5:$E$1048576,3,0),0) | AC39: =+IFERROR(VLOOKUP($A39,'[27]1'!$A$5:$E$1048576,3,0),0) | AD39: =+IFERROR(VLOOKUP($A39,'[28]1'!$A$5:$E$1048576,3,0),0) | AE39: =+IFERROR(VLOOKUP($A39,[29]Лист1!$A$5:$E$1048576,3,0),0) | AF39: =+IFERROR(VLOOKUP($A39,'[30]1'!$A$5:$E$1048576,3,0),0) | AG39: =+IFERROR(VLOOKUP($A39,'[31]1'!$A$5:$E$1048576,3,0),0) | AH39: =+IFERROR(VLOOKUP($A39,'[32]1-жадвал'!$A$5:$E$1048576,3,0),0) | AI39: =+IFERROR(VLOOKUP($A39,[33]Balance!$A$5:$E$1048576,3,0),0) | AJ39: =+IFERROR(VLOOKUP($A39,[34]Balance!$A$5:$E$1048576,3,0),0) | AK39: =+IFERROR(VLOOKUP($A39,'[35]1'!$A$5:$E$1048576,3,0),0)
A40: 13.1 | B40: Стандарт деб таснифланган кредитлар, лизинг ва факторинг бўйича захира | C40: =+IFERROR(VLOOKUP($A40,[1]Лист1!$A$5:$E$1048576,3,0),0) | D40: =+IFERROR(VLOOKUP($A40,'[2]1'!$A$5:$E$1048576,3,0),0) | E40: =+IFERROR(VLOOKUP($A40,'[3]1'!$A$5:$E$1048576,3,0),0) | F40: =+IFERROR(VLOOKUP($A40,[4]Balance!$A$5:$E$1048576,3,0),0) | G40: =+IFERROR(VLOOKUP($A40,'[5]1'!$A$5:$E$1048576,3,0),0) | H40: =+IFERROR(VLOOKUP($A40,[6]Balance!$A$5:$E$1048576,3,0),0) | I40: =+IFERROR(VLOOKUP($A40,[7]Balance!$A$5:$E$1048576,3,0),0) | J40: =+IFERROR(VLOOKUP($A40,'[8]1'!$A$5:$E$1048576,3,0),0) | K40: =+IFERROR(VLOOKUP($A40,'[9]1'!$A$5:$E$1048576,3,0),0) | L40: =+IFERROR(VLOOKUP($A40,'[10]1'!$A$5:$E$1048576,3,0),0) | M40: =+IFERROR(VLOOKUP($A40,'[11]1'!$A$5:$E$1048576,3,0),0) | N40: =+IFERROR(VLOOKUP($A40,[12]Balance!$A$5:$E$1048576,3,0),0) | O40: =+IFERROR(VLOOKUP($A40,'[13]1 т'!$A$5:$E$1048576,3,0),0) | P40: =+IFERROR(VLOOKUP($A40,[14]Balance!$A$5:$E$1048576,3,0),0) | Q40: =+IFERROR(VLOOKUP($A40,[15]Balance!$A$5:$E$1048576,3,0),0) | R40: =+IFERROR(VLOOKUP($A40,'[16]1'!$A$5:$E$1048576,3,0),0) | S40: =+IFERROR(VLOOKUP($A40,'[17]1'!$A$5:$E$1048576,3,0),0) | T40: =+IFERROR(VLOOKUP($A40,'[18]1'!$A$5:$E$1048576,3,0),0) | U40: =+IFERROR(VLOOKUP($A40,[19]Balans!$A$5:$E$1048576,3,0),0) | V40: =+IFERROR(VLOOKUP($A40,'[20]1'!$A$5:$E$1048576,3,0),0) | W40: =+IFERROR(VLOOKUP($A40,[21]Balance!$A$5:$E$1048576,3,0),0) | X40: =+IFERROR(VLOOKUP($A40,'[22]1'!$A$5:$E$1048576,3,0),0) | Y40: =+IFERROR(VLOOKUP($A40,[23]Лист1!$A$5:$E$1048576,3,0),0) | Z40: =+IFERROR(VLOOKUP($A40,'[24]1'!$A$5:$E$1048576,3,0),0) | AA40: =+IFERROR(VLOOKUP($A40,[25]Balance!$A$5:$E$1048576,3,0),0) | AB40: =+IFERROR(VLOOKUP($A40,'[26]1'!$A$5:$E$1048576,3,0),0) | AC40: =+IFERROR(VLOOKUP($A40,'[27]1'!$A$5:$E$1048576,3,0),0) | AD40: =+IFERROR(VLOOKUP($A40,'[28]1'!$A$5:$E$1048576,3,0),0) | AE40: =+IFERROR(VLOOKUP($A40,[29]Лист1!$A$5:$E$1048576,3,0),0) | AF40: =+IFERROR(VLOOKUP($A40,'[30]1'!$A$5:$E$1048576,3,0),0) | AG40: =+IFERROR(VLOOKUP($A40,'[31]1'!$A$5:$E$1048576,3,0),0) | AH40: =+IFERROR(VLOOKUP($A40,'[32]1-жадвал'!$A$5:$E$1048576,3,0),0) | AI40: =+IFERROR(VLOOKUP($A40,[33]Balance!$A$5:$E$1048576,3,0),0) | AJ40: =+IFERROR(VLOOKUP($A40,[34]Balance!$A$5:$E$1048576,3,0),0) | AK40: =+IFERROR(VLOOKUP($A40,'[35]1'!$A$5:$E$1048576,3,0),0)
A41: 13.2 | B41: Стандарт деб таснифланган бошқа активлар бўйича захира | C41: =+IFERROR(VLOOKUP($A41,[1]Лист1!$A$5:$E$1048576,3,0),0) | D41: =+IFERROR(VLOOKUP($A41,'[2]1'!$A$5:$E$1048576,3,0),0) | E41: =+IFERROR(VLOOKUP($A41,'[3]1'!$A$5:$E$1048576,3,0),0) | F41: =+IFERROR(VLOOKUP($A41,[4]Balance!$A$5:$E$1048576,3,0),0) | G41: =+IFERROR(VLOOKUP($A41,'[5]1'!$A$5:$E$1048576,3,0),0) | H41: =+IFERROR(VLOOKUP($A41,[6]Balance!$A$5:$E$1048576,3,0),0) | I41: =+IFERROR(VLOOKUP($A41,[7]Balance!$A$5:$E$1048576,3,0),0) | J41: =+IFERROR(VLOOKUP($A41,'[8]1'!$A$5:$E$1048576,3,0),0) | K41: =+IFERROR(VLOOKUP($A41,'[9]1'!$A$5:$E$1048576,3,0),0) | L41: =+IFERROR(VLOOKUP($A41,'[10]1'!$A$5:$E$1048576,3,0),0) | M41: =+IFERROR(VLOOKUP($A41,'[11]1'!$A$5:$E$1048576,3,0),0) | N41: =+IFERROR(VLOOKUP($A41,[12]Balance!$A$5:$E$1048576,3,0),0) | O41: =+IFERROR(VLOOKUP($A41,'[13]1 т'!$A$5:$E$1048576,3,0),0) | P41: =+IFERROR(VLOOKUP($A41,[14]Balance!$A$5:$E$1048576,3,0),0) | Q41: =+IFERROR(VLOOKUP($A41,[15]Balance!$A$5:$E$1048576,3,0),0) | R41: =+IFERROR(VLOOKUP($A41,'[16]1'!$A$5:$E$1048576,3,0),0) | S41: =+IFERROR(VLOOKUP($A41,'[17]1'!$A$5:$E$1048576,3,0),0) | T41: =+IFERROR(VLOOKUP($A41,'[18]1'!$A$5:$E$1048576,3,0),0) | U41: =+IFERROR(VLOOKUP($A41,[19]Balans!$A$5:$E$1048576,3,0),0) | V41: =+IFERROR(VLOOKUP($A41,'[20]1'!$A$5:$E$1048576,3,0),0) | W41: =+IFERROR(VLOOKUP($A41,[21]Balance!$A$5:$E$1048576,3,0),0) | X41: =+IFERROR(VLOOKUP($A41,'[22]1'!$A$5:$E$1048576,3,0),0) | Y41: =+IFERROR(VLOOKUP($A41,[23]Лист1!$A$5:$E$1048576,3,0),0) | Z41: =+IFERROR(VLOOKUP($A41,'[24]1'!$A$5:$E$1048576,3,0),0) | AA41: =+IFERROR(VLOOKUP($A41,[25]Balance!$A$5:$E$1048576,3,0),0) | AB41: =+IFERROR(VLOOKUP($A41,'[26]1'!$A$5:$E$1048576,3,0),0) | AC41: =+IFERROR(VLOOKUP($A41,'[27]1'!$A$5:$E$1048576,3,0),0) | AD41: =+IFERROR(VLOOKUP($A41,'[28]1'!$A$5:$E$1048576,3,0),0) | AE41: =+IFERROR(VLOOKUP($A41,[29]Лист1!$A$5:$E$1048576,3,0),0) | AF41: =+IFERROR(VLOOKUP($A41,'[30]1'!$A$5:$E$1048576,3,0),0) | AG41: =+IFERROR(VLOOKUP($A41,'[31]1'!$A$5:$E$1048576,3,0),0) | AH41: =+IFERROR(VLOOKUP($A41,'[32]1-жадвал'!$A$5:$E$1048576,3,0),0) | AI41: =+IFERROR(VLOOKUP($A41,[33]Balance!$A$5:$E$1048576,3,0),0) | AJ41: =+IFERROR(VLOOKUP($A41,[34]Balance!$A$5:$E$1048576,3,0),0) | AK41: =+IFERROR(VLOOKUP($A41,'[35]1'!$A$5:$E$1048576,3,0),0)
A42: 13.3 | B42: Стандарт деб таснифланган активлар бўйича фоизлар ва воситачилик ҳақларига оид захира | C42: =+IFERROR(VLOOKUP($A42,[1]Лист1!$A$5:$E$1048576,3,0),0) | D42: =+IFERROR(VLOOKUP($A42,'[2]1'!$A$5:$E$1048576,3,0),0) | E42: =+IFERROR(VLOOKUP($A42,'[3]1'!$A$5:$E$1048576,3,0),0) | F42: =+IFERROR(VLOOKUP($A42,[4]Balance!$A$5:$E$1048576,3,0),0) | G42: =+IFERROR(VLOOKUP($A42,'[5]1'!$A$5:$E$1048576,3,0),0) | H42: =+IFERROR(VLOOKUP($A42,[6]Balance!$A$5:$E$1048576,3,0),0) | I42: =+IFERROR(VLOOKUP($A42,[7]Balance!$A$5:$E$1048576,3,0),0) | J42: =+IFERROR(VLOOKUP($A42,'[8]1'!$A$5:$E$1048576,3,0),0) | K42: =+IFERROR(VLOOKUP($A42,'[9]1'!$A$5:$E$1048576,3,0),0) | L42: =+IFERROR(VLOOKUP($A42,'[10]1'!$A$5:$E$1048576,3,0),0) | M42: =+IFERROR(VLOOKUP($A42,'[11]1'!$A$5:$E$1048576,3,0),0) | N42: =+IFERROR(VLOOKUP($A42,[12]Balance!$A$5:$E$1048576,3,0),0) | O42: =+IFERROR(VLOOKUP($A42,'[13]1 т'!$A$5:$E$1048576,3,0),0) | P42: =+IFERROR(VLOOKUP($A42,[14]Balance!$A$5:$E$1048576,3,0),0) | Q42: =+IFERROR(VLOOKUP($A42,[15]Balance!$A$5:$E$1048576,3,0),0) | R42: =+IFERROR(VLOOKUP($A42,'[16]1'!$A$5:$E$1048576,3,0),0) | S42: =+IFERROR(VLOOKUP($A42,'[17]1'!$A$5:$E$1048576,3,0),0) | T42: =+IFERROR(VLOOKUP($A42,'[18]1'!$A$5:$E$1048576,3,0),0) | U42: =+IFERROR(VLOOKUP($A42,[19]Balans!$A$5:$E$1048576,3,0),0) | V42: =+IFERROR(VLOOKUP($A42,'[20]1'!$A$5:$E$1048576,3,0),0) | W42: =+IFERROR(VLOOKUP($A42,[21]Balance!$A$5:$E$1048576,3,0),0) | X42: =+IFERROR(VLOOKUP($A42,'[22]1'!$A$5:$E$1048576,3,0),0) | Y42: =+IFERROR(VLOOKUP($A42,[23]Лист1!$A$5:$E$1048576,3,0),0) | Z42: =+IFERROR(VLOOKUP($A42,'[24]1'!$A$5:$E$1048576,3,0),0) | AA42: =+IFERROR(VLOOKUP($A42,[25]Balance!$A$5:$E$1048576,3,0),0) | AB42: =+IFERROR(VLOOKUP($A42,'[26]1'!$A$5:$E$1048576,3,0),0) | AC42: =+IFERROR(VLOOKUP($A42,'[27]1'!$A$5:$E$1048576,3,0),0) | AD42: =+IFERROR(VLOOKUP($A42,'[28]1'!$A$5:$E$1048576,3,0),0) | AE42: =+IFERROR(VLOOKUP($A42,[29]Лист1!$A$5:$E$1048576,3,0),0) | AF42: =+IFERROR(VLOOKUP($A42,'[30]1'!$A$5:$E$1048576,3,0),0) | AG42: =+IFERROR(VLOOKUP($A42,'[31]1'!$A$5:$E$1048576,3,0),0) | AH42: =+IFERROR(VLOOKUP($A42,'[32]1-жадвал'!$A$5:$E$1048576,3,0),0) | AI42: =+IFERROR(VLOOKUP($A42,[33]Balance!$A$5:$E$1048576,3,0),0) | AJ42: =+IFERROR(VLOOKUP($A42,[34]Balance!$A$5:$E$1048576,3,0),0) | AK42: =+IFERROR(VLOOKUP($A42,'[35]1'!$A$5:$E$1048576,3,0),0)
A43: 14 | B43: Бошқа активлар, соф | C43: =+IFERROR(VLOOKUP($A43,[1]Лист1!$A$5:$E$1048576,3,0),0) | D43: =+IFERROR(VLOOKUP($A43,'[2]1'!$A$5:$E$1048576,3,0),0) | E43: =+IFERROR(VLOOKUP($A43,'[3]1'!$A$5:$E$1048576,3,0),0) | F43: =+IFERROR(VLOOKUP($A43,[4]Balance!$A$5:$E$1048576,3,0),0) | G43: =+IFERROR(VLOOKUP($A43,'[5]1'!$A$5:$E$1048576,3,0),0) | H43: =+IFERROR(VLOOKUP($A43,[6]Balance!$A$5:$E$1048576,3,0),0) | I43: =+IFERROR(VLOOKUP($A43,[7]Balance!$A$5:$E$1048576,3,0),0) | J43: =+IFERROR(VLOOKUP($A43,'[8]1'!$A$5:$E$1048576,3,0),0) | K43: =+IFERROR(VLOOKUP($A43,'[9]1'!$A$5:$E$1048576,3,0),0) | L43: =+IFERROR(VLOOKUP($A43,'[10]1'!$A$5:$E$1048576,3,0),0) | M43: =+IFERROR(VLOOKUP($A43,'[11]1'!$A$5:$E$1048576,3,0),0) | N43: =+IFERROR(VLOOKUP($A43,[12]Balance!$A$5:$E$1048576,3,0),0) | O43: =+IFERROR(VLOOKUP($A43,'[13]1 т'!$A$5:$E$1048576,3,0),0) | P43: =+IFERROR(VLOOKUP($A43,[14]Balance!$A$5:$E$1048576,3,0),0) | Q43: =+IFERROR(VLOOKUP($A43,[15]Balance!$A$5:$E$1048576,3,0),0) | R43: =+IFERROR(VLOOKUP($A43,'[16]1'!$A$5:$E$1048576,3,0),0) | S43: =+IFERROR(VLOOKUP($A43,'[17]1'!$A$5:$E$1048576,3,0),0) | T43: =+IFERROR(VLOOKUP($A43,'[18]1'!$A$5:$E$1048576,3,0),0) | U43: =+IFERROR(VLOOKUP($A43,[19]Balans!$A$5:$E$1048576,3,0),0) | V43: =+IFERROR(VLOOKUP($A43,'[20]1'!$A$5:$E$1048576,3,0),0) | W43: =+IFERROR(VLOOKUP($A43,[21]Balance!$A$5:$E$1048576,3,0),0) | X43: =+IFERROR(VLOOKUP($A43,'[22]1'!$A$5:$E$1048576,3,0),0) | Y43: =+IFERROR(VLOOKUP($A43,[23]Лист1!$A$5:$E$1048576,3,0),0) | Z43: =+IFERROR(VLOOKUP($A43,'[24]1'!$A$5:$E$1048576,3,0),0) | AA43: =+IFERROR(VLOOKUP($A43,[25]Balance!$A$5:$E$1048576,3,0),0) | AB43: =+IFERROR(VLOOKUP($A43,'[26]1'!$A$5:$E$1048576,3,0),0) | AC43: =+IFERROR(VLOOKUP($A43,'[27]1'!$A$5:$E$1048576,3,0),0) | AD43: =+IFERROR(VLOOKUP($A43,'[28]1'!$A$5:$E$1048576,3,0),0) | AE43: =+IFERROR(VLOOKUP($A43,[29]Лист1!$A$5:$E$1048576,3,0),0) | AF43: =+IFERROR(VLOOKUP($A43,'[30]1'!$A$5:$E$1048576,3,0),0) | AG43: =+IFERROR(VLOOKUP($A43,'[31]1'!$A$5:$E$1048576,3,0),0) | AH43: =+IFERROR(VLOOKUP($A43,'[32]1-жадвал'!$A$5:$E$1048576,3,0),0) | AI43: =+IFERROR(VLOOKUP($A43,[33]Balance!$A$5:$E$1048576,3,0),0) | AJ43: =+IFERROR(VLOOKUP($A43,[34]Balance!$A$5:$E$1048576,3,0),0) | AK43: =+IFERROR(VLOOKUP($A43,'[35]1'!$A$5:$E$1048576,3,0),0)
A44: 14.1 | B44: Бошқа активлар, брутто | C44: =+IFERROR(VLOOKUP($A44,[1]Лист1!$A$5:$E$1048576,3,0),0) | D44: =+IFERROR(VLOOKUP($A44,'[2]1'!$A$5:$E$1048576,3,0),0) | E44: =+IFERROR(VLOOKUP($A44,'[3]1'!$A$5:$E$1048576,3,0),0) | F44: =+IFERROR(VLOOKUP($A44,[4]Balance!$A$5:$E$1048576,3,0),0) | G44: =+IFERROR(VLOOKUP($A44,'[5]1'!$A$5:$E$1048576,3,0),0) | H44: =+IFERROR(VLOOKUP($A44,[6]Balance!$A$5:$E$1048576,3,0),0) | I44: =+IFERROR(VLOOKUP($A44,[7]Balance!$A$5:$E$1048576,3,0),0) | J44: =+IFERROR(VLOOKUP($A44,'[8]1'!$A$5:$E$1048576,3,0),0) | K44: =+IFERROR(VLOOKUP($A44,'[9]1'!$A$5:$E$1048576,3,0),0) | L44: =+IFERROR(VLOOKUP($A44,'[10]1'!$A$5:$E$1048576,3,0),0) | M44: =+IFERROR(VLOOKUP($A44,'[11]1'!$A$5:$E$1048576,3,0),0) | N44: =+IFERROR(VLOOKUP($A44,[12]Balance!$A$5:$E$1048576,3,0),0) | O44: =+IFERROR(VLOOKUP($A44,'[13]1 т'!$A$5:$E$1048576,3,0),0) | P44: =+IFERROR(VLOOKUP($A44,[14]Balance!$A$5:$E$1048576,3,0),0) | Q44: =+IFERROR(VLOOKUP($A44,[15]Balance!$A$5:$E$1048576,3,0),0) | R44: =+IFERROR(VLOOKUP($A44,'[16]1'!$A$5:$E$1048576,3,0),0) | S44: =+IFERROR(VLOOKUP($A44,'[17]1'!$A$5:$E$1048576,3,0),0) | T44: =+IFERROR(VLOOKUP($A44,'[18]1'!$A$5:$E$1048576,3,0),0) | U44: =+IFERROR(VLOOKUP($A44,[19]Balans!$A$5:$E$1048576,3,0),0) | V44: =+IFERROR(VLOOKUP($A44,'[20]1'!$A$5:$E$1048576,3,0),0) | W44: =+IFERROR(VLOOKUP($A44,[21]Balance!$A$5:$E$1048576,3,0),0) | X44: =+IFERROR(VLOOKUP($A44,'[22]1'!$A$5:$E$1048576,3,0),0) | Y44: =+IFERROR(VLOOKUP($A44,[23]Лист1!$A$5:$E$1048576,3,0),0) | Z44: =+IFERROR(VLOOKUP($A44,'[24]1'!$A$5:$E$1048576,3,0),0) | AA44: =+IFERROR(VLOOKUP($A44,[25]Balance!$A$5:$E$1048576,3,0),0) | AB44: =+IFERROR(VLOOKUP($A44,'[26]1'!$A$5:$E$1048576,3,0),0) | AC44: =+IFERROR(VLOOKUP($A44,'[27]1'!$A$5:$E$1048576,3,0),0) | AD44: =+IFERROR(VLOOKUP($A44,'[28]1'!$A$5:$E$1048576,3,0),0) | AE44: =+IFERROR(VLOOKUP($A44,[29]Лист1!$A$5:$E$1048576,3,0),0) | AF44: =+IFERROR(VLOOKUP($A44,'[30]1'!$A$5:$E$1048576,3,0),0) | AG44: =+IFERROR(VLOOKUP($A44,'[31]1'!$A$5:$E$1048576,3,0),0) | AH44: =+IFERROR(VLOOKUP($A44,'[32]1-жадвал'!$A$5:$E$1048576,3,0),0) | AI44: =+IFERROR(VLOOKUP($A44,[33]Balance!$A$5:$E$1048576,3,0),0) | AJ44: =+IFERROR(VLOOKUP($A44,[34]Balance!$A$5:$E$1048576,3,0),0) | AK44: =+IFERROR(VLOOKUP($A44,'[35]1'!$A$5:$E$1048576,3,0),0)
A45: 14.2 | B45: Минус: Кўрилиши мумкин бўлган зарарларни қоплаш захираси | C45: =+IFERROR(VLOOKUP($A45,[1]Лист1!$A$5:$E$1048576,3,0),0) | D45: =+IFERROR(VLOOKUP($A45,'[2]1'!$A$5:$E$1048576,3,0),0) | E45: =+IFERROR(VLOOKUP($A45,'[3]1'!$A$5:$E$1048576,3,0),0) | F45: =+IFERROR(VLOOKUP($A45,[4]Balance!$A$5:$E$1048576,3,0),0) | G45: =+IFERROR(VLOOKUP($A45,'[5]1'!$A$5:$E$1048576,3,0),0) | H45: =+IFERROR(VLOOKUP($A45,[6]Balance!$A$5:$E$1048576,3,0),0) | I45: =+IFERROR(VLOOKUP($A45,[7]Balance!$A$5:$E$1048576,3,0),0) | J45: =+IFERROR(VLOOKUP($A45,'[8]1'!$A$5:$E$1048576,3,0),0) | K45: =+IFERROR(VLOOKUP($A45,'[9]1'!$A$5:$E$1048576,3,0),0) | L45: =+IFERROR(VLOOKUP($A45,'[10]1'!$A$5:$E$1048576,3,0),0) | M45: =+IFERROR(VLOOKUP($A45,'[11]1'!$A$5:$E$1048576,3,0),0) | N45: =+IFERROR(VLOOKUP($A45,[12]Balance!$A$5:$E$1048576,3,0),0) | O45: =+IFERROR(VLOOKUP($A45,'[13]1 т'!$A$5:$E$1048576,3,0),0) | P45: =+IFERROR(VLOOKUP($A45,[14]Balance!$A$5:$E$1048576,3,0),0) | Q45: =+IFERROR(VLOOKUP($A45,[15]Balance!$A$5:$E$1048576,3,0),0) | R45: =+IFERROR(VLOOKUP($A45,'[16]1'!$A$5:$E$1048576,3,0),0) | S45: =+IFERROR(VLOOKUP($A45,'[17]1'!$A$5:$E$1048576,3,0),0) | T45: =+IFERROR(VLOOKUP($A45,'[18]1'!$A$5:$E$1048576,3,0),0) | U45: =+IFERROR(VLOOKUP($A45,[19]Balans!$A$5:$E$1048576,3,0),0) | V45: =+IFERROR(VLOOKUP($A45,'[20]1'!$A$5:$E$1048576,3,0),0) | W45: =+IFERROR(VLOOKUP($A45,[21]Balance!$A$5:$E$1048576,3,0),0) | X45: =+IFERROR(VLOOKUP($A45,'[22]1'!$A$5:$E$1048576,3,0),0) | Y45: =+IFERROR(VLOOKUP($A45,[23]Лист1!$A$5:$E$1048576,3,0),0) | Z45: =+IFERROR(VLOOKUP($A45,'[24]1'!$A$5:$E$1048576,3,0),0) | AA45: =+IFERROR(VLOOKUP($A45,[25]Balance!$A$5:$E$1048576,3,0),0) | AB45: =+IFERROR(VLOOKUP($A45,'[26]1'!$A$5:$E$1048576,3,0),0) | AC45: =+IFERROR(VLOOKUP($A45,'[27]1'!$A$5:$E$1048576,3,0),0) | AD45: =+IFERROR(VLOOKUP($A45,'[28]1'!$A$5:$E$1048576,3,0),0) | AE45: =+IFERROR(VLOOKUP($A45,[29]Лист1!$A$5:$E$1048576,3,0),0) | AF45: =+IFERROR(VLOOKUP($A45,'[30]1'!$A$5:$E$1048576,3,0),0) | AG45: =+IFERROR(VLOOKUP($A45,'[31]1'!$A$5:$E$1048576,3,0),0) | AH45: =+IFERROR(VLOOKUP($A45,'[32]1-жадвал'!$A$5:$E$1048576,3,0),0) | AI45: =+IFERROR(VLOOKUP($A45,[33]Balance!$A$5:$E$1048576,3,0),0) | AJ45: =+IFERROR(VLOOKUP($A45,[34]Balance!$A$5:$E$1048576,3,0),0) | AK45: =+IFERROR(VLOOKUP($A45,'[35]1'!$A$5:$E$1048576,3,0),0)
A46: 14.3 | B46: Валюталар савдоси ва валюта позициялари | C46: =+IFERROR(VLOOKUP($A46,[1]Лист1!$A$5:$E$1048576,3,0),0) | D46: =+IFERROR(VLOOKUP($A46,'[2]1'!$A$5:$E$1048576,3,0),0) | E46: =+IFERROR(VLOOKUP($A46,'[3]1'!$A$5:$E$1048576,3,0),0) | F46: =+IFERROR(VLOOKUP($A46,[4]Balance!$A$5:$E$1048576,3,0),0) | G46: =+IFERROR(VLOOKUP($A46,'[5]1'!$A$5:$E$1048576,3,0),0) | H46: =+IFERROR(VLOOKUP($A46,[6]Balance!$A$5:$E$1048576,3,0),0) | I46: =+IFERROR(VLOOKUP($A46,[7]Balance!$A$5:$E$1048576,3,0),0) | J46: =+IFERROR(VLOOKUP($A46,'[8]1'!$A$5:$E$1048576,3,0),0) | K46: =+IFERROR(VLOOKUP($A46,'[9]1'!$A$5:$E$1048576,3,0),0) | L46: =+IFERROR(VLOOKUP($A46,'[10]1'!$A$5:$E$1048576,3,0),0) | M46: =+IFERROR(VLOOKUP($A46,'[11]1'!$A$5:$E$1048576,3,0),0) | N46: =+IFERROR(VLOOKUP($A46,[12]Balance!$A$5:$E$1048576,3,0),0) | O46: =+IFERROR(VLOOKUP($A46,'[13]1 т'!$A$5:$E$1048576,3,0),0) | P46: =+IFERROR(VLOOKUP($A46,[14]Balance!$A$5:$E$1048576,3,0),0) | Q46: =+IFERROR(VLOOKUP($A46,[15]Balance!$A$5:$E$1048576,3,0),0) | R46: =+IFERROR(VLOOKUP($A46,'[16]1'!$A$5:$E$1048576,3,0),0) | S46: =+IFERROR(VLOOKUP($A46,'[17]1'!$A$5:$E$1048576,3,0),0) | T46: =+IFERROR(VLOOKUP($A46,'[18]1'!$A$5:$E$1048576,3,0),0) | U46: =+IFERROR(VLOOKUP($A46,[19]Balans!$A$5:$E$1048576,3,0),0) | V46: =+IFERROR(VLOOKUP($A46,'[20]1'!$A$5:$E$1048576,3,0),0) | W46: =+IFERROR(VLOOKUP($A46,[21]Balance!$A$5:$E$1048576,3,0),0) | X46: =+IFERROR(VLOOKUP($A46,'[22]1'!$A$5:$E$1048576,3,0),0) | Y46: =+IFERROR(VLOOKUP($A46,[23]Лист1!$A$5:$E$1048576,3,0),0) | Z46: =+IFERROR(VLOOKUP($A46,'[24]1'!$A$5:$E$1048576,3,0),0) | AA46: =+IFERROR(VLOOKUP($A46,[25]Balance!$A$5:$E$1048576,3,0),0) | AB46: =+IFERROR(VLOOKUP($A46,'[26]1'!$A$5:$E$1048576,3,0),0) | AC46: =+IFERROR(VLOOKUP($A46,'[27]1'!$A$5:$E$1048576,3,0),0) | AD46: =+IFERROR(VLOOKUP($A46,'[28]1'!$A$5:$E$1048576,3,0),0) | AE46: =+IFERROR(VLOOKUP($A46,[29]Лист1!$A$5:$E$1048576,3,0),0) | AF46: =+IFERROR(VLOOKUP($A46,'[30]1'!$A$5:$E$1048576,3,0),0) | AG46: =+IFERROR(VLOOKUP($A46,'[31]1'!$A$5:$E$1048576,3,0),0) | AH46: =+IFERROR(VLOOKUP($A46,'[32]1-жадвал'!$A$5:$E$1048576,3,0),0) | AI46: =+IFERROR(VLOOKUP($A46,[33]Balance!$A$5:$E$1048576,3,0),0) | AJ46: =+IFERROR(VLOOKUP($A46,[34]Balance!$A$5:$E$1048576,3,0),0) | AK46: =+IFERROR(VLOOKUP($A46,'[35]1'!$A$5:$E$1048576,3,0),0)
A47: 15 | B47: Жами активлар | C47: =+IFERROR(VLOOKUP($A47,[1]Лист1!$A$5:$E$1048576,3,0),0) | D47: =+IFERROR(VLOOKUP($A47,'[2]1'!$A$5:$E$1048576,3,0),0) | E47: =+IFERROR(VLOOKUP($A47,'[3]1'!$A$5:$E$1048576,3,0),0) | F47: =+IFERROR(VLOOKUP($A47,[4]Balance!$A$5:$E$1048576,3,0),0) | G47: =+IFERROR(VLOOKUP($A47,'[5]1'!$A$5:$E$1048576,3,0),0) | H47: =+IFERROR(VLOOKUP($A47,[6]Balance!$A$5:$E$1048576,3,0),0) | I47: =+IFERROR(VLOOKUP($A47,[7]Balance!$A$5:$E$1048576,3,0),0) | J47: =+IFERROR(VLOOKUP($A47,'[8]1'!$A$5:$E$1048576,3,0),0) | K47: =+IFERROR(VLOOKUP($A47,'[9]1'!$A$5:$E$1048576,3,0),0) | L47: =+IFERROR(VLOOKUP($A47,'[10]1'!$A$5:$E$1048576,3,0),0) | M47: =+IFERROR(VLOOKUP($A47,'[11]1'!$A$5:$E$1048576,3,0),0) | N47: =+IFERROR(VLOOKUP($A47,[12]Balance!$A$5:$E$1048576,3,0),0) | O47: =+IFERROR(VLOOKUP($A47,'[13]1 т'!$A$5:$E$1048576,3,0),0) | P47: =+IFERROR(VLOOKUP($A47,[14]Balance!$A$5:$E$1048576,3,0),0) | Q47: =+IFERROR(VLOOKUP($A47,[15]Balance!$A$5:$E$1048576,3,0),0) | R47: =+IFERROR(VLOOKUP($A47,'[16]1'!$A$5:$E$1048576,3,0),0) | S47: =+IFERROR(VLOOKUP($A47,'[17]1'!$A$5:$E$1048576,3,0),0) | T47: =+IFERROR(VLOOKUP($A47,'[18]1'!$A$5:$E$1048576,3,0),0) | U47: =+IFERROR(VLOOKUP($A47,[19]Balans!$A$5:$E$1048576,3,0),0) | V47: =+IFERROR(VLOOKUP($A47,'[20]1'!$A$5:$E$1048576,3,0),0) | W47: =+IFERROR(VLOOKUP($A47,[21]Balance!$A$5:$E$1048576,3,0),0) | X47: =+IFERROR(VLOOKUP($A47,'[22]1'!$A$5:$E$1048576,3,0),0) | Y47: =+IFERROR(VLOOKUP($A47,[23]Лист1!$A$5:$E$1048576,3,0),0) | Z47: =+IFERROR(VLOOKUP($A47,'[24]1'!$A$5:$E$1048576,3,0),0) | AA47: =+IFERROR(VLOOKUP($A47,[25]Balance!$A$5:$E$1048576,3,0),0) | AB47: =+IFERROR(VLOOKUP($A47,'[26]1'!$A$5:$E$1048576,3,0),0) | AC47: =+IFERROR(VLOOKUP($A47,'[27]1'!$A$5:$E$1048576,3,0),0) | AD47: =+IFERROR(VLOOKUP($A47,'[28]1'!$A$5:$E$1048576,3,0),0) | AE47: =+IFERROR(VLOOKUP($A47,[29]Лист1!$A$5:$E$1048576,3,0),0) | AF47: =+IFERROR(VLOOKUP($A47,'[30]1'!$A$5:$E$1048576,3,0),0) | AG47: =+IFERROR(VLOOKUP($A47,'[31]1'!$A$5:$E$1048576,3,0),0) | AH47: =+IFERROR(VLOOKUP($A47,'[32]1-жадвал'!$A$5:$E$1048576,3,0),0) | AI47: =+IFERROR(VLOOKUP($A47,[33]Balance!$A$5:$E$1048576,3,0),0) | AJ47: =+IFERROR(VLOOKUP($A47,[34]Balance!$A$5:$E$1048576,3,0),0) | AK47: =+IFERROR(VLOOKUP($A47,'[35]1'!$A$5:$E$1048576,3,0),0)
B49: МАЖБУРИЯТЛАР
A50: 16 | B50: Талаб қилиб олингунча сақланадиган депозитлар | C50: =+IFERROR(VLOOKUP($A50,[1]Лист1!$A$5:$E$1048576,3,0),0) | D50: =+IFERROR(VLOOKUP($A50,'[2]1'!$A$5:$E$1048576,3,0),0) | E50: =+IFERROR(VLOOKUP($A50,'[3]1'!$A$5:$E$1048576,3,0),0) | F50: =+IFERROR(VLOOKUP($A50,[4]Balance!$A$5:$E$1048576,3,0),0) | G50: =+IFERROR(VLOOKUP($A50,'[5]1'!$A$5:$E$1048576,3,0),0) | H50: =+IFERROR(VLOOKUP($A50,[6]Balance!$A$5:$E$1048576,3,0),0) | I50: =+IFERROR(VLOOKUP($A50,[7]Balance!$A$5:$E$1048576,3,0),0) | J50: =+IFERROR(VLOOKUP($A50,'[8]1'!$A$5:$E$1048576,3,0),0) | K50: =+IFERROR(VLOOKUP($A50,'[9]1'!$A$5:$E$1048576,3,0),0) | L50: =+IFERROR(VLOOKUP($A50,'[10]1'!$A$5:$E$1048576,3,0),0) | M50: =+IFERROR(VLOOKUP($A50,'[11]1'!$A$5:$E$1048576,3,0),0) | N50: =+IFERROR(VLOOKUP($A50,[12]Balance!$A$5:$E$1048576,3,0),0) | O50: =+IFERROR(VLOOKUP($A50,'[13]1 т'!$A$5:$E$1048576,3,0),0) | P50: =+IFERROR(VLOOKUP($A50,[14]Balance!$A$5:$E$1048576,3,0),0) | Q50: =+IFERROR(VLOOKUP($A50,[15]Balance!$A$5:$E$1048576,3,0),0) | R50: =+IFERROR(VLOOKUP($A50,'[16]1'!$A$5:$E$1048576,3,0),0) | S50: =+IFERROR(VLOOKUP($A50,'[17]1'!$A$5:$E$1048576,3,0),0) | T50: =+IFERROR(VLOOKUP($A50,'[18]1'!$A$5:$E$1048576,3,0),0) | U50: =+IFERROR(VLOOKUP($A50,[19]Balans!$A$5:$E$1048576,3,0),0) | V50: =+IFERROR(VLOOKUP($A50,'[20]1'!$A$5:$E$1048576,3,0),0) | W50: =+IFERROR(VLOOKUP($A50,[21]Balance!$A$5:$E$1048576,3,0),0) | X50: =+IFERROR(VLOOKUP($A50,'[22]1'!$A$5:$E$1048576,3,0),0) | Y50: =+IFERROR(VLOOKUP($A50,[23]Лист1!$A$5:$E$1048576,3,0),0) | Z50: =+IFERROR(VLOOKUP($A50,'[24]1'!$A$5:$E$1048576,3,0),0) | AA50: =+IFERROR(VLOOKUP($A50,[25]Balance!$A$5:$E$1048576,3,0),0) | AB50: =+IFERROR(VLOOKUP($A50,'[26]1'!$A$5:$E$1048576,3,0),0) | AC50: =+IFERROR(VLOOKUP($A50,'[27]1'!$A$5:$E$1048576,3,0),0) | AD50: =+IFERROR(VLOOKUP($A50,'[28]1'!$A$5:$E$1048576,3,0),0) | AE50: =+IFERROR(VLOOKUP($A50,[29]Лист1!$A$5:$E$1048576,3,0),0) | AF50: =+IFERROR(VLOOKUP($A50,'[30]1'!$A$5:$E$1048576,3,0),0) | AG50: =+IFERROR(VLOOKUP($A50,'[31]1'!$A$5:$E$1048576,3,0),0) | AH50: =+IFERROR(VLOOKUP($A50,'[32]1-жадвал'!$A$5:$E$1048576,3,0),0) | AI50: =+IFERROR(VLOOKUP($A50,[33]Balance!$A$5:$E$1048576,3,0),0) | AJ50: =+IFERROR(VLOOKUP($A50,[34]Balance!$A$5:$E$1048576,3,0),0) | AK50: =+IFERROR(VLOOKUP($A50,'[35]1'!$A$5:$E$1048576,3,0),0)
A51: 17 | B51: Муддатли депозитлар | C51: =+IFERROR(VLOOKUP($A51,[1]Лист1!$A$5:$E$1048576,3,0),0) | D51: =+IFERROR(VLOOKUP($A51,'[2]1'!$A$5:$E$1048576,3,0),0) | E51: =+IFERROR(VLOOKUP($A51,'[3]1'!$A$5:$E$1048576,3,0),0) | F51: =+IFERROR(VLOOKUP($A51,[4]Balance!$A$5:$E$1048576,3,0),0) | G51: =+IFERROR(VLOOKUP($A51,'[5]1'!$A$5:$E$1048576,3,0),0) | H51: =+IFERROR(VLOOKUP($A51,[6]Balance!$A$5:$E$1048576,3,0),0) | I51: =+IFERROR(VLOOKUP($A51,[7]Balance!$A$5:$E$1048576,3,0),0) | J51: =+IFERROR(VLOOKUP($A51,'[8]1'!$A$5:$E$1048576,3,0),0) | K51: =+IFERROR(VLOOKUP($A51,'[9]1'!$A$5:$E$1048576,3,0),0) | L51: =+IFERROR(VLOOKUP($A51,'[10]1'!$A$5:$E$1048576,3,0),0) | M51: =+IFERROR(VLOOKUP($A51,'[11]1'!$A$5:$E$1048576,3,0),0) | N51: =+IFERROR(VLOOKUP($A51,[12]Balance!$A$5:$E$1048576,3,0),0) | O51: =+IFERROR(VLOOKUP($A51,'[13]1 т'!$A$5:$E$1048576,3,0),0) | P51: =+IFERROR(VLOOKUP($A51,[14]Balance!$A$5:$E$1048576,3,0),0) | Q51: =+IFERROR(VLOOKUP($A51,[15]Balance!$A$5:$E$1048576,3,0),0) | R51: =+IFERROR(VLOOKUP($A51,'[16]1'!$A$5:$E$1048576,3,0),0) | S51: =+IFERROR(VLOOKUP($A51,'[17]1'!$A$5:$E$1048576,3,0),0) | T51: =+IFERROR(VLOOKUP($A51,'[18]1'!$A$5:$E$1048576,3,0),0) | U51: =+IFERROR(VLOOKUP($A51,[19]Balans!$A$5:$E$1048576,3,0),0) | V51: =+IFERROR(VLOOKUP($A51,'[20]1'!$A$5:$E$1048576,3,0),0) | W51: =+IFERROR(VLOOKUP($A51,[21]Balance!$A$5:$E$1048576,3,0),0) | X51: =+IFERROR(VLOOKUP($A51,'[22]1'!$A$5:$E$1048576,3,0),0) | Y51: =+IFERROR(VLOOKUP($A51,[23]Лист1!$A$5:$E$1048576,3,0),0) | Z51: =+IFERROR(VLOOKUP($A51,'[24]1'!$A$5:$E$1048576,3,0),0) | AA51: =+IFERROR(VLOOKUP($A51,[25]Balance!$A$5:$E$1048576,3,0),0) | AB51: =+IFERROR(VLOOKUP($A51,'[26]1'!$A$5:$E$1048576,3,0),0) | AC51: =+IFERROR(VLOOKUP($A51,'[27]1'!$A$5:$E$1048576,3,0),0) | AD51: =+IFERROR(VLOOKUP($A51,'[28]1'!$A$5:$E$1048576,3,0),0) | AE51: =+IFERROR(VLOOKUP($A51,[29]Лист1!$A$5:$E$1048576,3,0),0) | AF51: =+IFERROR(VLOOKUP($A51,'[30]1'!$A$5:$E$1048576,3,0),0) | AG51: =+IFERROR(VLOOKUP($A51,'[31]1'!$A$5:$E$1048576,3,0),0) | AH51: =+IFERROR(VLOOKUP($A51,'[32]1-жадвал'!$A$5:$E$1048576,3,0),0) | AI51: =+IFERROR(VLOOKUP($A51,[33]Balance!$A$5:$E$1048576,3,0),0) | AJ51: =+IFERROR(VLOOKUP($A51,[34]Balance!$A$5:$E$1048576,3,0),0) | AK51: =+IFERROR(VLOOKUP($A51,'[35]1'!$A$5:$E$1048576,3,0),0)
A52: 18 | B52: Марказий банкка тўланиши лозим бўлган маблағлар | C52: =+IFERROR(VLOOKUP($A52,[1]Лист1!$A$5:$E$1048576,3,0),0) | D52: =+IFERROR(VLOOKUP($A52,'[2]1'!$A$5:$E$1048576,3,0),0) | E52: =+IFERROR(VLOOKUP($A52,'[3]1'!$A$5:$E$1048576,3,0),0) | F52: =+IFERROR(VLOOKUP($A52,[4]Balance!$A$5:$E$1048576,3,0),0) | G52: =+IFERROR(VLOOKUP($A52,'[5]1'!$A$5:$E$1048576,3,0),0) | H52: =+IFERROR(VLOOKUP($A52,[6]Balance!$A$5:$E$1048576,3,0),0) | I52: =+IFERROR(VLOOKUP($A52,[7]Balance!$A$5:$E$1048576,3,0),0) | J52: =+IFERROR(VLOOKUP($A52,'[8]1'!$A$5:$E$1048576,3,0),0) | K52: =+IFERROR(VLOOKUP($A52,'[9]1'!$A$5:$E$1048576,3,0),0) | L52: =+IFERROR(VLOOKUP($A52,'[10]1'!$A$5:$E$1048576,3,0),0) | M52: =+IFERROR(VLOOKUP($A52,'[11]1'!$A$5:$E$1048576,3,0),0) | N52: =+IFERROR(VLOOKUP($A52,[12]Balance!$A$5:$E$1048576,3,0),0) | O52: =+IFERROR(VLOOKUP($A52,'[13]1 т'!$A$5:$E$1048576,3,0),0) | P52: =+IFERROR(VLOOKUP($A52,[14]Balance!$A$5:$E$1048576,3,0),0) | Q52: =+IFERROR(VLOOKUP($A52,[15]Balance!$A$5:$E$1048576,3,0),0) | R52: =+IFERROR(VLOOKUP($A52,'[16]1'!$A$5:$E$1048576,3,0),0) | S52: =+IFERROR(VLOOKUP($A52,'[17]1'!$A$5:$E$1048576,3,0),0) | T52: =+IFERROR(VLOOKUP($A52,'[18]1'!$A$5:$E$1048576,3,0),0) | U52: =+IFERROR(VLOOKUP($A52,[19]Balans!$A$5:$E$1048576,3,0),0) | V52: =+IFERROR(VLOOKUP($A52,'[20]1'!$A$5:$E$1048576,3,0),0) | W52: =+IFERROR(VLOOKUP($A52,[21]Balance!$A$5:$E$1048576,3,0),0) | X52: =+IFERROR(VLOOKUP($A52,'[22]1'!$A$5:$E$1048576,3,0),0) | Y52: =+IFERROR(VLOOKUP($A52,[23]Лист1!$A$5:$E$1048576,3,0),0) | Z52: =+IFERROR(VLOOKUP($A52,'[24]1'!$A$5:$E$1048576,3,0),0) | AA52: =+IFERROR(VLOOKUP($A52,[25]Balance!$A$5:$E$1048576,3,0),0) | AB52: =+IFERROR(VLOOKUP($A52,'[26]1'!$A$5:$E$1048576,3,0),0) | AC52: =+IFERROR(VLOOKUP($A52,'[27]1'!$A$5:$E$1048576,3,0),0) | AD52: =+IFERROR(VLOOKUP($A52,'[28]1'!$A$5:$E$1048576,3,0),0) | AE52: =+IFERROR(VLOOKUP($A52,[29]Лист1!$A$5:$E$1048576,3,0),0) | AF52: =+IFERROR(VLOOKUP($A52,'[30]1'!$A$5:$E$1048576,3,0),0) | AG52: =+IFERROR(VLOOKUP($A52,'[31]1'!$A$5:$E$1048576,3,0),0) | AH52: =+IFERROR(VLOOKUP($A52,'[32]1-жадвал'!$A$5:$E$1048576,3,0),0) | AI52: =+IFERROR(VLOOKUP($A52,[33]Balance!$A$5:$E$1048576,3,0),0) | AJ52: =+IFERROR(VLOOKUP($A52,[34]Balance!$A$5:$E$1048576,3,0),0) | AK52: =+IFERROR(VLOOKUP($A52,'[35]1'!$A$5:$E$1048576,3,0),0)
A53: 19 | B53: Бошқа банклар ва молиявий ташкилотларнинг ҳисобварақлари | C53: =+IFERROR(VLOOKUP($A53,[1]Лист1!$A$5:$E$1048576,3,0),0) | D53: =+IFERROR(VLOOKUP($A53,'[2]1'!$A$5:$E$1048576,3,0),0) | E53: =+IFERROR(VLOOKUP($A53,'[3]1'!$A$5:$E$1048576,3,0),0) | F53: =+IFERROR(VLOOKUP($A53,[4]Balance!$A$5:$E$1048576,3,0),0) | G53: =+IFERROR(VLOOKUP($A53,'[5]1'!$A$5:$E$1048576,3,0),0) | H53: =+IFERROR(VLOOKUP($A53,[6]Balance!$A$5:$E$1048576,3,0),0) | I53: =+IFERROR(VLOOKUP($A53,[7]Balance!$A$5:$E$1048576,3,0),0) | J53: =+IFERROR(VLOOKUP($A53,'[8]1'!$A$5:$E$1048576,3,0),0) | K53: =+IFERROR(VLOOKUP($A53,'[9]1'!$A$5:$E$1048576,3,0),0) | L53: =+IFERROR(VLOOKUP($A53,'[10]1'!$A$5:$E$1048576,3,0),0) | M53: =+IFERROR(VLOOKUP($A53,'[11]1'!$A$5:$E$1048576,3,0),0) | N53: =+IFERROR(VLOOKUP($A53,[12]Balance!$A$5:$E$1048576,3,0),0) | O53: =+IFERROR(VLOOKUP($A53,'[13]1 т'!$A$5:$E$1048576,3,0),0) | P53: =+IFERROR(VLOOKUP($A53,[14]Balance!$A$5:$E$1048576,3,0),0) | Q53: =+IFERROR(VLOOKUP($A53,[15]Balance!$A$5:$E$1048576,3,0),0) | R53: =+IFERROR(VLOOKUP($A53,'[16]1'!$A$5:$E$1048576,3,0),0) | S53: =+IFERROR(VLOOKUP($A53,'[17]1'!$A$5:$E$1048576,3,0),0) | T53: =+IFERROR(VLOOKUP($A53,'[18]1'!$A$5:$E$1048576,3,0),0) | U53: =+IFERROR(VLOOKUP($A53,[19]Balans!$A$5:$E$1048576,3,0),0) | V53: =+IFERROR(VLOOKUP($A53,'[20]1'!$A$5:$E$1048576,3,0),0) | W53: =+IFERROR(VLOOKUP($A53,[21]Balance!$A$5:$E$1048576,3,0),0) | X53: =+IFERROR(VLOOKUP($A53,'[22]1'!$A$5:$E$1048576,3,0),0) | Y53: =+IFERROR(VLOOKUP($A53,[23]Лист1!$A$5:$E$1048576,3,0),0) | Z53: =+IFERROR(VLOOKUP($A53,'[24]1'!$A$5:$E$1048576,3,0),0) | AA53: =+IFERROR(VLOOKUP($A53,[25]Balance!$A$5:$E$1048576,3,0),0) | AB53: =+IFERROR(VLOOKUP($A53,'[26]1'!$A$5:$E$1048576,3,0),0) | AC53: =+IFERROR(VLOOKUP($A53,'[27]1'!$A$5:$E$1048576,3,0),0) | AD53: =+IFERROR(VLOOKUP($A53,'[28]1'!$A$5:$E$1048576,3,0),0) | AE53: =+IFERROR(VLOOKUP($A53,[29]Лист1!$A$5:$E$1048576,3,0),0) | AF53: =+IFERROR(VLOOKUP($A53,'[30]1'!$A$5:$E$1048576,3,0),0) | AG53: =+IFERROR(VLOOKUP($A53,'[31]1'!$A$5:$E$1048576,3,0),0) | AH53: =+IFERROR(VLOOKUP($A53,'[32]1-жадвал'!$A$5:$E$1048576,3,0),0) | AI53: =+IFERROR(VLOOKUP($A53,[33]Balance!$A$5:$E$1048576,3,0),0) | AJ53: =+IFERROR(VLOOKUP($A53,[34]Balance!$A$5:$E$1048576,3,0),0) | AK53: =+IFERROR(VLOOKUP($A53,'[35]1'!$A$5:$E$1048576,3,0),0)
A54: 20 | B54: РЕПО битимлари бўйича сотилган қимматли қоғозлар | C54: =+IFERROR(VLOOKUP($A54,[1]Лист1!$A$5:$E$1048576,3,0),0) | D54: =+IFERROR(VLOOKUP($A54,'[2]1'!$A$5:$E$1048576,3,0),0) | E54: =+IFERROR(VLOOKUP($A54,'[3]1'!$A$5:$E$1048576,3,0),0) | F54: =+IFERROR(VLOOKUP($A54,[4]Balance!$A$5:$E$1048576,3,0),0) | G54: =+IFERROR(VLOOKUP($A54,'[5]1'!$A$5:$E$1048576,3,0),0) | H54: =+IFERROR(VLOOKUP($A54,[6]Balance!$A$5:$E$1048576,3,0),0) | I54: =+IFERROR(VLOOKUP($A54,[7]Balance!$A$5:$E$1048576,3,0),0) | J54: =+IFERROR(VLOOKUP($A54,'[8]1'!$A$5:$E$1048576,3,0),0) | K54: =+IFERROR(VLOOKUP($A54,'[9]1'!$A$5:$E$1048576,3,0),0) | L54: =+IFERROR(VLOOKUP($A54,'[10]1'!$A$5:$E$1048576,3,0),0) | M54: =+IFERROR(VLOOKUP($A54,'[11]1'!$A$5:$E$1048576,3,0),0) | N54: =+IFERROR(VLOOKUP($A54,[12]Balance!$A$5:$E$1048576,3,0),0) | O54: =+IFERROR(VLOOKUP($A54,'[13]1 т'!$A$5:$E$1048576,3,0),0) | P54: =+IFERROR(VLOOKUP($A54,[14]Balance!$A$5:$E$1048576,3,0),0) | Q54: =+IFERROR(VLOOKUP($A54,[15]Balance!$A$5:$E$1048576,3,0),0) | R54: =+IFERROR(VLOOKUP($A54,'[16]1'!$A$5:$E$1048576,3,0),0) | S54: =+IFERROR(VLOOKUP($A54,'[17]1'!$A$5:$E$1048576,3,0),0) | T54: =+IFERROR(VLOOKUP($A54,'[18]1'!$A$5:$E$1048576,3,0),0) | U54: =+IFERROR(VLOOKUP($A54,[19]Balans!$A$5:$E$1048576,3,0),0) | V54: =+IFERROR(VLOOKUP($A54,'[20]1'!$A$5:$E$1048576,3,0),0) | W54: =+IFERROR(VLOOKUP($A54,[21]Balance!$A$5:$E$1048576,3,0),0) | X54: =+IFERROR(VLOOKUP($A54,'[22]1'!$A$5:$E$1048576,3,0),0) | Y54: =+IFERROR(VLOOKUP($A54,[23]Лист1!$A$5:$E$1048576,3,0),0) | Z54: =+IFERROR(VLOOKUP($A54,'[24]1'!$A$5:$E$1048576,3,0),0) | AA54: =+IFERROR(VLOOKUP($A54,[25]Balance!$A$5:$E$1048576,3,0),0) | AB54: =+IFERROR(VLOOKUP($A54,'[26]1'!$A$5:$E$1048576,3,0),0) | AC54: =+IFERROR(VLOOKUP($A54,'[27]1'!$A$5:$E$1048576,3,0),0) | AD54: =+IFERROR(VLOOKUP($A54,'[28]1'!$A$5:$E$1048576,3,0),0) | AE54: =+IFERROR(VLOOKUP($A54,[29]Лист1!$A$5:$E$1048576,3,0),0) | AF54: =+IFERROR(VLOOKUP($A54,'[30]1'!$A$5:$E$1048576,3,0),0) | AG54: =+IFERROR(VLOOKUP($A54,'[31]1'!$A$5:$E$1048576,3,0),0) | AH54: =+IFERROR(VLOOKUP($A54,'[32]1-жадвал'!$A$5:$E$1048576,3,0),0) | AI54: =+IFERROR(VLOOKUP($A54,[33]Balance!$A$5:$E$1048576,3,0),0) | AJ54: =+IFERROR(VLOOKUP($A54,[34]Balance!$A$5:$E$1048576,3,0),0) | AK54: =+IFERROR(VLOOKUP($A54,'[35]1'!$A$5:$E$1048576,3,0),0)
A55: 21 | B55: Кредит ва лизинг операциялари бўйича мажбуриятлар | C55: =+IFERROR(VLOOKUP($A55,[1]Лист1!$A$5:$E$1048576,3,0),0) | D55: =+IFERROR(VLOOKUP($A55,'[2]1'!$A$5:$E$1048576,3,0),0) | E55: =+IFERROR(VLOOKUP($A55,'[3]1'!$A$5:$E$1048576,3,0),0) | F55: =+IFERROR(VLOOKUP($A55,[4]Balance!$A$5:$E$1048576,3,0),0) | G55: =+IFERROR(VLOOKUP($A55,'[5]1'!$A$5:$E$1048576,3,0),0) | H55: =+IFERROR(VLOOKUP($A55,[6]Balance!$A$5:$E$1048576,3,0),0) | I55: =+IFERROR(VLOOKUP($A55,[7]Balance!$A$5:$E$1048576,3,0),0) | J55: =+IFERROR(VLOOKUP($A55,'[8]1'!$A$5:$E$1048576,3,0),0) | K55: =+IFERROR(VLOOKUP($A55,'[9]1'!$A$5:$E$1048576,3,0),0) | L55: =+IFERROR(VLOOKUP($A55,'[10]1'!$A$5:$E$1048576,3,0),0) | M55: =+IFERROR(VLOOKUP($A55,'[11]1'!$A$5:$E$1048576,3,0),0) | N55: =+IFERROR(VLOOKUP($A55,[12]Balance!$A$5:$E$1048576,3,0),0) | O55: =+IFERROR(VLOOKUP($A55,'[13]1 т'!$A$5:$E$1048576,3,0),0) | P55: =+IFERROR(VLOOKUP($A55,[14]Balance!$A$5:$E$1048576,3,0),0) | Q55: =+IFERROR(VLOOKUP($A55,[15]Balance!$A$5:$E$1048576,3,0),0) | R55: =+IFERROR(VLOOKUP($A55,'[16]1'!$A$5:$E$1048576,3,0),0) | S55: =+IFERROR(VLOOKUP($A55,'[17]1'!$A$5:$E$1048576,3,0),0) | T55: =+IFERROR(VLOOKUP($A55,'[18]1'!$A$5:$E$1048576,3,0),0) | U55: =+IFERROR(VLOOKUP($A55,[19]Balans!$A$5:$E$1048576,3,0),0) | V55: =+IFERROR(VLOOKUP($A55,'[20]1'!$A$5:$E$1048576,3,0),0) | W55: =+IFERROR(VLOOKUP($A55,[21]Balance!$A$5:$E$1048576,3,0),0) | X55: =+IFERROR(VLOOKUP($A55,'[22]1'!$A$5:$E$1048576,3,0),0) | Y55: =+IFERROR(VLOOKUP($A55,[23]Лист1!$A$5:$E$1048576,3,0),0) | Z55: =+IFERROR(VLOOKUP($A55,'[24]1'!$A$5:$E$1048576,3,0),0) | AA55: =+IFERROR(VLOOKUP($A55,[25]Balance!$A$5:$E$1048576,3,0),0) | AB55: =+IFERROR(VLOOKUP($A55,'[26]1'!$A$5:$E$1048576,3,0),0) | AC55: =+IFERROR(VLOOKUP($A55,'[27]1'!$A$5:$E$1048576,3,0),0) | AD55: =+IFERROR(VLOOKUP($A55,'[28]1'!$A$5:$E$1048576,3,0),0) | AE55: =+IFERROR(VLOOKUP($A55,[29]Лист1!$A$5:$E$1048576,3,0),0) | AF55: =+IFERROR(VLOOKUP($A55,'[30]1'!$A$5:$E$1048576,3,0),0) | AG55: =+IFERROR(VLOOKUP($A55,'[31]1'!$A$5:$E$1048576,3,0),0) | AH55: =+IFERROR(VLOOKUP($A55,'[32]1-жадвал'!$A$5:$E$1048576,3,0),0) | AI55: =+IFERROR(VLOOKUP($A55,[33]Balance!$A$5:$E$1048576,3,0),0) | AJ55: =+IFERROR(VLOOKUP($A55,[34]Balance!$A$5:$E$1048576,3,0),0) | AK55: =+IFERROR(VLOOKUP($A55,'[35]1'!$A$5:$E$1048576,3,0),0)
A56: 22 | B56: Банк томонидан чиқарилган қимматли қоғозлар | C56: =+IFERROR(VLOOKUP($A56,[1]Лист1!$A$5:$E$1048576,3,0),0) | D56: =+IFERROR(VLOOKUP($A56,'[2]1'!$A$5:$E$1048576,3,0),0) | E56: =+IFERROR(VLOOKUP($A56,'[3]1'!$A$5:$E$1048576,3,0),0) | F56: =+IFERROR(VLOOKUP($A56,[4]Balance!$A$5:$E$1048576,3,0),0) | G56: =+IFERROR(VLOOKUP($A56,'[5]1'!$A$5:$E$1048576,3,0),0) | H56: =+IFERROR(VLOOKUP($A56,[6]Balance!$A$5:$E$1048576,3,0),0) | I56: =+IFERROR(VLOOKUP($A56,[7]Balance!$A$5:$E$1048576,3,0),0) | J56: =+IFERROR(VLOOKUP($A56,'[8]1'!$A$5:$E$1048576,3,0),0) | K56: =+IFERROR(VLOOKUP($A56,'[9]1'!$A$5:$E$1048576,3,0),0) | L56: =+IFERROR(VLOOKUP($A56,'[10]1'!$A$5:$E$1048576,3,0),0) | M56: =+IFERROR(VLOOKUP($A56,'[11]1'!$A$5:$E$1048576,3,0),0) | N56: =+IFERROR(VLOOKUP($A56,[12]Balance!$A$5:$E$1048576,3,0),0) | O56: =+IFERROR(VLOOKUP($A56,'[13]1 т'!$A$5:$E$1048576,3,0),0) | P56: =+IFERROR(VLOOKUP($A56,[14]Balance!$A$5:$E$1048576,3,0),0) | Q56: =+IFERROR(VLOOKUP($A56,[15]Balance!$A$5:$E$1048576,3,0),0) | R56: =+IFERROR(VLOOKUP($A56,'[16]1'!$A$5:$E$1048576,3,0),0) | S56: =+IFERROR(VLOOKUP($A56,'[17]1'!$A$5:$E$1048576,3,0),0) | T56: =+IFERROR(VLOOKUP($A56,'[18]1'!$A$5:$E$1048576,3,0),0) | U56: =+IFERROR(VLOOKUP($A56,[19]Balans!$A$5:$E$1048576,3,0),0) | V56: =+IFERROR(VLOOKUP($A56,'[20]1'!$A$5:$E$1048576,3,0),0) | W56: =+IFERROR(VLOOKUP($A56,[21]Balance!$A$5:$E$1048576,3,0),0) | X56: =+IFERROR(VLOOKUP($A56,'[22]1'!$A$5:$E$1048576,3,0),0) | Y56: =+IFERROR(VLOOKUP($A56,[23]Лист1!$A$5:$E$1048576,3,0),0) | Z56: =+IFERROR(VLOOKUP($A56,'[24]1'!$A$5:$E$1048576,3,0),0) | AA56: =+IFERROR(VLOOKUP($A56,[25]Balance!$A$5:$E$1048576,3,0),0) | AB56: =+IFERROR(VLOOKUP($A56,'[26]1'!$A$5:$E$1048576,3,0),0) | AC56: =+IFERROR(VLOOKUP($A56,'[27]1'!$A$5:$E$1048576,3,0),0) | AD56: =+IFERROR(VLOOKUP($A56,'[28]1'!$A$5:$E$1048576,3,0),0) | AE56: =+IFERROR(VLOOKUP($A56,[29]Лист1!$A$5:$E$1048576,3,0),0) | AF56: =+IFERROR(VLOOKUP($A56,'[30]1'!$A$5:$E$1048576,3,0),0) | AG56: =+IFERROR(VLOOKUP($A56,'[31]1'!$A$5:$E$1048576,3,0),0) | AH56: =+IFERROR(VLOOKUP($A56,'[32]1-жадвал'!$A$5:$E$1048576,3,0),0) | AI56: =+IFERROR(VLOOKUP($A56,[33]Balance!$A$5:$E$1048576,3,0),0) | AJ56: =+IFERROR(VLOOKUP($A56,[34]Balance!$A$5:$E$1048576,3,0),0) | AK56: =+IFERROR(VLOOKUP($A56,'[35]1'!$A$5:$E$1048576,3,0),0)
A57: 23 | B57: Субординар қарз | C57: =+IFERROR(VLOOKUP($A57,[1]Лист1!$A$5:$E$1048576,3,0),0) | D57: =+IFERROR(VLOOKUP($A57,'[2]1'!$A$5:$E$1048576,3,0),0) | E57: =+IFERROR(VLOOKUP($A57,'[3]1'!$A$5:$E$1048576,3,0),0) | F57: =+IFERROR(VLOOKUP($A57,[4]Balance!$A$5:$E$1048576,3,0),0) | G57: =+IFERROR(VLOOKUP($A57,'[5]1'!$A$5:$E$1048576,3,0),0) | H57: =+IFERROR(VLOOKUP($A57,[6]Balance!$A$5:$E$1048576,3,0),0) | I57: =+IFERROR(VLOOKUP($A57,[7]Balance!$A$5:$E$1048576,3,0),0) | J57: =+IFERROR(VLOOKUP($A57,'[8]1'!$A$5:$E$1048576,3,0),0) | K57: =+IFERROR(VLOOKUP($A57,'[9]1'!$A$5:$E$1048576,3,0),0) | L57: =+IFERROR(VLOOKUP($A57,'[10]1'!$A$5:$E$1048576,3,0),0) | M57: =+IFERROR(VLOOKUP($A57,'[11]1'!$A$5:$E$1048576,3,0),0) | N57: =+IFERROR(VLOOKUP($A57,[12]Balance!$A$5:$E$1048576,3,0),0) | O57: =+IFERROR(VLOOKUP($A57,'[13]1 т'!$A$5:$E$1048576,3,0),0) | P57: =+IFERROR(VLOOKUP($A57,[14]Balance!$A$5:$E$1048576,3,0),0) | Q57: =+IFERROR(VLOOKUP($A57,[15]Balance!$A$5:$E$1048576,3,0),0) | R57: =+IFERROR(VLOOKUP($A57,'[16]1'!$A$5:$E$1048576,3,0),0) | S57: =+IFERROR(VLOOKUP($A57,'[17]1'!$A$5:$E$1048576,3,0),0) | T57: =+IFERROR(VLOOKUP($A57,'[18]1'!$A$5:$E$1048576,3,0),0) | U57: =+IFERROR(VLOOKUP($A57,[19]Balans!$A$5:$E$1048576,3,0),0) | V57: =+IFERROR(VLOOKUP($A57,'[20]1'!$A$5:$E$1048576,3,0),0) | W57: =+IFERROR(VLOOKUP($A57,[21]Balance!$A$5:$E$1048576,3,0),0) | X57: =+IFERROR(VLOOKUP($A57,'[22]1'!$A$5:$E$1048576,3,0),0) | Y57: =+IFERROR(VLOOKUP($A57,[23]Лист1!$A$5:$E$1048576,3,0),0) | Z57: =+IFERROR(VLOOKUP($A57,'[24]1'!$A$5:$E$1048576,3,0),0) | AA57: =+IFERROR(VLOOKUP($A57,[25]Balance!$A$5:$E$1048576,3,0),0) | AB57: =+IFERROR(VLOOKUP($A57,'[26]1'!$A$5:$E$1048576,3,0),0) | AC57: =+IFERROR(VLOOKUP($A57,'[27]1'!$A$5:$E$1048576,3,0),0) | AD57: =+IFERROR(VLOOKUP($A57,'[28]1'!$A$5:$E$1048576,3,0),0) | AE57: =+IFERROR(VLOOKUP($A57,[29]Лист1!$A$5:$E$1048576,3,0),0) | AF57: =+IFERROR(VLOOKUP($A57,'[30]1'!$A$5:$E$1048576,3,0),0) | AG57: =+IFERROR(VLOOKUP($A57,'[31]1'!$A$5:$E$1048576,3,0),0) | AH57: =+IFERROR(VLOOKUP($A57,'[32]1-жадвал'!$A$5:$E$1048576,3,0),0) | AI57: =+IFERROR(VLOOKUP($A57,[33]Balance!$A$5:$E$1048576,3,0),0) | AJ57: =+IFERROR(VLOOKUP($A57,[34]Balance!$A$5:$E$1048576,3,0),0) | AK57: =+IFERROR(VLOOKUP($A57,'[35]1'!$A$5:$E$1048576,3,0),0)
A58: 24 | B58: Тўланиши лозим бўлган ҳисобланган фоизлар | C58: =+IFERROR(VLOOKUP($A58,[1]Лист1!$A$5:$E$1048576,3,0),0) | D58: =+IFERROR(VLOOKUP($A58,'[2]1'!$A$5:$E$1048576,3,0),0) | E58: =+IFERROR(VLOOKUP($A58,'[3]1'!$A$5:$E$1048576,3,0),0) | F58: =+IFERROR(VLOOKUP($A58,[4]Balance!$A$5:$E$1048576,3,0),0) | G58: =+IFERROR(VLOOKUP($A58,'[5]1'!$A$5:$E$1048576,3,0),0) | H58: =+IFERROR(VLOOKUP($A58,[6]Balance!$A$5:$E$1048576,3,0),0) | I58: =+IFERROR(VLOOKUP($A58,[7]Balance!$A$5:$E$1048576,3,0),0) | J58: =+IFERROR(VLOOKUP($A58,'[8]1'!$A$5:$E$1048576,3,0),0) | K58: =+IFERROR(VLOOKUP($A58,'[9]1'!$A$5:$E$1048576,3,0),0) | L58: =+IFERROR(VLOOKUP($A58,'[10]1'!$A$5:$E$1048576,3,0),0) | M58: =+IFERROR(VLOOKUP($A58,'[11]1'!$A$5:$E$1048576,3,0),0) | N58: =+IFERROR(VLOOKUP($A58,[12]Balance!$A$5:$E$1048576,3,0),0) | O58: =+IFERROR(VLOOKUP($A58,'[13]1 т'!$A$5:$E$1048576,3,0),0) | P58: =+IFERROR(VLOOKUP($A58,[14]Balance!$A$5:$E$1048576,3,0),0) | Q58: =+IFERROR(VLOOKUP($A58,[15]Balance!$A$5:$E$1048576,3,0),0) | R58: =+IFERROR(VLOOKUP($A58,'[16]1'!$A$5:$E$1048576,3,0),0) | S58: =+IFERROR(VLOOKUP($A58,'[17]1'!$A$5:$E$1048576,3,0),0) | T58: =+IFERROR(VLOOKUP($A58,'[18]1'!$A$5:$E$1048576,3,0),0) | U58: =+IFERROR(VLOOKUP($A58,[19]Balans!$A$5:$E$1048576,3,0),0) | V58: =+IFERROR(VLOOKUP($A58,'[20]1'!$A$5:$E$1048576,3,0),0) | W58: =+IFERROR(VLOOKUP($A58,[21]Balance!$A$5:$E$1048576,3,0),0) | X58: =+IFERROR(VLOOKUP($A58,'[22]1'!$A$5:$E$1048576,3,0),0) | Y58: =+IFERROR(VLOOKUP($A58,[23]Лист1!$A$5:$E$1048576,3,0),0) | Z58: =+IFERROR(VLOOKUP($A58,'[24]1'!$A$5:$E$1048576,3,0),0) | AA58: =+IFERROR(VLOOKUP($A58,[25]Balance!$A$5:$E$1048576,3,0),0) | AB58: =+IFERROR(VLOOKUP($A58,'[26]1'!$A$5:$E$1048576,3,0),0) | AC58: =+IFERROR(VLOOKUP($A58,'[27]1'!$A$5:$E$1048576,3,0),0) | AD58: =+IFERROR(VLOOKUP($A58,'[28]1'!$A$5:$E$1048576,3,0),0) | AE58: =+IFERROR(VLOOKUP($A58,[29]Лист1!$A$5:$E$1048576,3,0),0) | AF58: =+IFERROR(VLOOKUP($A58,'[30]1'!$A$5:$E$1048576,3,0),0) | AG58: =+IFERROR(VLOOKUP($A58,'[31]1'!$A$5:$E$1048576,3,0),0) | AH58: =+IFERROR(VLOOKUP($A58,'[32]1-жадвал'!$A$5:$E$1048576,3,0),0) | AI58: =+IFERROR(VLOOKUP($A58,[33]Balance!$A$5:$E$1048576,3,0),0) | AJ58: =+IFERROR(VLOOKUP($A58,[34]Balance!$A$5:$E$1048576,3,0),0) | AK58: =+IFERROR(VLOOKUP($A58,'[35]1'!$A$5:$E$1048576,3,0),0)
A59: 25 | B59: Ҳисобланган солиқлар бўйича мажбуриятлар | C59: =+IFERROR(VLOOKUP($A59,[1]Лист1!$A$5:$E$1048576,3,0),0) | D59: =+IFERROR(VLOOKUP($A59,'[2]1'!$A$5:$E$1048576,3,0),0) | E59: =+IFERROR(VLOOKUP($A59,'[3]1'!$A$5:$E$1048576,3,0),0) | F59: =+IFERROR(VLOOKUP($A59,[4]Balance!$A$5:$E$1048576,3,0),0) | G59: =+IFERROR(VLOOKUP($A59,'[5]1'!$A$5:$E$1048576,3,0),0) | H59: =+IFERROR(VLOOKUP($A59,[6]Balance!$A$5:$E$1048576,3,0),0) | I59: =+IFERROR(VLOOKUP($A59,[7]Balance!$A$5:$E$1048576,3,0),0) | J59: =+IFERROR(VLOOKUP($A59,'[8]1'!$A$5:$E$1048576,3,0),0) | K59: =+IFERROR(VLOOKUP($A59,'[9]1'!$A$5:$E$1048576,3,0),0) | L59: =+IFERROR(VLOOKUP($A59,'[10]1'!$A$5:$E$1048576,3,0),0) | M59: =+IFERROR(VLOOKUP($A59,'[11]1'!$A$5:$E$1048576,3,0),0) | N59: =+IFERROR(VLOOKUP($A59,[12]Balance!$A$5:$E$1048576,3,0),0) | O59: =+IFERROR(VLOOKUP($A59,'[13]1 т'!$A$5:$E$1048576,3,0),0) | P59: =+IFERROR(VLOOKUP($A59,[14]Balance!$A$5:$E$1048576,3,0),0) | Q59: =+IFERROR(VLOOKUP($A59,[15]Balance!$A$5:$E$1048576,3,0),0) | R59: =+IFERROR(VLOOKUP($A59,'[16]1'!$A$5:$E$1048576,3,0),0) | S59: =+IFERROR(VLOOKUP($A59,'[17]1'!$A$5:$E$1048576,3,0),0) | T59: =+IFERROR(VLOOKUP($A59,'[18]1'!$A$5:$E$1048576,3,0),0) | U59: =+IFERROR(VLOOKUP($A59,[19]Balans!$A$5:$E$1048576,3,0),0) | V59: =+IFERROR(VLOOKUP($A59,'[20]1'!$A$5:$E$1048576,3,0),0) | W59: =+IFERROR(VLOOKUP($A59,[21]Balance!$A$5:$E$1048576,3,0),0) | X59: =+IFERROR(VLOOKUP($A59,'[22]1'!$A$5:$E$1048576,3,0),0) | Y59: =+IFERROR(VLOOKUP($A59,[23]Лист1!$A$5:$E$1048576,3,0),0) | Z59: =+IFERROR(VLOOKUP($A59,'[24]1'!$A$5:$E$1048576,3,0),0) | AA59: =+IFERROR(VLOOKUP($A59,[25]Balance!$A$5:$E$1048576,3,0),0) | AB59: =+IFERROR(VLOOKUP($A59,'[26]1'!$A$5:$E$1048576,3,0),0) | AC59: =+IFERROR(VLOOKUP($A59,'[27]1'!$A$5:$E$1048576,3,0),0) | AD59: =+IFERROR(VLOOKUP($A59,'[28]1'!$A$5:$E$1048576,3,0),0) | AE59: =+IFERROR(VLOOKUP($A59,[29]Лист1!$A$5:$E$1048576,3,0),0) | AF59: =+IFERROR(VLOOKUP($A59,'[30]1'!$A$5:$E$1048576,3,0),0) | AG59: =+IFERROR(VLOOKUP($A59,'[31]1'!$A$5:$E$1048576,3,0),0) | AH59: =+IFERROR(VLOOKUP($A59,'[32]1-жадвал'!$A$5:$E$1048576,3,0),0) | AI59: =+IFERROR(VLOOKUP($A59,[33]Balance!$A$5:$E$1048576,3,0),0) | AJ59: =+IFERROR(VLOOKUP($A59,[34]Balance!$A$5:$E$1048576,3,0),0) | AK59: =+IFERROR(VLOOKUP($A59,'[35]1'!$A$5:$E$1048576,3,0),0)
A60: 26 | B60: Клиринг транзакциялари | C60: =+IFERROR(VLOOKUP($A60,[1]Лист1!$A$5:$E$1048576,3,0),0) | D60: =+IFERROR(VLOOKUP($A60,'[2]1'!$A$5:$E$1048576,3,0),0) | E60: =+IFERROR(VLOOKUP($A60,'[3]1'!$A$5:$E$1048576,3,0),0) | F60: =+IFERROR(VLOOKUP($A60,[4]Balance!$A$5:$E$1048576,3,0),0) | G60: =+IFERROR(VLOOKUP($A60,'[5]1'!$A$5:$E$1048576,3,0),0) | H60: =+IFERROR(VLOOKUP($A60,[6]Balance!$A$5:$E$1048576,3,0),0) | I60: =+IFERROR(VLOOKUP($A60,[7]Balance!$A$5:$E$1048576,3,0),0) | J60: =+IFERROR(VLOOKUP($A60,'[8]1'!$A$5:$E$1048576,3,0),0) | K60: =+IFERROR(VLOOKUP($A60,'[9]1'!$A$5:$E$1048576,3,0),0) | L60: =+IFERROR(VLOOKUP($A60,'[10]1'!$A$5:$E$1048576,3,0),0) | M60: =+IFERROR(VLOOKUP($A60,'[11]1'!$A$5:$E$1048576,3,0),0) | N60: =+IFERROR(VLOOKUP($A60,[12]Balance!$A$5:$E$1048576,3,0),0) | O60: =+IFERROR(VLOOKUP($A60,'[13]1 т'!$A$5:$E$1048576,3,0),0) | P60: =+IFERROR(VLOOKUP($A60,[14]Balance!$A$5:$E$1048576,3,0),0) | Q60: =+IFERROR(VLOOKUP($A60,[15]Balance!$A$5:$E$1048576,3,0),0) | R60: =+IFERROR(VLOOKUP($A60,'[16]1'!$A$5:$E$1048576,3,0),0) | S60: =+IFERROR(VLOOKUP($A60,'[17]1'!$A$5:$E$1048576,3,0),0) | T60: =+IFERROR(VLOOKUP($A60,'[18]1'!$A$5:$E$1048576,3,0),0) | U60: =+IFERROR(VLOOKUP($A60,[19]Balans!$A$5:$E$1048576,3,0),0) | V60: =+IFERROR(VLOOKUP($A60,'[20]1'!$A$5:$E$1048576,3,0),0) | W60: =+IFERROR(VLOOKUP($A60,[21]Balance!$A$5:$E$1048576,3,0),0) | X60: =+IFERROR(VLOOKUP($A60,'[22]1'!$A$5:$E$1048576,3,0),0) | Y60: =+IFERROR(VLOOKUP($A60,[23]Лист1!$A$5:$E$1048576,3,0),0) | Z60: =+IFERROR(VLOOKUP($A60,'[24]1'!$A$5:$E$1048576,3,0),0) | AA60: =+IFERROR(VLOOKUP($A60,[25]Balance!$A$5:$E$1048576,3,0),0) | AB60: =+IFERROR(VLOOKUP($A60,'[26]1'!$A$5:$E$1048576,3,0),0) | AC60: =+IFERROR(VLOOKUP($A60,'[27]1'!$A$5:$E$1048576,3,0),0) | AD60: =+IFERROR(VLOOKUP($A60,'[28]1'!$A$5:$E$1048576,3,0),0) | AE60: =+IFERROR(VLOOKUP($A60,[29]Лист1!$A$5:$E$1048576,3,0),0) | AF60: =+IFERROR(VLOOKUP($A60,'[30]1'!$A$5:$E$1048576,3,0),0) | AG60: =+IFERROR(VLOOKUP($A60,'[31]1'!$A$5:$E$1048576,3,0),0) | AH60: =+IFERROR(VLOOKUP($A60,'[32]1-жадвал'!$A$5:$E$1048576,3,0),0) | AI60: =+IFERROR(VLOOKUP($A60,[33]Balance!$A$5:$E$1048576,3,0),0) | AJ60: =+IFERROR(VLOOKUP($A60,[34]Balance!$A$5:$E$1048576,3,0),0) | AK60: =+IFERROR(VLOOKUP($A60,'[35]1'!$A$5:$E$1048576,3,0),0)
A61: 27 | B61: Стандарт деб таснифланган балансдан ташқари моддаларга яратилган захиралар | C61: =+IFERROR(VLOOKUP($A61,[1]Лист1!$A$5:$E$1048576,3,0),0) | D61: =+IFERROR(VLOOKUP($A61,'[2]1'!$A$5:$E$1048576,3,0),0) | E61: =+IFERROR(VLOOKUP($A61,'[3]1'!$A$5:$E$1048576,3,0),0) | F61: =+IFERROR(VLOOKUP($A61,[4]Balance!$A$5:$E$1048576,3,0),0) | G61: =+IFERROR(VLOOKUP($A61,'[5]1'!$A$5:$E$1048576,3,0),0) | H61: =+IFERROR(VLOOKUP($A61,[6]Balance!$A$5:$E$1048576,3,0),0) | I61: =+IFERROR(VLOOKUP($A61,[7]Balance!$A$5:$E$1048576,3,0),0) | J61: =+IFERROR(VLOOKUP($A61,'[8]1'!$A$5:$E$1048576,3,0),0) | K61: =+IFERROR(VLOOKUP($A61,'[9]1'!$A$5:$E$1048576,3,0),0) | L61: =+IFERROR(VLOOKUP($A61,'[10]1'!$A$5:$E$1048576,3,0),0) | M61: =+IFERROR(VLOOKUP($A61,'[11]1'!$A$5:$E$1048576,3,0),0) | N61: =+IFERROR(VLOOKUP($A61,[12]Balance!$A$5:$E$1048576,3,0),0) | O61: =+IFERROR(VLOOKUP($A61,'[13]1 т'!$A$5:$E$1048576,3,0),0) | P61: =+IFERROR(VLOOKUP($A61,[14]Balance!$A$5:$E$1048576,3,0),0) | Q61: =+IFERROR(VLOOKUP($A61,[15]Balance!$A$5:$E$1048576,3,0),0) | R61: =+IFERROR(VLOOKUP($A61,'[16]1'!$A$5:$E$1048576,3,0),0) | S61: =+IFERROR(VLOOKUP($A61,'[17]1'!$A$5:$E$1048576,3,0),0) | T61: =+IFERROR(VLOOKUP($A61,'[18]1'!$A$5:$E$1048576,3,0),0) | U61: =+IFERROR(VLOOKUP($A61,[19]Balans!$A$5:$E$1048576,3,0),0) | V61: =+IFERROR(VLOOKUP($A61,'[20]1'!$A$5:$E$1048576,3,0),0) | W61: =+IFERROR(VLOOKUP($A61,[21]Balance!$A$5:$E$1048576,3,0),0) | X61: =+IFERROR(VLOOKUP($A61,'[22]1'!$A$5:$E$1048576,3,0),0) | Y61: =+IFERROR(VLOOKUP($A61,[23]Лист1!$A$5:$E$1048576,3,0),0) | Z61: =+IFERROR(VLOOKUP($A61,'[24]1'!$A$5:$E$1048576,3,0),0) | AA61: =+IFERROR(VLOOKUP($A61,[25]Balance!$A$5:$E$1048576,3,0),0) | AB61: =+IFERROR(VLOOKUP($A61,'[26]1'!$A$5:$E$1048576,3,0),0) | AC61: =+IFERROR(VLOOKUP($A61,'[27]1'!$A$5:$E$1048576,3,0),0) | AD61: =+IFERROR(VLOOKUP($A61,'[28]1'!$A$5:$E$1048576,3,0),0) | AE61: =+IFERROR(VLOOKUP($A61,[29]Лист1!$A$5:$E$1048576,3,0),0) | AF61: =+IFERROR(VLOOKUP($A61,'[30]1'!$A$5:$E$1048576,3,0),0) | AG61: =+IFERROR(VLOOKUP($A61,'[31]1'!$A$5:$E$1048576,3,0),0) | AH61: =+IFERROR(VLOOKUP($A61,'[32]1-жадвал'!$A$5:$E$1048576,3,0),0) | AI61: =+IFERROR(VLOOKUP($A61,[33]Balance!$A$5:$E$1048576,3,0),0) | AJ61: =+IFERROR(VLOOKUP($A61,[34]Balance!$A$5:$E$1048576,3,0),0) | AK61: =+IFERROR(VLOOKUP($A61,'[35]1'!$A$5:$E$1048576,3,0),0)
... A63: 29 | B63: Жами мажбуриятлар | C63: =+IFERROR(VLOOKUP($A63,[1]Лист1!$A$5:$E$1048576,3,0),0) | D63: =+IFERROR(VLOOKUP($A63,'[2]1'!$A$5:$E$1048576,3,0),0) | E63: =+IFERROR(VLOOKUP($A63,'[3]1'!$A$5:$E$1048576,3,0),0) | F63: =+IFERROR(VLOOKUP($A63,[4]Balance!$A$5:$E$1048576,3,0),0) | G63: =+IFERROR(VLOOKUP($A63,'[5]1'!$A$5:$E$1048576,3,0),0) | H63: =+IFERROR(VLOOKUP($A63,[6]Balance!$A$5:$E$1048576,3,0),0) | I63: =+IFERROR(VLOOKUP($A63,[7]Balance!$A$5:$E$1048576,3,0),0) | J63: =+IFERROR(VLOOKUP($A63,'[8]1'!$A$5:$E$1048576,3,0),0) | K63: =+IFERROR(VLOOKUP($A63,'[9]1'!$A$5:$E$1048576,3,0),0) | L63: =+IFERROR(VLOOKUP($A63,'[10]1'!$A$5:$E$1048576,3,0),0) | M63: =+IFERROR(VLOOKUP($A63,'[11]1'!$A$5:$E$1048576,3,0),0) | N63: =+IFERROR(VLOOKUP($A63,[12]Balance!$A$5:$E$1048576,3,0),0) | O63: =+IFERROR(VLOOKUP($A63,'[13]1 т'!$A$5:$E$1048576,3,0),0) | P63: =+IFERROR(VLOOKUP($A63,[14]Balance!$A$5:$E$1048576,3,0),0) | Q63: =+IFERROR(VLOOKUP($A63,[15]Balance!$A$5:$E$1048576,3,0),0) | R63: =+IFERROR(VLOOKUP($A63,'[16]1'!$A$5:$E$1048576,3,0),0) | S63: =+IFERROR(VLOOKUP($A63,'[17]1'!$A$5:$E$1048576,3,0),0) | T63: =+IFERROR(VLOOKUP($A63,'[18]1'!$A$5:$E$1048576,3,0),0) | U63: =+IFERROR(VLOOKUP($A63,[19]Balans!$A$5:$E$1048576,3,0),0) | V63: =+IFERROR(VLOOKUP($A63,'[20]1'!$A$5:$E$1048576,3,0),0) | W63: =+IFERROR(VLOOKUP($A63,[21]Balance!$A$5:$E$1048576,3,0),0) | X63: =+IFERROR(VLOOKUP($A63,'[22]1'!$A$5:$E$1048576,3,0),0) | Y63: =+IFERROR(VLOOKUP($A63,[23]Лист1!$A$5:$E$1048576,3,0),0) | Z63: =+IFERROR(VLOOKUP($A63,'[24]1'!$A$5:$E$1048576,3,0),0) | AA63: =+IFERROR(VLOOKUP($A63,[25]Balance!$A$5:$E$1048576,3,0),0) | AB63: =+IFERROR(VLOOKUP($A63,'[26]1'!$A$5:$E$1048576,3,0),0) | AC63: =+IFERROR(VLOOKUP($A63,'[27]1'!$A$5:$E$1048576,3,0),0) | AD63: =+IFERROR(VLOOKUP($A63,'[28]1'!$A$5:$E$1048576,3,0),0) | AE63: =+IFERROR(VLOOKUP($A63,[29]Лист1!$A$5:$E$1048576,3,0),0) | AF63: =+IFERROR(VLOOKUP($A63,'[30]1'!$A$5:$E$1048576,3,0),0) | AG63: =+IFERROR(VLOOKUP($A63,'[31]1'!$A$5:$E$1048576,3,0),0) | AH63: =+IFERROR(VLOOKUP($A63,'[32]1-жадвал'!$A$5:$E$1048576,3,0),0) | AI63: =+IFERROR(VLOOKUP($A63,[33]Balance!$A$5:$E$1048576,3,0),0) | AJ63: =+IFERROR(VLOOKUP($A63,[34]Balance!$A$5:$E$1048576,3,0),0) | AK63: =+IFERROR(VLOOKUP($A63,'[35]1'!$A$5:$E$1048576,3,0),0)
B65: ХУСУСИЙ КАПИТАЛ | AP65: 784488
A66: 30 | B66: Устав капитали | C66: =+IFERROR(VLOOKUP($A66,[1]Лист1!$A$5:$E$1048576,3,0),0) | D66: =+IFERROR(VLOOKUP($A66,'[2]1'!$A$5:$E$1048576,3,0),0) | E66: =+IFERROR(VLOOKUP($A66,'[3]1'!$A$5:$E$1048576,3,0),0) | F66: =+IFERROR(VLOOKUP($A66,[4]Balance!$A$5:$E$1048576,3,0),0) | G66: =+IFERROR(VLOOKUP($A66,'[5]1'!$A$5:$E$1048576,3,0),0) | H66: =+IFERROR(VLOOKUP($A66,[6]Balance!$A$5:$E$1048576,3,0),0) | I66: =+IFERROR(VLOOKUP($A66,[7]Balance!$A$5:$E$1048576,3,0),0) | J66: =+IFERROR(VLOOKUP($A66,'[8]1'!$A$5:$E$1048576,3,0),0) | K66: =+IFERROR(VLOOKUP($A66,'[9]1'!$A$5:$E$1048576,3,0),0) | L66: =+IFERROR(VLOOKUP($A66,'[10]1'!$A$5:$E$1048576,3,0),0) | M66: =+IFERROR(VLOOKUP($A66,'[11]1'!$A$5:$E$1048576,3,0),0) | N66: =+IFERROR(VLOOKUP($A66,[12]Balance!$A$5:$E$1048576,3,0),0) | O66: =+IFERROR(VLOOKUP($A66,'[13]1 т'!$A$5:$E$1048576,3,0),0) | P66: =+IFERROR(VLOOKUP($A66,[14]Balance!$A$5:$E$1048576,3,0),0) | Q66: =+IFERROR(VLOOKUP($A66,[15]Balance!$A$5:$E$1048576,3,0),0) | R66: =+IFERROR(VLOOKUP($A66,'[16]1'!$A$5:$E$1048576,3,0),0) | S66: =+IFERROR(VLOOKUP($A66,'[17]1'!$A$5:$E$1048576,3,0),0) | T66: =+IFERROR(VLOOKUP($A66,'[18]1'!$A$5:$E$1048576,3,0),0) | U66: =+IFERROR(VLOOKUP($A66,[19]Balans!$A$5:$E$1048576,3,0),0) | V66: =+IFERROR(VLOOKUP($A66,'[20]1'!$A$5:$E$1048576,3,0),0) | W66: =+IFERROR(VLOOKUP($A66,[21]Balance!$A$5:$E$1048576,3,0),0) | X66: =+IFERROR(VLOOKUP($A66,'[22]1'!$A$5:$E$1048576,3,0),0) | Y66: =+IFERROR(VLOOKUP($A66,[23]Лист1!$A$5:$E$1048576,3,0),0) | Z66: =+IFERROR(VLOOKUP($A66,'[24]1'!$A$5:$E$1048576,3,0),0) | AA66: =+IFERROR(VLOOKUP($A66,[25]Balance!$A$5:$E$1048576,3,0),0) | AB66: =+IFERROR(VLOOKUP($A66,'[26]1'!$A$5:$E$1048576,3,0),0) | AC66: =+IFERROR(VLOOKUP($A66,'[27]1'!$A$5:$E$1048576,3,0),0) | AD66: =+IFERROR(VLOOKUP($A66,'[28]1'!$A$5:$E$1048576,3,0),0) | AE66: =+IFERROR(VLOOKUP($A66,[29]Лист1!$A$5:$E$1048576,3,0),0) | AF66: =+IFERROR(VLOOKUP($A66,'[30]1'!$A$5:$E$1048576,3,0),0) | AG66: =+IFERROR(VLOOKUP($A66,'[31]1'!$A$5:$E$1048576,3,0),0) | AH66: =+IFERROR(VLOOKUP($A66,'[32]1-жадвал'!$A$5:$E$1048576,3,0),0) | AI66: =+IFERROR(VLOOKUP($A66,[33]Balance!$A$5:$E$1048576,3,0),0) | AJ66: =+IFERROR(VLOOKUP($A66,[34]Balance!$A$5:$E$1048576,3,0),0) | AK66: =+IFERROR(VLOOKUP($A66,'[35]1'!$A$5:$E$1048576,3,0),0) | AP66: =+#REF!+AP65
A67: 30.1 | B67: Aкциялар – оддий | C67: =+IFERROR(VLOOKUP($A67,[1]Лист1!$A$5:$E$1048576,3,0),0) | D67: =+IFERROR(VLOOKUP($A67,'[2]1'!$A$5:$E$1048576,3,0),0) | E67: =+IFERROR(VLOOKUP($A67,'[3]1'!$A$5:$E$1048576,3,0),0) | F67: =+IFERROR(VLOOKUP($A67,[4]Balance!$A$5:$E$1048576,3,0),0) | G67: =+IFERROR(VLOOKUP($A67,'[5]1'!$A$5:$E$1048576,3,0),0) | H67: =+IFERROR(VLOOKUP($A67,[6]Balance!$A$5:$E$1048576,3,0),0) | I67: =+IFERROR(VLOOKUP($A67,[7]Balance!$A$5:$E$1048576,3,0),0) | J67: =+IFERROR(VLOOKUP($A67,'[8]1'!$A$5:$E$1048576,3,0),0) | K67: =+IFERROR(VLOOKUP($A67,'[9]1'!$A$5:$E$1048576,3,0),0) | L67: =+IFERROR(VLOOKUP($A67,'[10]1'!$A$5:$E$1048576,3,0),0) | M67: =+IFERROR(VLOOKUP($A67,'[11]1'!$A$5:$E$1048576,3,0),0) | N67: =+IFERROR(VLOOKUP($A67,[12]Balance!$A$5:$E$1048576,3,0),0) | O67: =+IFERROR(VLOOKUP($A67,'[13]1 т'!$A$5:$E$1048576,3,0),0) | P67: =+IFERROR(VLOOKUP($A67,[14]Balance!$A$5:$E$1048576,3,0),0) | Q67: =+IFERROR(VLOOKUP($A67,[15]Balance!$A$5:$E$1048576,3,0),0) | R67: =+IFERROR(VLOOKUP($A67,'[16]1'!$A$5:$E$1048576,3,0),0) | S67: =+IFERROR(VLOOKUP($A67,'[17]1'!$A$5:$E$1048576,3,0),0) | T67: =+IFERROR(VLOOKUP($A67,'[18]1'!$A$5:$E$1048576,3,0),0) | U67: =+IFERROR(VLOOKUP($A67,[19]Balans!$A$5:$E$1048576,3,0),0) | V67: =+IFERROR(VLOOKUP($A67,'[20]1'!$A$5:$E$1048576,3,0),0) | W67: =+IFERROR(VLOOKUP($A67,[21]Balance!$A$5:$E$1048576,3,0),0) | X67: =+IFERROR(VLOOKUP($A67,'[22]1'!$A$5:$E$1048576,3,0),0) | Y67: =+IFERROR(VLOOKUP($A67,[23]Лист1!$A$5:$E$1048576,3,0),0) | Z67: =+IFERROR(VLOOKUP($A67,'[24]1'!$A$5:$E$1048576,3,0),0) | AA67: =+IFERROR(VLOOKUP($A67,[25]Balance!$A$5:$E$1048576,3,0),0) | AB67: =+IFERROR(VLOOKUP($A67,'[26]1'!$A$5:$E$1048576,3,0),0) | AC67: =+IFERROR(VLOOKUP($A67,'[27]1'!$A$5:$E$1048576,3,0),0) | AD67: =+IFERROR(VLOOKUP($A67,'[28]1'!$A$5:$E$1048576,3,0),0) | AE67: =+IFERROR(VLOOKUP($A67,[29]Лист1!$A$5:$E$1048576,3,0),0) | AF67: =+IFERROR(VLOOKUP($A67,'[30]1'!$A$5:$E$1048576,3,0),0) | AG67: =+IFERROR(VLOOKUP($A67,'[31]1'!$A$5:$E$1048576,3,0),0) | AH67: =+IFERROR(VLOOKUP($A67,'[32]1-жадвал'!$A$5:$E$1048576,3,0),0) | AI67: =+IFERROR(VLOOKUP($A67,[33]Balance!$A$5:$E$1048576,3,0),0) | AJ67: =+IFERROR(VLOOKUP($A67,[34]Balance!$A$5:$E$1048576,3,0),0) | AK67: =+IFERROR(VLOOKUP($A67,'[35]1'!$A$5:$E$1048576,3,0),0)
A68: 30.2 | B68: Aкциялар – имтиёзли | C68: =+IFERROR(VLOOKUP($A68,[1]Лист1!$A$5:$E$1048576,3,0),0) | D68: =+IFERROR(VLOOKUP($A68,'[2]1'!$A$5:$E$1048576,3,0),0) | E68: =+IFERROR(VLOOKUP($A68,'[3]1'!$A$5:$E$1048576,3,0),0) | F68: =+IFERROR(VLOOKUP($A68,[4]Balance!$A$5:$E$1048576,3,0),0) | G68: =+IFERROR(VLOOKUP($A68,'[5]1'!$A$5:$E$1048576,3,0),0) | H68: =+IFERROR(VLOOKUP($A68,[6]Balance!$A$5:$E$1048576,3,0),0) | I68: =+IFERROR(VLOOKUP($A68,[7]Balance!$A$5:$E$1048576,3,0),0) | J68: =+IFERROR(VLOOKUP($A68,'[8]1'!$A$5:$E$1048576,3,0),0) | K68: =+IFERROR(VLOOKUP($A68,'[9]1'!$A$5:$E$1048576,3,0),0) | L68: =+IFERROR(VLOOKUP($A68,'[10]1'!$A$5:$E$1048576,3,0),0) | M68: =+IFERROR(VLOOKUP($A68,'[11]1'!$A$5:$E$1048576,3,0),0) | N68: =+IFERROR(VLOOKUP($A68,[12]Balance!$A$5:$E$1048576,3,0),0) | O68: =+IFERROR(VLOOKUP($A68,'[13]1 т'!$A$5:$E$1048576,3,0),0) | P68: =+IFERROR(VLOOKUP($A68,[14]Balance!$A$5:$E$1048576,3,0),0) | Q68: =+IFERROR(VLOOKUP($A68,[15]Balance!$A$5:$E$1048576,3,0),0) | R68: =+IFERROR(VLOOKUP($A68,'[16]1'!$A$5:$E$1048576,3,0),0) | S68: =+IFERROR(VLOOKUP($A68,'[17]1'!$A$5:$E$1048576,3,0),0) | T68: =+IFERROR(VLOOKUP($A68,'[18]1'!$A$5:$E$1048576,3,0),0) | U68: =+IFERROR(VLOOKUP($A68,[19]Balans!$A$5:$E$1048576,3,0),0) | V68: =+IFERROR(VLOOKUP($A68,'[20]1'!$A$5:$E$1048576,3,0),0) | W68: =+IFERROR(VLOOKUP($A68,[21]Balance!$A$5:$E$1048576,3,0),0) | X68: =+IFERROR(VLOOKUP($A68,'[22]1'!$A$5:$E$1048576,3,0),0) | Y68: =+IFERROR(VLOOKUP($A68,[23]Лист1!$A$5:$E$1048576,3,0),0) | Z68: =+IFERROR(VLOOKUP($A68,'[24]1'!$A$5:$E$1048576,3,0),0) | AA68: =+IFERROR(VLOOKUP($A68,[25]Balance!$A$5:$E$1048576,3,0),0) | AB68: =+IFERROR(VLOOKUP($A68,'[26]1'!$A$5:$E$1048576,3,0),0) | AC68: =+IFERROR(VLOOKUP($A68,'[27]1'!$A$5:$E$1048576,3,0),0) | AD68: =+IFERROR(VLOOKUP($A68,'[28]1'!$A$5:$E$1048576,3,0),0) | AE68: =+IFERROR(VLOOKUP($A68,[29]Лист1!$A$5:$E$1048576,3,0),0) | AF68: =+IFERROR(VLOOKUP($A68,'[30]1'!$A$5:$E$1048576,3,0),0) | AG68: =+IFERROR(VLOOKUP($A68,'[31]1'!$A$5:$E$1048576,3,0),0) | AH68: =+IFERROR(VLOOKUP($A68,'[32]1-жадвал'!$A$5:$E$1048576,3,0),0) | AI68: =+IFERROR(VLOOKUP($A68,[33]Balance!$A$5:$E$1048576,3,0),0) | AJ68: =+IFERROR(VLOOKUP($A68,[34]Balance!$A$5:$E$1048576,3,0),0) | AK68: =+IFERROR(VLOOKUP($A68,'[35]1'!$A$5:$E$1048576,3,0),0)
A69: 31 | B69: Қўшилган капитал | C69: =+IFERROR(VLOOKUP($A69,[1]Лист1!$A$5:$E$1048576,3,0),0) | D69: =+IFERROR(VLOOKUP($A69,'[2]1'!$A$5:$E$1048576,3,0),0) | E69: =+IFERROR(VLOOKUP($A69,'[3]1'!$A$5:$E$1048576,3,0),0) | F69: =+IFERROR(VLOOKUP($A69,[4]Balance!$A$5:$E$1048576,3,0),0) | G69: =+IFERROR(VLOOKUP($A69,'[5]1'!$A$5:$E$1048576,3,0),0) | H69: =+IFERROR(VLOOKUP($A69,[6]Balance!$A$5:$E$1048576,3,0),0) | I69: =+IFERROR(VLOOKUP($A69,[7]Balance!$A$5:$E$1048576,3,0),0) | J69: =+IFERROR(VLOOKUP($A69,'[8]1'!$A$5:$E$1048576,3,0),0) | K69: =+IFERROR(VLOOKUP($A69,'[9]1'!$A$5:$E$1048576,3,0),0) | L69: =+IFERROR(VLOOKUP($A69,'[10]1'!$A$5:$E$1048576,3,0),0) | M69: =+IFERROR(VLOOKUP($A69,'[11]1'!$A$5:$E$1048576,3,0),0) | N69: =+IFERROR(VLOOKUP($A69,[12]Balance!$A$5:$E$1048576,3,0),0) | O69: =+IFERROR(VLOOKUP($A69,'[13]1 т'!$A$5:$E$1048576,3,0),0) | P69: =+IFERROR(VLOOKUP($A69,[14]Balance!$A$5:$E$1048576,3,0),0) | Q69: =+IFERROR(VLOOKUP($A69,[15]Balance!$A$5:$E$1048576,3,0),0) | R69: =+IFERROR(VLOOKUP($A69,'[16]1'!$A$5:$E$1048576,3,0),0) | S69: =+IFERROR(VLOOKUP($A69,'[17]1'!$A$5:$E$1048576,3,0),0) | T69: =+IFERROR(VLOOKUP($A69,'[18]1'!$A$5:$E$1048576,3,0),0) | U69: =+IFERROR(VLOOKUP($A69,[19]Balans!$A$5:$E$1048576,3,0),0) | V69: =+IFERROR(VLOOKUP($A69,'[20]1'!$A$5:$E$1048576,3,0),0) | W69: =+IFERROR(VLOOKUP($A69,[21]Balance!$A$5:$E$1048576,3,0),0) | X69: =+IFERROR(VLOOKUP($A69,'[22]1'!$A$5:$E$1048576,3,0),0) | Y69: =+IFERROR(VLOOKUP($A69,[23]Лист1!$A$5:$E$1048576,3,0),0) | Z69: =+IFERROR(VLOOKUP($A69,'[24]1'!$A$5:$E$1048576,3,0),0) | AA69: =+IFERROR(VLOOKUP($A69,[25]Balance!$A$5:$E$1048576,3,0),0) | AB69: =+IFERROR(VLOOKUP($A69,'[26]1'!$A$5:$E$1048576,3,0),0) | AC69: =+IFERROR(VLOOKUP($A69,'[27]1'!$A$5:$E$1048576,3,0),0) | AD69: =+IFERROR(VLOOKUP($A69,'[28]1'!$A$5:$E$1048576,3,0),0) | AE69: =+IFERROR(VLOOKUP($A69,[29]Лист1!$A$5:$E$1048576,3,0),0) | AF69: =+IFERROR(VLOOKUP($A69,'[30]1'!$A$5:$E$1048576,3,0),0) | AG69: =+IFERROR(VLOOKUP($A69,'[31]1'!$A$5:$E$1048576,3,0),0) | AH69: =+IFERROR(VLOOKUP($A69,'[32]1-жадвал'!$A$5:$E$1048576,3,0),0) | AI69: =+IFERROR(VLOOKUP($A69,[33]Balance!$A$5:$E$1048576,3,0),0) | AJ69: =+IFERROR(VLOOKUP($A69,[34]Balance!$A$5:$E$1048576,3,0),0) | AK69: =+IFERROR(VLOOKUP($A69,'[35]1'!$A$5:$E$1048576,3,0),0)
A70: 32 | B70: Захира капитали | C70: =+IFERROR(VLOOKUP($A70,[1]Лист1!$A$5:$E$1048576,3,0),0) | D70: =+IFERROR(VLOOKUP($A70,'[2]1'!$A$5:$E$1048576,3,0),0) | E70: =+IFERROR(VLOOKUP($A70,'[3]1'!$A$5:$E$1048576,3,0),0) | F70: =+IFERROR(VLOOKUP($A70,[4]Balance!$A$5:$E$1048576,3,0),0) | G70: =+IFERROR(VLOOKUP($A70,'[5]1'!$A$5:$E$1048576,3,0),0) | H70: =+IFERROR(VLOOKUP($A70,[6]Balance!$A$5:$E$1048576,3,0),0) | I70: =+IFERROR(VLOOKUP($A70,[7]Balance!$A$5:$E$1048576,3,0),0) | J70: =+IFERROR(VLOOKUP($A70,'[8]1'!$A$5:$E$1048576,3,0),0) | K70: =+IFERROR(VLOOKUP($A70,'[9]1'!$A$5:$E$1048576,3,0),0) | L70: =+IFERROR(VLOOKUP($A70,'[10]1'!$A$5:$E$1048576,3,0),0) | M70: =+IFERROR(VLOOKUP($A70,'[11]1'!$A$5:$E$1048576,3,0),0) | N70: =+IFERROR(VLOOKUP($A70,[12]Balance!$A$5:$E$1048576,3,0),0) | O70: =+IFERROR(VLOOKUP($A70,'[13]1 т'!$A$5:$E$1048576,3,0),0) | P70: =+IFERROR(VLOOKUP($A70,[14]Balance!$A$5:$E$1048576,3,0),0) | Q70: =+IFERROR(VLOOKUP($A70,[15]Balance!$A$5:$E$1048576,3,0),0) | R70: =+IFERROR(VLOOKUP($A70,'[16]1'!$A$5:$E$1048576,3,0),0) | S70: =+IFERROR(VLOOKUP($A70,'[17]1'!$A$5:$E$1048576,3,0),0) | T70: =+IFERROR(VLOOKUP($A70,'[18]1'!$A$5:$E$1048576,3,0),0) | U70: =+IFERROR(VLOOKUP($A70,[19]Balans!$A$5:$E$1048576,3,0),0) | V70: =+IFERROR(VLOOKUP($A70,'[20]1'!$A$5:$E$1048576,3,0),0) | W70: =+IFERROR(VLOOKUP($A70,[21]Balance!$A$5:$E$1048576,3,0),0) | X70: =+IFERROR(VLOOKUP($A70,'[22]1'!$A$5:$E$1048576,3,0),0) | Y70: =+IFERROR(VLOOKUP($A70,[23]Лист1!$A$5:$E$1048576,3,0),0) | Z70: =+IFERROR(VLOOKUP($A70,'[24]1'!$A$5:$E$1048576,3,0),0) | AA70: =+IFERROR(VLOOKUP($A70,[25]Balance!$A$5:$E$1048576,3,0),0) | AB70: =+IFERROR(VLOOKUP($A70,'[26]1'!$A$5:$E$1048576,3,0),0) | AC70: =+IFERROR(VLOOKUP($A70,'[27]1'!$A$5:$E$1048576,3,0),0) | AD70: =+IFERROR(VLOOKUP($A70,'[28]1'!$A$5:$E$1048576,3,0),0) | AE70: =+IFERROR(VLOOKUP($A70,[29]Лист1!$A$5:$E$1048576,3,0),0) | AF70: =+IFERROR(VLOOKUP($A70,'[30]1'!$A$5:$E$1048576,3,0),0) | AG70: =+IFERROR(VLOOKUP($A70,'[31]1'!$A$5:$E$1048576,3,0),0) | AH70: =+IFERROR(VLOOKUP($A70,'[32]1-жадвал'!$A$5:$E$1048576,3,0),0) | AI70: =+IFERROR(VLOOKUP($A70,[33]Balance!$A$5:$E$1048576,3,0),0) | AJ70: =+IFERROR(VLOOKUP($A70,[34]Balance!$A$5:$E$1048576,3,0),0) | AK70: =+IFERROR(VLOOKUP($A70,'[35]1'!$A$5:$E$1048576,3,0),0)
A71: 32.1 | B71: Умумий захира фонди | C71: =+IFERROR(VLOOKUP($A71,[1]Лист1!$A$5:$E$1048576,3,0),0) | D71: =+IFERROR(VLOOKUP($A71,'[2]1'!$A$5:$E$1048576,3,0),0) | E71: =+IFERROR(VLOOKUP($A71,'[3]1'!$A$5:$E$1048576,3,0),0) | F71: =+IFERROR(VLOOKUP($A71,[4]Balance!$A$5:$E$1048576,3,0),0) | G71: =+IFERROR(VLOOKUP($A71,'[5]1'!$A$5:$E$1048576,3,0),0) | H71: =+IFERROR(VLOOKUP($A71,[6]Balance!$A$5:$E$1048576,3,0),0) | I71: =+IFERROR(VLOOKUP($A71,[7]Balance!$A$5:$E$1048576,3,0),0) | J71: =+IFERROR(VLOOKUP($A71,'[8]1'!$A$5:$E$1048576,3,0),0) | K71: =+IFERROR(VLOOKUP($A71,'[9]1'!$A$5:$E$1048576,3,0),0) | L71: =+IFERROR(VLOOKUP($A71,'[10]1'!$A$5:$E$1048576,3,0),0) | M71: =+IFERROR(VLOOKUP($A71,'[11]1'!$A$5:$E$1048576,3,0),0) | N71: =+IFERROR(VLOOKUP($A71,[12]Balance!$A$5:$E$1048576,3,0),0) | O71: =+IFERROR(VLOOKUP($A71,'[13]1 т'!$A$5:$E$1048576,3,0),0) | P71: =+IFERROR(VLOOKUP($A71,[14]Balance!$A$5:$E$1048576,3,0),0) | Q71: =+IFERROR(VLOOKUP($A71,[15]Balance!$A$5:$E$1048576,3,0),0) | R71: =+IFERROR(VLOOKUP($A71,'[16]1'!$A$5:$E$1048576,3,0),0) | S71: =+IFERROR(VLOOKUP($A71,'[17]1'!$A$5:$E$1048576,3,0),0) | T71: =+IFERROR(VLOOKUP($A71,'[18]1'!$A$5:$E$1048576,3,0),0) | U71: =+IFERROR(VLOOKUP($A71,[19]Balans!$A$5:$E$1048576,3,0),0) | V71: =+IFERROR(VLOOKUP($A71,'[20]1'!$A$5:$E$1048576,3,0),0) | W71: =+IFERROR(VLOOKUP($A71,[21]Balance!$A$5:$E$1048576,3,0),0) | X71: =+IFERROR(VLOOKUP($A71,'[22]1'!$A$5:$E$1048576,3,0),0) | Y71: =+IFERROR(VLOOKUP($A71,[23]Лист1!$A$5:$E$1048576,3,0),0) | Z71: =+IFERROR(VLOOKUP($A71,'[24]1'!$A$5:$E$1048576,3,0),0) | AA71: =+IFERROR(VLOOKUP($A71,[25]Balance!$A$5:$E$1048576,3,0),0) | AB71: =+IFERROR(VLOOKUP($A71,'[26]1'!$A$5:$E$1048576,3,0),0) | AC71: =+IFERROR(VLOOKUP($A71,'[27]1'!$A$5:$E$1048576,3,0),0) | AD71: =+IFERROR(VLOOKUP($A71,'[28]1'!$A$5:$E$1048576,3,0),0) | AE71: =+IFERROR(VLOOKUP($A71,[29]Лист1!$A$5:$E$1048576,3,0),0) | AF71: =+IFERROR(VLOOKUP($A71,'[30]1'!$A$5:$E$1048576,3,0),0) | AG71: =+IFERROR(VLOOKUP($A71,'[31]1'!$A$5:$E$1048576,3,0),0) | AH71: =+IFERROR(VLOOKUP($A71,'[32]1-жадвал'!$A$5:$E$1048576,3,0),0) | AI71: =+IFERROR(VLOOKUP($A71,[33]Balance!$A$5:$E$1048576,3,0),0) | AJ71: =+IFERROR(VLOOKUP($A71,[34]Balance!$A$5:$E$1048576,3,0),0) | AK71: =+IFERROR(VLOOKUP($A71,'[35]1'!$A$5:$E$1048576,3,0),0)
A72: 32.2 | B72: Девальвация учун захира | C72: =+IFERROR(VLOOKUP($A72,[1]Лист1!$A$5:$E$1048576,3,0),0) | D72: =+IFERROR(VLOOKUP($A72,'[2]1'!$A$5:$E$1048576,3,0),0) | E72: =+IFERROR(VLOOKUP($A72,'[3]1'!$A$5:$E$1048576,3,0),0) | F72: =+IFERROR(VLOOKUP($A72,[4]Balance!$A$5:$E$1048576,3,0),0) | G72: =+IFERROR(VLOOKUP($A72,'[5]1'!$A$5:$E$1048576,3,0),0) | H72: =+IFERROR(VLOOKUP($A72,[6]Balance!$A$5:$E$1048576,3,0),0) | I72: =+IFERROR(VLOOKUP($A72,[7]Balance!$A$5:$E$1048576,3,0),0) | J72: =+IFERROR(VLOOKUP($A72,'[8]1'!$A$5:$E$1048576,3,0),0) | K72: =+IFERROR(VLOOKUP($A72,'[9]1'!$A$5:$E$1048576,3,0),0) | L72: =+IFERROR(VLOOKUP($A72,'[10]1'!$A$5:$E$1048576,3,0),0) | M72: =+IFERROR(VLOOKUP($A72,'[11]1'!$A$5:$E$1048576,3,0),0) | N72: =+IFERROR(VLOOKUP($A72,[12]Balance!$A$5:$E$1048576,3,0),0) | O72: =+IFERROR(VLOOKUP($A72,'[13]1 т'!$A$5:$E$1048576,3,0),0) | P72: =+IFERROR(VLOOKUP($A72,[14]Balance!$A$5:$E$1048576,3,0),0) | Q72: =+IFERROR(VLOOKUP($A72,[15]Balance!$A$5:$E$1048576,3,0),0) | R72: =+IFERROR(VLOOKUP($A72,'[16]1'!$A$5:$E$1048576,3,0),0) | S72: =+IFERROR(VLOOKUP($A72,'[17]1'!$A$5:$E$1048576,3,0),0) | T72: =+IFERROR(VLOOKUP($A72,'[18]1'!$A$5:$E$1048576,3,0),0) | U72: =+IFERROR(VLOOKUP($A72,[19]Balans!$A$5:$E$1048576,3,0),0) | V72: =+IFERROR(VLOOKUP($A72,'[20]1'!$A$5:$E$1048576,3,0),0) | W72: =+IFERROR(VLOOKUP($A72,[21]Balance!$A$5:$E$1048576,3,0),0) | X72: =+IFERROR(VLOOKUP($A72,'[22]1'!$A$5:$E$1048576,3,0),0) | Y72: =+IFERROR(VLOOKUP($A72,[23]Лист1!$A$5:$E$1048576,3,0),0) | Z72: =+IFERROR(VLOOKUP($A72,'[24]1'!$A$5:$E$1048576,3,0),0) | AA72: =+IFERROR(VLOOKUP($A72,[25]Balance!$A$5:$E$1048576,3,0),0) | AB72: =+IFERROR(VLOOKUP($A72,'[26]1'!$A$5:$E$1048576,3,0),0) | AC72: =+IFERROR(VLOOKUP($A72,'[27]1'!$A$5:$E$1048576,3,0),0) | AD72: =+IFERROR(VLOOKUP($A72,'[28]1'!$A$5:$E$1048576,3,0),0) | AE72: =+IFERROR(VLOOKUP($A72,[29]Лист1!$A$5:$E$1048576,3,0),0) | AF72: =+IFERROR(VLOOKUP($A72,'[30]1'!$A$5:$E$1048576,3,0),0) | AG72: =+IFERROR(VLOOKUP($A72,'[31]1'!$A$5:$E$1048576,3,0),0) | AH72: =+IFERROR(VLOOKUP($A72,'[32]1-жадвал'!$A$5:$E$1048576,3,0),0) | AI72: =+IFERROR(VLOOKUP($A72,[33]Balance!$A$5:$E$1048576,3,0),0) | AJ72: =+IFERROR(VLOOKUP($A72,[34]Balance!$A$5:$E$1048576,3,0),0) | AK72: =+IFERROR(VLOOKUP($A72,'[35]1'!$A$5:$E$1048576,3,0),0)
A73: 32.3 | B73: Бошқа захира фондлари | C73: =+IFERROR(VLOOKUP($A73,[1]Лист1!$A$5:$E$1048576,3,0),0) | D73: =+IFERROR(VLOOKUP($A73,'[2]1'!$A$5:$E$1048576,3,0),0) | E73: =+IFERROR(VLOOKUP($A73,'[3]1'!$A$5:$E$1048576,3,0),0) | F73: =+IFERROR(VLOOKUP($A73,[4]Balance!$A$5:$E$1048576,3,0),0) | G73: =+IFERROR(VLOOKUP($A73,'[5]1'!$A$5:$E$1048576,3,0),0) | H73: =+IFERROR(VLOOKUP($A73,[6]Balance!$A$5:$E$1048576,3,0),0) | I73: =+IFERROR(VLOOKUP($A73,[7]Balance!$A$5:$E$1048576,3,0),0) | J73: =+IFERROR(VLOOKUP($A73,'[8]1'!$A$5:$E$1048576,3,0),0) | K73: =+IFERROR(VLOOKUP($A73,'[9]1'!$A$5:$E$1048576,3,0),0) | L73: =+IFERROR(VLOOKUP($A73,'[10]1'!$A$5:$E$1048576,3,0),0) | M73: =+IFERROR(VLOOKUP($A73,'[11]1'!$A$5:$E$1048576,3,0),0) | N73: =+IFERROR(VLOOKUP($A73,[12]Balance!$A$5:$E$1048576,3,0),0) | O73: =+IFERROR(VLOOKUP($A73,'[13]1 т'!$A$5:$E$1048576,3,0),0) | P73: =+IFERROR(VLOOKUP($A73,[14]Balance!$A$5:$E$1048576,3,0),0) | Q73: =+IFERROR(VLOOKUP($A73,[15]Balance!$A$5:$E$1048576,3,0),0) | R73: =+IFERROR(VLOOKUP($A73,'[16]1'!$A$5:$E$1048576,3,0),0) | S73: =+IFERROR(VLOOKUP($A73,'[17]1'!$A$5:$E$1048576,3,0),0) | T73: =+IFERROR(VLOOKUP($A73,'[18]1'!$A$5:$E$1048576,3,0),0) | U73: =+IFERROR(VLOOKUP($A73,[19]Balans!$A$5:$E$1048576,3,0),0) | V73: =+IFERROR(VLOOKUP($A73,'[20]1'!$A$5:$E$1048576,3,0),0) | W73: =+IFERROR(VLOOKUP($A73,[21]Balance!$A$5:$E$1048576,3,0),0) | X73: =+IFERROR(VLOOKUP($A73,'[22]1'!$A$5:$E$1048576,3,0),0) | Y73: =+IFERROR(VLOOKUP($A73,[23]Лист1!$A$5:$E$1048576,3,0),0) | Z73: =+IFERROR(VLOOKUP($A73,'[24]1'!$A$5:$E$1048576,3,0),0) | AA73: =+IFERROR(VLOOKUP($A73,[25]Balance!$A$5:$E$1048576,3,0),0) | AB73: =+IFERROR(VLOOKUP($A73,'[26]1'!$A$5:$E$1048576,3,0),0) | AC73: =+IFERROR(VLOOKUP($A73,'[27]1'!$A$5:$E$1048576,3,0),0) | AD73: =+IFERROR(VLOOKUP($A73,'[28]1'!$A$5:$E$1048576,3,0),0) | AE73: =+IFERROR(VLOOKUP($A73,[29]Лист1!$A$5:$E$1048576,3,0),0) | AF73: =+IFERROR(VLOOKUP($A73,'[30]1'!$A$5:$E$1048576,3,0),0) | AG73: =+IFERROR(VLOOKUP($A73,'[31]1'!$A$5:$E$1048576,3,0),0) | AH73: =+IFERROR(VLOOKUP($A73,'[32]1-жадвал'!$A$5:$E$1048576,3,0),0) | AI73: =+IFERROR(VLOOKUP($A73,[33]Balance!$A$5:$E$1048576,3,0),0) | AJ73: =+IFERROR(VLOOKUP($A73,[34]Balance!$A$5:$E$1048576,3,0),0) | AK73: =+IFERROR(VLOOKUP($A73,'[35]1'!$A$5:$E$1048576,3,0),0)
A74: 33 | B74: Тақсимланмаган фойда | C74: =+IFERROR(VLOOKUP($A74,[1]Лист1!$A$5:$E$1048576,3,0),0) | D74: =+IFERROR(VLOOKUP($A74,'[2]1'!$A$5:$E$1048576,3,0),0) | E74: =+IFERROR(VLOOKUP($A74,'[3]1'!$A$5:$E$1048576,3,0),0) | F74: =+IFERROR(VLOOKUP($A74,[4]Balance!$A$5:$E$1048576,3,0),0) | G74: =+IFERROR(VLOOKUP($A74,'[5]1'!$A$5:$E$1048576,3,0),0) | H74: =+IFERROR(VLOOKUP($A74,[6]Balance!$A$5:$E$1048576,3,0),0) | I74: =+IFERROR(VLOOKUP($A74,[7]Balance!$A$5:$E$1048576,3,0),0) | J74: =+IFERROR(VLOOKUP($A74,'[8]1'!$A$5:$E$1048576,3,0),0) | K74: =+IFERROR(VLOOKUP($A74,'[9]1'!$A$5:$E$1048576,3,0),0) | L74: =+IFERROR(VLOOKUP($A74,'[10]1'!$A$5:$E$1048576,3,0),0) | M74: =+IFERROR(VLOOKUP($A74,'[11]1'!$A$5:$E$1048576,3,0),0) | N74: =+IFERROR(VLOOKUP($A74,[12]Balance!$A$5:$E$1048576,3,0),0) | O74: =+IFERROR(VLOOKUP($A74,'[13]1 т'!$A$5:$E$1048576,3,0),0) | P74: =+IFERROR(VLOOKUP($A74,[14]Balance!$A$5:$E$1048576,3,0),0) | Q74: =+IFERROR(VLOOKUP($A74,[15]Balance!$A$5:$E$1048576,3,0),0) | R74: =+IFERROR(VLOOKUP($A74,'[16]1'!$A$5:$E$1048576,3,0),0) | S74: =+IFERROR(VLOOKUP($A74,'[17]1'!$A$5:$E$1048576,3,0),0) | T74: =+IFERROR(VLOOKUP($A74,'[18]1'!$A$5:$E$1048576,3,0),0) | U74: =+IFERROR(VLOOKUP($A74,[19]Balans!$A$5:$E$1048576,3,0),0) | V74: =+IFERROR(VLOOKUP($A74,'[20]1'!$A$5:$E$1048576,3,0),0) | W74: =+IFERROR(VLOOKUP($A74,[21]Balance!$A$5:$E$1048576,3,0),0) | X74: =+IFERROR(VLOOKUP($A74,'[22]1'!$A$5:$E$1048576,3,0),0) | Y74: =+IFERROR(VLOOKUP($A74,[23]Лист1!$A$5:$E$1048576,3,0),0) | Z74: =+IFERROR(VLOOKUP($A74,'[24]1'!$A$5:$E$1048576,3,0),0) | AA74: =+IFERROR(VLOOKUP($A74,[25]Balance!$A$5:$E$1048576,3,0),0) | AB74: =+IFERROR(VLOOKUP($A74,'[26]1'!$A$5:$E$1048576,3,0),0) | AC74: =+IFERROR(VLOOKUP($A74,'[27]1'!$A$5:$E$1048576,3,0),0) | AD74: =+IFERROR(VLOOKUP($A74,'[28]1'!$A$5:$E$1048576,3,0),0) | AE74: =+IFERROR(VLOOKUP($A74,[29]Лист1!$A$5:$E$1048576,3,0),0) | AF74: =+IFERROR(VLOOKUP($A74,'[30]1'!$A$5:$E$1048576,3,0),0) | AG74: =+IFERROR(VLOOKUP($A74,'[31]1'!$A$5:$E$1048576,3,0),0) | AH74: =+IFERROR(VLOOKUP($A74,'[32]1-жадвал'!$A$5:$E$1048576,3,0),0) | AI74: =+IFERROR(VLOOKUP($A74,[33]Balance!$A$5:$E$1048576,3,0),0) | AJ74: =+IFERROR(VLOOKUP($A74,[34]Balance!$A$5:$E$1048576,3,0),0) | AK74: =+IFERROR(VLOOKUP($A74,'[35]1'!$A$5:$E$1048576,3,0),0)
A75: 33.1 | B75: шундан, жорий йил соф фойдаси (зарари) | C75: =+IFERROR(VLOOKUP($A75,[1]Лист1!$A$5:$E$1048576,3,0),0) | D75: =+IFERROR(VLOOKUP($A75,'[2]1'!$A$5:$E$1048576,3,0),0) | E75: =+IFERROR(VLOOKUP($A75,'[3]1'!$A$5:$E$1048576,3,0),0) | F75: =+IFERROR(VLOOKUP($A75,[4]Balance!$A$5:$E$1048576,3,0),0) | G75: =+IFERROR(VLOOKUP($A75,'[5]1'!$A$5:$E$1048576,3,0),0) | H75: =+IFERROR(VLOOKUP($A75,[6]Balance!$A$5:$E$1048576,3,0),0) | I75: =+IFERROR(VLOOKUP($A75,[7]Balance!$A$5:$E$1048576,3,0),0) | J75: =+IFERROR(VLOOKUP($A75,'[8]1'!$A$5:$E$1048576,3,0),0) | K75: =+IFERROR(VLOOKUP($A75,'[9]1'!$A$5:$E$1048576,3,0),0) | L75: =+IFERROR(VLOOKUP($A75,'[10]1'!$A$5:$E$1048576,3,0),0) | M75: =+IFERROR(VLOOKUP($A75,'[11]1'!$A$5:$E$1048576,3,0),0) | N75: =+IFERROR(VLOOKUP($A75,[12]Balance!$A$5:$E$1048576,3,0),0) | O75: =+IFERROR(VLOOKUP($A75,'[13]1 т'!$A$5:$E$1048576,3,0),0) | P75: =+IFERROR(VLOOKUP($A75,[14]Balance!$A$5:$E$1048576,3,0),0) | Q75: =+IFERROR(VLOOKUP($A75,[15]Balance!$A$5:$E$1048576,3,0),0) | R75: =+IFERROR(VLOOKUP($A75,'[16]1'!$A$5:$E$1048576,3,0),0) | S75: =+IFERROR(VLOOKUP($A75,'[17]1'!$A$5:$E$1048576,3,0),0) | T75: =+IFERROR(VLOOKUP($A75,'[18]1'!$A$5:$E$1048576,3,0),0) | U75: =+IFERROR(VLOOKUP($A75,[19]Balans!$A$5:$E$1048576,3,0),0) | V75: =+IFERROR(VLOOKUP($A75,'[20]1'!$A$5:$E$1048576,3,0),0) | W75: =+IFERROR(VLOOKUP($A75,[21]Balance!$A$5:$E$1048576,3,0),0) | X75: =+IFERROR(VLOOKUP($A75,'[22]1'!$A$5:$E$1048576,3,0),0) | Y75: =+IFERROR(VLOOKUP($A75,[23]Лист1!$A$5:$E$1048576,3,0),0) | Z75: =+IFERROR(VLOOKUP($A75,'[24]1'!$A$5:$E$1048576,3,0),0) | AA75: =+IFERROR(VLOOKUP($A75,[25]Balance!$A$5:$E$1048576,3,0),0) | AB75: =+IFERROR(VLOOKUP($A75,'[26]1'!$A$5:$E$1048576,3,0),0) | AC75: =+IFERROR(VLOOKUP($A75,'[27]1'!$A$5:$E$1048576,3,0),0) | AD75: =+IFERROR(VLOOKUP($A75,'[28]1'!$A$5:$E$1048576,3,0),0) | AE75: =+IFERROR(VLOOKUP($A75,[29]Лист1!$A$5:$E$1048576,3,0),0) | AF75: =+IFERROR(VLOOKUP($A75,'[30]1'!$A$5:$E$1048576,3,0),0) | AG75: =+IFERROR(VLOOKUP($A75,'[31]1'!$A$5:$E$1048576,3,0),0) | AH75: =+IFERROR(VLOOKUP($A75,'[32]1-жадвал'!$A$5:$E$1048576,3,0),0) | AI75: =+IFERROR(VLOOKUP($A75,[33]Balance!$A$5:$E$1048576,3,0),0) | AJ75: =+IFERROR(VLOOKUP($A75,[34]Balance!$A$5:$E$1048576,3,0),0) | AK75: =+IFERROR(VLOOKUP($A75,'[35]1'!$A$5:$E$1048576,3,0),0)
A76: 34 | B76: Жами хусусий капитал | C76: =+IFERROR(VLOOKUP($A76,[1]Лист1!$A$5:$E$1048576,3,0),0) | D76: =+IFERROR(VLOOKUP($A76,'[2]1'!$A$5:$E$1048576,3,0),0) | E76: =+IFERROR(VLOOKUP($A76,'[3]1'!$A$5:$E$1048576,3,0),0) | F76: =+IFERROR(VLOOKUP($A76,[4]Balance!$A$5:$E$1048576,3,0),0) | G76: =+IFERROR(VLOOKUP($A76,'[5]1'!$A$5:$E$1048576,3,0),0) | H76: =+IFERROR(VLOOKUP($A76,[6]Balance!$A$5:$E$1048576,3,0),0) | I76: =+IFERROR(VLOOKUP($A76,[7]Balance!$A$5:$E$1048576,3,0),0) | J76: =+IFERROR(VLOOKUP($A76,'[8]1'!$A$5:$E$1048576,3,0),0) | K76: =+IFERROR(VLOOKUP($A76,'[9]1'!$A$5:$E$1048576,3,0),0) | L76: =+IFERROR(VLOOKUP($A76,'[10]1'!$A$5:$E$1048576,3,0),0) | M76: =+IFERROR(VLOOKUP($A76,'[11]1'!$A$5:$E$1048576,3,0),0) | N76: =+IFERROR(VLOOKUP($A76,[12]Balance!$A$5:$E$1048576,3,0),0) | O76: =+IFERROR(VLOOKUP($A76,'[13]1 т'!$A$5:$E$1048576,3,0),0) | P76: =+IFERROR(VLOOKUP($A76,[14]Balance!$A$5:$E$1048576,3,0),0) | Q76: =+IFERROR(VLOOKUP($A76,[15]Balance!$A$5:$E$1048576,3,0),0) | R76: =+IFERROR(VLOOKUP($A76,'[16]1'!$A$5:$E$1048576,3,0),0) | S76: =+IFERROR(VLOOKUP($A76,'[17]1'!$A$5:$E$1048576,3,0),0) | T76: =+IFERROR(VLOOKUP($A76,'[18]1'!$A$5:$E$1048576,3,0),0) | U76: =+IFERROR(VLOOKUP($A76,[19]Balans!$A$5:$E$1048576,3,0),0) | V76: =+IFERROR(VLOOKUP($A76,'[20]1'!$A$5:$E$1048576,3,0),0) | W76: =+IFERROR(VLOOKUP($A76,[21]Balance!$A$5:$E$1048576,3,0),0) | X76: =+IFERROR(VLOOKUP($A76,'[22]1'!$A$5:$E$1048576,3,0),0) | Y76: =+IFERROR(VLOOKUP($A76,[23]Лист1!$A$5:$E$1048576,3,0),0) | Z76: =+IFERROR(VLOOKUP($A76,'[24]1'!$A$5:$E$1048576,3,0),0) | AA76: =+IFERROR(VLOOKUP($A76,[25]Balance!$A$5:$E$1048576,3,0),0) | AB76: =+IFERROR(VLOOKUP($A76,'[26]1'!$A$5:$E$1048576,3,0),0) | AC76: =+IFERROR(VLOOKUP($A76,'[27]1'!$A$5:$E$1048576,3,0),0) | AD76: =+IFERROR(VLOOKUP($A76,'[28]1'!$A$5:$E$1048576,3,0),0) | AE76: =+IFERROR(VLOOKUP($A76,[29]Лист1!$A$5:$E$1048576,3,0),0) | AF76: =+IFERROR(VLOOKUP($A76,'[30]1'!$A$5:$E$1048576,3,0),0) | AG76: =+IFERROR(VLOOKUP($A76,'[31]1'!$A$5:$E$1048576,3,0),0) | AH76: =+IFERROR(VLOOKUP($A76,'[32]1-жадвал'!$A$5:$E$1048576,3,0),0) | AI76: =+IFERROR(VLOOKUP($A76,[33]Balance!$A$5:$E$1048576,3,0),0) | AJ76: =+IFERROR(VLOOKUP($A76,[34]Balance!$A$5:$E$1048576,3,0),0) | AK76: =+IFERROR(VLOOKUP($A76,'[35]1'!$A$5:$E$1048576,3,0),0)
A77: 35 | B77: Жами мажбуриятлар ва хусусий капитал | C77: =+IFERROR(VLOOKUP($A77,[1]Лист1!$A$5:$E$1048576,3,0),0) | D77: =+IFERROR(VLOOKUP($A77,'[2]1'!$A$5:$E$1048576,3,0),0) | E77: =+IFERROR(VLOOKUP($A77,'[3]1'!$A$5:$E$1048576,3,0),0) | F77: =+IFERROR(VLOOKUP($A77,[4]Balance!$A$5:$E$1048576,3,0),0) | G77: =+IFERROR(VLOOKUP($A77,'[5]1'!$A$5:$E$1048576,3,0),0) | H77: =+IFERROR(VLOOKUP($A77,[6]Balance!$A$5:$E$1048576,3,0),0) | I77: =+IFERROR(VLOOKUP($A77,[7]Balance!$A$5:$E$1048576,3,0),0) | J77: =+IFERROR(VLOOKUP($A77,'[8]1'!$A$5:$E$1048576,3,0),0) | K77: =+IFERROR(VLOOKUP($A77,'[9]1'!$A$5:$E$1048576,3,0),0) | L77: =+IFERROR(VLOOKUP($A77,'[10]1'!$A$5:$E$1048576,3,0),0) | M77: =+IFERROR(VLOOKUP($A77,'[11]1'!$A$5:$E$1048576,3,0),0) | N77: =+IFERROR(VLOOKUP($A77,[12]Balance!$A$5:$E$1048576,3,0),0) | O77: =+IFERROR(VLOOKUP($A77,'[13]1 т'!$A$5:$E$1048576,3,0),0) | P77: =+IFERROR(VLOOKUP($A77,[14]Balance!$A$5:$E$1048576,3,0),0) | Q77: =+IFERROR(VLOOKUP($A77,[15]Balance!$A$5:$E$1048576,3,0),0) | R77: =+IFERROR(VLOOKUP($A77,'[16]1'!$A$5:$E$1048576,3,0),0) | S77: =+IFERROR(VLOOKUP($A77,'[17]1'!$A$5:$E$1048576,3,0),0) | T77: =+IFERROR(VLOOKUP($A77,'[18]1'!$A$5:$E$1048576,3,0),0) | U77: =+IFERROR(VLOOKUP($A77,[19]Balans!$A$5:$E$1048576,3,0),0) | V77: =+IFERROR(VLOOKUP($A77,'[20]1'!$A$5:$E$1048576,3,0),0) | W77: =+IFERROR(VLOOKUP($A77,[21]Balance!$A$5:$E$1048576,3,0),0) | X77: =+IFERROR(VLOOKUP($A77,'[22]1'!$A$5:$E$1048576,3,0),0) | Y77: =+IFERROR(VLOOKUP($A77,[23]Лист1!$A$5:$E$1048576,3,0),0) | Z77: =+IFERROR(VLOOKUP($A77,'[24]1'!$A$5:$E$1048576,3,0),0) | AA77: =+IFERROR(VLOOKUP($A77,[25]Balance!$A$5:$E$1048576,3,0),0) | AB77: =+IFERROR(VLOOKUP($A77,'[26]1'!$A$5:$E$1048576,3,0),0) | AC77: =+IFERROR(VLOOKUP($A77,'[27]1'!$A$5:$E$1048576,3,0),0) | AD77: =+IFERROR(VLOOKUP($A77,'[28]1'!$A$5:$E$1048576,3,0),0) | AE77: =+IFERROR(VLOOKUP($A77,[29]Лист1!$A$5:$E$1048576,3,0),0) | AF77: =+IFERROR(VLOOKUP($A77,'[30]1'!$A$5:$E$1048576,3,0),0) | AG77: =+IFERROR(VLOOKUP($A77,'[31]1'!$A$5:$E$1048576,3,0),0) | AH77: =+IFERROR(VLOOKUP($A77,'[32]1-жадвал'!$A$5:$E$1048576,3,0),0) | AI77: =+IFERROR(VLOOKUP($A77,[33]Balance!$A$5:$E$1048576,3,0),0) | AJ77: =+IFERROR(VLOOKUP($A77,[34]Balance!$A$5:$E$1048576,3,0),0) | AK77: =+IFERROR(VLOOKUP($A77,'[35]1'!$A$5:$E$1048576,3,0),0)
B79: Банкнинг Марказий банкдаги маблағлари (мажбурий захирасиз) | C79: =+[1]Лист3!$C$7 | D79: =+'[2]17'!$C$7 | E79: =+'[3]3'!$C$7 | F79: =+'[4]Bank Assets Analysis'!$C$7 | G79: =+'[5]17'!$C$7 | H79: =+'[6]Bank Assets Analysis'!$C$7 | I79: =+'[7]Bank Assets Analysis'!$C$7 | J79: =+'[8]17'!$C$7 | K79: =+'[9]17'!$C$7 | L79: =+'[10]17'!$C$7 | M79: =+'[11]17'!$C$7 | N79: =+'[12]Bank Asset Analysis'!$C$7 | O79: =+'[13]17 т'!$C$7 | P79: =+'[14]Bank Assets Analysis'!$C$7 | Q79: =+'[15]Bank Assets Analysis'!$C$7 | R79: =+'[16]17'!$C$7 | S79: =+'[17]17'!$C$7 | T79: =+'[18]3'!$C$7 | U79: =+'[19]Bank Assets analysis'!$C$7 | V79: =+'[20]17'!$C$7 | W79: =+'[21]Bank Assets Analysis'!$C$7 | X79: =+'[22]17'!$C$7 | Y79: =+[23]Лист2!$C$7 | Z79: =+'[24]3'!$C$7 | AA79: =+[25]Assets!$C$7 | AB79: =+'[26]17'!$C$7 | AC79: =+'[27]17'!$C$7 | AD79: =+'[28]17'!$C$7 | AE79: =+[29]Лист3!$C$7 | AF79: =+'[30]17'!$C$7 | AG79: =+'[31]17'!$C$7 | AH79: =+'[32]17-жадвал'!$C$7 | AI79: =+[33]Assets!$C$7 | AJ79: =+'[34]Bank Assets Analysis'!$C$7 | AK79: =+'[35]17'!$C$7
B80: Бошқа банклар ва молиявий ташкилотлардан олиниши лозим бўлган маблағлар (бесроч.) | C80: =+[1]Лист3!$C$9 | D80: =+'[2]17'!$C$9 | E80: =+'[3]3'!$C$9 | F80: =+'[4]Bank Assets Analysis'!$C$9 | G80: =+'[5]17'!$C$9 | H80: =+'[6]Bank Assets Analysis'!$C$9 | I80: =+'[7]Bank Assets Analysis'!$C$9 | J80: =+'[8]17'!$C$9 | K80: =+'[9]17'!$C$9 | L80: =+'[10]17'!$C$9 | M80: =+'[11]17'!$C$9 | N80: =+'[12]Bank Asset Analysis'!$C$9 | O80: =+'[13]17 т'!$C$9 | P80: =+'[14]Bank Assets Analysis'!$C$9 | Q80: =+'[15]Bank Assets Analysis'!$C$9 | R80: =+'[16]17'!$C$9 | S80: =+'[17]17'!$C$9 | T80: =+'[18]3'!$C$9 | U80: =+'[19]Bank Assets analysis'!$C$9 | V80: =+'[20]17'!$C$9 | W80: =+'[21]Bank Assets Analysis'!$C$9 | X80: =+'[22]17'!$C$9 | Y80: =+[23]Лист2!$C$9 | Z80: =+'[24]3'!$C$9 | AA80: =+[25]Assets!$C$9 | AB80: =+'[26]17'!$C$9 | AC80: =+'[27]17'!$C$9 | AD80: =+'[28]17'!$C$9 | AE80: =+[29]Лист3!$C$9 | AF80: =+'[30]17'!$C$9 | AG80: =+'[31]17'!$C$9 | AH80: =+'[32]17-жадвал'!$C$9 | AI80: =+[33]Assets!$C$9 | AJ80: =+'[34]Bank Assets Analysis'!$C$9 | AK80: =+'[35]17'!$C$9
B81: Бошқа банклар ва молиявий ташкилотлардан олиниши лозим бўлган маблағлар (1-30 кун) | C81: =+[1]Лист3!$E$9+[1]Лист3!$G$9 | D81: =+'[2]17'!$E$9+'[2]17'!$G$9 | E81: =+'[3]3'!$E$9+'[3]3'!$G$9 | F81: =+'[4]Bank Assets Analysis'!$E$9+'[4]Bank Assets Analysis'!$G$9 | G81: =+'[5]17'!$E$9+'[5]17'!$G$9 | H81: =+'[6]Bank Assets Analysis'!$E$9+'[6]Bank Assets Analysis'!$G$9 | I81: =+'[7]Bank Assets Analysis'!$E$9+'[7]Bank Assets Analysis'!$G$9 | J81: =+'[8]17'!$E$9+'[8]17'!$G$9 | K81: =+'[9]17'!$E$9+'[9]17'!$G$9 | L81: =+'[10]17'!$E$9+'[10]17'!$G$9 | M81: =+'[11]17'!$E$9+'[11]17'!$G$9 | N81: =+'[12]Bank Asset Analysis'!$E$9+'[12]Bank Asset Analysis'!$G$9 | O81: =+'[13]17 т'!$E$9+'[13]17 т'!$G$9 | P81: =+'[14]Bank Assets Analysis'!$E$9+'[14]Bank Assets Analysis'!$G$9 | Q81: =+'[15]Bank Assets Analysis'!$E$9+'[15]Bank Assets Analysis'!$G$9 | R81: =+'[16]17'!$E$9+'[16]17'!$G$9 | S81: =+'[17]17'!$E$9+'[17]17'!$G$9 | T81: =+'[18]3'!$E$9+'[18]3'!$G$9 | U81: =+'[19]Bank Assets analysis'!$E$9+'[19]Bank Assets analysis'!$G$9 | V81: =+'[20]17'!$E$9+'[20]17'!$G$9 | W81: =+'[21]Bank Assets Analysis'!$E$9+'[21]Bank Assets Analysis'!$G$9 | X81: =+'[22]17'!$E$9+'[22]17'!$G$9 | Y81: =+[23]Лист2!$E$9+[23]Лист2!$G$9 | Z81: =+'[24]3'!$E$9+'[24]3'!$G$9 | AA81: =+[25]Assets!$E$9+[25]Assets!$G$9 | AB81: =+'[26]17'!$E$9+'[26]17'!$G$9 | AC81: =+'[27]17'!$E$9+'[27]17'!$G$9 | AD81: =+'[28]17'!$E$9+'[28]17'!$G$9 | AE81: =+[29]Лист3!$E$9+[29]Лист3!$G$9 | AF81: =+'[30]17'!$E$9+'[30]17'!$G$9 | AG81: =+'[31]17'!$E$9+'[31]17'!$G$9 | AH81: =+'[32]17-жадвал'!$E$9+'[32]17-жадвал'!$G$9 | AI81: =+[33]Assets!$E$9+[33]Assets!$G$9 | AJ81: =+'[34]Bank Assets Analysis'!$E$9+'[34]Bank Assets Analysis'!$G$9 | AK81: =+'[35]17'!$E$9+'[35]17'!$G$9
B82: P&L
A83: 1 | B83: Жами фоизли даромадлар | C83: =+IFERROR(VLOOKUP(B83,[1]Лист2!$B$6:$E$1048576,2,0),0) | D83: =+IFERROR(VLOOKUP(B83,'[2]3'!$B$6:$D$1048576,2,0),0) | E83: =+IFERROR(VLOOKUP(B83,'[3]2'!$B$5:$C$77,2,0),0) | F83: =+IFERROR(VLOOKUP(B83,'[4]Income '!$B$5:$E$77,2,0),0) | G83: =+IFERROR(VLOOKUP(B83,'[5]3'!$B$6:$C$1048576,2,0),0) | H83: =+IFERROR(VLOOKUP(B83,[6]Income!$B$6:$D$1048576,2,0),0) | I83: =+IFERROR(VLOOKUP(B83,'[7]Income '!$B$6:$E$1048576,2,0),0) | J83: =+IFERROR(VLOOKUP(B83,'[8]3'!$B$5:$C$77,2,0),0) | K83: =+IFERROR(VLOOKUP(B83,'[9]3'!$B$6:$E$1048576,2,0),0) | L83: =+IFERROR(VLOOKUP(B83,'[10]3'!$B$6:$E$1048576,2,0),0) | M83: =+IFERROR(VLOOKUP(B83,'[11]3'!$B$6:$E$1048576,2,0),0) | N83: =+IFERROR(VLOOKUP(B83,[12]Income!$B$6:$D$1048576,2,0),0) | O83: =+IFERROR(VLOOKUP(B83,'[13]3 т'!$B$6:$C$1048576,2,0),0) | P83: =+IFERROR(VLOOKUP(B83,[14]Income!$B$6:$D$1048576,2,0),0) | Q83: =+IFERROR(VLOOKUP(B83,[15]Income!$B$6:$E$1048576,2,0),0) | R83: =+IFERROR(VLOOKUP(B83,'[16]3'!$B$5:$E$90,2,0),0) | S83: =+IFERROR(VLOOKUP(B83,'[17]3'!$B$6:$E$1048576,2,0),0) | T83: =+IFERROR(VLOOKUP(B83,'[18]2'!$B$5:$E$78,2,0),0) | U83: =+IFERROR(VLOOKUP(B83,[19]Income!$B$6:$D$1048576,2,0),0) | V83: =+IFERROR(VLOOKUP(B83,'[20]3'!$B$6:$E$1048576,2,0),0) | W83: =+IFERROR(VLOOKUP(B83,'[21]Income '!$B$6:$D$1048576,2,0),0) | X83: =+IFERROR(VLOOKUP(B83,'[22]3'!$B$6:$D$1048576,2,0),0) | Y83: =+IFERROR(VLOOKUP(B83,[23]Лист4!$B$5:$C$78,2,0),0) | Z83: =+IFERROR(VLOOKUP(B83,'[24]2'!$B$5:$C$78,2,0),0) | AA83: =+IFERROR(VLOOKUP(B83,[25]Income!$B$5:$C$78,2,0),0) | AB83: =+IFERROR(VLOOKUP(B83,'[26]3'!$B$6:$E$1048576,2,0),0) | AC83: =+IFERROR(VLOOKUP(B83,'[27]3'!$B$6:$E$1048576,2,0),0) | AD83: =+IFERROR(VLOOKUP(B83,'[28]3'!$B$6:$E$1048576,2,0),0) | AE83: =+IFERROR(VLOOKUP(B83,[29]Лист2!$B$6:$E$1048576,2,0),0) | AF83: =+IFERROR(VLOOKUP($B83,'[30]3'!$B$6:$E$1048576,2,0),0) | AG83: =+IFERROR(VLOOKUP(B83,'[31]3'!$B$6:$D$1048576,2,0),0) | AH83: =+IFERROR(VLOOKUP(B83,'[32]3-жадвал'!$B$6:$C$1048576,2,0),0) | AI83: =+IFERROR(VLOOKUP(B83,[33]Income!$B$5:$C$78,2,0),0) | AJ83: =+IFERROR(VLOOKUP(B83,[34]Income!$B$6:$D$1048576,2,0),0) | AK83: =+IFERROR(VLOOKUP($B83,'[35]3'!$B$6:$D$1048576,2,0),0)
A84: 2 | B84: Жами фоизли харажатлар | C84: =+IFERROR(VLOOKUP(B84,[1]Лист2!$B$6:$E$1048576,2,0),0) | D84: =+IFERROR(VLOOKUP(B84,'[2]3'!$B$6:$D$1048576,2,0),0) | E84: =+IFERROR(VLOOKUP(B84,'[3]2'!$B$5:$C$77,2,0),0) | F84: =+IFERROR(VLOOKUP(B84,'[4]Income '!$B$5:$E$77,2,0),0) | G84: =+IFERROR(VLOOKUP(B84,'[5]3'!$B$6:$C$1048576,2,0),0) | H84: =+IFERROR(VLOOKUP(B84,[6]Income!$B$6:$D$1048576,2,0),0) | I84: =+IFERROR(VLOOKUP(B84,'[7]Income '!$B$6:$E$1048576,2,0),0) | J84: =+IFERROR(VLOOKUP(B84,'[8]3'!$B$5:$C$77,2,0),0) | K84: =+IFERROR(VLOOKUP(B84,'[9]3'!$B$6:$E$1048576,2,0),0) | L84: =+IFERROR(VLOOKUP(B84,'[10]3'!$B$6:$E$1048576,2,0),0) | M84: =+IFERROR(VLOOKUP(B84,'[11]3'!$B$6:$E$1048576,2,0),0) | N84: =+IFERROR(VLOOKUP(B84,[12]Income!$B$6:$D$1048576,2,0),0) | O84: =+IFERROR(VLOOKUP(B84,'[13]3 т'!$B$6:$C$1048576,2,0),0) | P84: =+IFERROR(VLOOKUP(B84,[14]Income!$B$6:$D$1048576,2,0),0) | Q84: =+IFERROR(VLOOKUP(B84,[15]Income!$B$6:$E$1048576,2,0),0) | R84: =+IFERROR(VLOOKUP(B84,'[16]3'!$B$5:$E$90,2,0),0) | S84: =+IFERROR(VLOOKUP(B84,'[17]3'!$B$6:$E$1048576,2,0),0) | T84: =+IFERROR(VLOOKUP(B84,'[18]2'!$B$5:$E$78,2,0),0) | U84: =+IFERROR(VLOOKUP(B84,[19]Income!$B$6:$D$1048576,2,0),0) | V84: =+IFERROR(VLOOKUP(B84,'[20]3'!$B$6:$E$1048576,2,0),0) | W84: =+IFERROR(VLOOKUP(B84,'[21]Income '!$B$6:$D$1048576,2,0),0) | X84: =+IFERROR(VLOOKUP(B84,'[22]3'!$B$6:$D$1048576,2,0),0) | Y84: =+IFERROR(VLOOKUP(B84,[23]Лист4!$B$5:$C$78,2,0),0) | Z84: =+IFERROR(VLOOKUP(B84,'[24]2'!$B$5:$C$78,2,0),0) | AA84: =+IFERROR(VLOOKUP(B84,[25]Income!$B$5:$C$78,2,0),0) | AB84: =+IFERROR(VLOOKUP(B84,'[26]3'!$B$6:$E$1048576,2,0),0) | AC84: =+IFERROR(VLOOKUP(B84,'[27]3'!$B$6:$E$1048576,2,0),0) | AD84: =+IFERROR(VLOOKUP(B84,'[28]3'!$B$6:$E$1048576,2,0),0) | AE84: =+IFERROR(VLOOKUP(B84,[29]Лист2!$B$6:$E$1048576,2,0),0) | AF84: =+IFERROR(VLOOKUP($B84,'[30]3'!$B$6:$E$1048576,2,0),0) | AG84: =+IFERROR(VLOOKUP(B84,'[31]3'!$B$6:$D$1048576,2,0),0) | AH84: =+IFERROR(VLOOKUP(B84,'[32]3-жадвал'!$B$6:$C$1048576,2,0),0) | AI84: =+IFERROR(VLOOKUP(B84,[33]Income!$B$5:$C$78,2,0),0) | AJ84: =+IFERROR(VLOOKUP(B84,[34]Income!$B$6:$D$1048576,2,0),0) | AK84: =+IFERROR(VLOOKUP($B84,'[35]3'!$B$6:$D$1048576,2,0),0)
A85: 3 | B85: Активлар бўйича эҳтимолий йўқотишларга қарши яратилган захираларни баҳолашдан олдинги соф даромад | C85: =+IFERROR(VLOOKUP(B85,[1]Лист2!$B$6:$E$1048576,2,0),0) | D85: =+IFERROR(VLOOKUP(B85,'[2]3'!$B$6:$D$1048576,2,0),0) | E85: =+IFERROR(VLOOKUP(B85,'[3]2'!$B$5:$C$77,2,0),0) | F85: =+IFERROR(VLOOKUP(B85,'[4]Income '!$B$5:$E$77,2,0),0) | G85: =+IFERROR(VLOOKUP(B85,'[5]3'!$B$6:$C$1048576,2,0),0) | H85: =+IFERROR(VLOOKUP(B85,[6]Income!$B$6:$D$1048576,2,0),0) | I85: =+IFERROR(VLOOKUP(B85,'[7]Income '!$B$6:$E$1048576,2,0),0) | J85: =+IFERROR(VLOOKUP(B85,'[8]3'!$B$5:$C$77,2,0),0) | K85: =+IFERROR(VLOOKUP(B85,'[9]3'!$B$6:$E$1048576,2,0),0) | L85: =+IFERROR(VLOOKUP(B85,'[10]3'!$B$6:$E$1048576,2,0),0) | M85: =+IFERROR(VLOOKUP(B85,'[11]3'!$B$6:$E$1048576,2,0),0) | N85: =+IFERROR(VLOOKUP(B85,[12]Income!$B$6:$D$1048576,2,0),0) | O85: =+IFERROR(VLOOKUP(B85,'[13]3 т'!$B$6:$C$1048576,2,0),0) | P85: =+IFERROR(VLOOKUP(B85,[14]Income!$B$6:$D$1048576,2,0),0) | Q85: =+IFERROR(VLOOKUP(B85,[15]Income!$B$6:$E$1048576,2,0),0) | R85: =+IFERROR(VLOOKUP(B85,'[16]3'!$B$5:$E$90,2,0),0) | S85: =+IFERROR(VLOOKUP(B85,'[17]3'!$B$6:$E$1048576,2,0),0) | T85: =+IFERROR(VLOOKUP(B85,'[18]2'!$B$5:$E$78,2,0),0) | U85: =+IFERROR(VLOOKUP(B85,[19]Income!$B$6:$D$1048576,2,0),0) | V85: =+IFERROR(VLOOKUP(B85,'[20]3'!$B$6:$E$1048576,2,0),0) | W85: =+IFERROR(VLOOKUP(B85,'[21]Income '!$B$6:$D$1048576,2,0),0) | X85: =+IFERROR(VLOOKUP(B85,'[22]3'!$B$6:$D$1048576,2,0),0) | Y85: =+IFERROR(VLOOKUP(B85,[23]Лист4!$B$5:$C$78,2,0),0) | Z85: =+IFERROR(VLOOKUP(B85,'[24]2'!$B$5:$C$78,2,0),0) | AA85: =+IFERROR(VLOOKUP(B85,[25]Income!$B$5:$C$78,2,0),0) | AB85: =+IFERROR(VLOOKUP(B85,'[26]3'!$B$6:$E$1048576,2,0),0) | AC85: =+IFERROR(VLOOKUP(B85,'[27]3'!$B$6:$E$1048576,2,0),0) | AD85: =+IFERROR(VLOOKUP(B85,'[28]3'!$B$6:$E$1048576,2,0),0) | AE85: =+IFERROR(VLOOKUP(B85,[29]Лист2!$B$6:$E$1048576,2,0),0) | AF85: =+IFERROR(VLOOKUP($B85,'[30]3'!$B$6:$E$1048576,2,0),0) | AG85: =+IFERROR(VLOOKUP(B85,'[31]3'!$B$6:$D$1048576,2,0),0) | AH85: =+IFERROR(VLOOKUP(B85,'[32]3-жадвал'!$B$6:$C$1048576,2,0),0) | AI85: =+IFERROR(VLOOKUP(B85,[33]Income!$B$5:$C$78,2,0),0) | AJ85: =+IFERROR(VLOOKUP(B85,[34]Income!$B$6:$D$1048576,2,0),0) | AK85: =+IFERROR(VLOOKUP($B85,'[35]3'!$B$6:$D$1048576,2,0),0)
A86: а. | B86: Минус: Кредит ва лизинглар бўйича кўрилиши мумкин бўлган зарарларни баҳолаш | C86: =+IFERROR(VLOOKUP(B86,[1]Лист2!$B$6:$E$1048576,2,0),0) | D86: =+IFERROR(VLOOKUP(B86,'[2]3'!$B$6:$D$1048576,2,0),0) | E86: =+IFERROR(VLOOKUP(B86,'[3]2'!$B$5:$C$77,2,0),0) | F86: =+IFERROR(VLOOKUP(B86,'[4]Income '!$B$5:$E$77,2,0),0) | G86: =+IFERROR(VLOOKUP(B86,'[5]3'!$B$6:$C$1048576,2,0),0) | H86: =+IFERROR(VLOOKUP(B86,[6]Income!$B$6:$D$1048576,2,0),0) | I86: =+IFERROR(VLOOKUP(B86,'[7]Income '!$B$6:$E$1048576,2,0),0) | J86: =+IFERROR(VLOOKUP(B86,'[8]3'!$B$5:$C$77,2,0),0) | K86: =+IFERROR(VLOOKUP(B86,'[9]3'!$B$6:$E$1048576,2,0),0) | L86: =+IFERROR(VLOOKUP(B86,'[10]3'!$B$6:$E$1048576,2,0),0) | M86: =+IFERROR(VLOOKUP(B86,'[11]3'!$B$6:$E$1048576,2,0),0) | N86: =+IFERROR(VLOOKUP(B86,[12]Income!$B$6:$D$1048576,2,0),0) | O86: =+IFERROR(VLOOKUP(B86,'[13]3 т'!$B$6:$C$1048576,2,0),0) | P86: =+IFERROR(VLOOKUP(B86,[14]Income!$B$6:$D$1048576,2,0),0) | Q86: =+IFERROR(VLOOKUP(B86,[15]Income!$B$6:$E$1048576,2,0),0) | R86: =+IFERROR(VLOOKUP(B86,'[16]3'!$B$5:$E$90,2,0),0) | S86: =+IFERROR(VLOOKUP(B86,'[17]3'!$B$6:$E$1048576,2,0),0) | T86: =+IFERROR(VLOOKUP(B86,'[18]2'!$B$5:$E$78,2,0),0) | U86: =+IFERROR(VLOOKUP(B86,[19]Income!$B$6:$D$1048576,2,0),0) | V86: =+IFERROR(VLOOKUP(B86,'[20]3'!$B$6:$E$1048576,2,0),0) | W86: =+IFERROR(VLOOKUP(B86,'[21]Income '!$B$6:$D$1048576,2,0),0) | X86: =+IFERROR(VLOOKUP(B86,'[22]3'!$B$6:$D$1048576,2,0),0) | Y86: =+IFERROR(VLOOKUP(B86,[23]Лист4!$B$5:$C$78,2,0),0) | Z86: =+IFERROR(VLOOKUP(B86,'[24]2'!$B$5:$C$78,2,0),0) | AA86: =+IFERROR(VLOOKUP(B86,[25]Income!$B$5:$C$78,2,0),0) | AB86: =+IFERROR(VLOOKUP(B86,'[26]3'!$B$6:$E$1048576,2,0),0) | AC86: =+IFERROR(VLOOKUP(B86,'[27]3'!$B$6:$E$1048576,2,0),0) | AD86: =+IFERROR(VLOOKUP(B86,'[28]3'!$B$6:$E$1048576,2,0),0) | AE86: =+IFERROR(VLOOKUP(B86,[29]Лист2!$B$6:$E$1048576,2,0),0) | AF86: =+IFERROR(VLOOKUP($B86,'[30]3'!$B$6:$E$1048576,2,0),0) | AG86: =+IFERROR(VLOOKUP(B86,'[31]3'!$B$6:$D$1048576,2,0),0) | AH86: =+IFERROR(VLOOKUP(B86,'[32]3-жадвал'!$B$6:$C$1048576,2,0),0) | AI86: =+IFERROR(VLOOKUP(B86,[33]Income!$B$5:$C$78,2,0),0) | AJ86: =+IFERROR(VLOOKUP(B86,[34]Income!$B$6:$D$1048576,2,0),0) | AK86: =+IFERROR(VLOOKUP($B86,'[35]3'!$B$6:$D$1048576,2,0),0)
A87: б. | B87: Минус: Қимматли қоғозлар бўйича кўрилиши мумкин бўлган зарарларни баҳолаш | C87: =+IFERROR(VLOOKUP(B87,[1]Лист2!$B$6:$E$1048576,2,0),0) | D87: =+IFERROR(VLOOKUP(B87,'[2]3'!$B$6:$D$1048576,2,0),0) | E87: =+IFERROR(VLOOKUP(B87,'[3]2'!$B$5:$C$77,2,0),0) | F87: =+IFERROR(VLOOKUP(B87,'[4]Income '!$B$5:$E$77,2,0),0) | G87: =+IFERROR(VLOOKUP(B87,'[5]3'!$B$6:$C$1048576,2,0),0) | H87: =+IFERROR(VLOOKUP(B87,[6]Income!$B$6:$D$1048576,2,0),0) | I87: =+IFERROR(VLOOKUP(B87,'[7]Income '!$B$6:$E$1048576,2,0),0) | J87: =+IFERROR(VLOOKUP(B87,'[8]3'!$B$5:$C$77,2,0),0) | K87: =+IFERROR(VLOOKUP(B87,'[9]3'!$B$6:$E$1048576,2,0),0) | L87: =+IFERROR(VLOOKUP(B87,'[10]3'!$B$6:$E$1048576,2,0),0) | M87: =+IFERROR(VLOOKUP(B87,'[11]3'!$B$6:$E$1048576,2,0),0) | N87: =+IFERROR(VLOOKUP(B87,[12]Income!$B$6:$D$1048576,2,0),0) | O87: =+IFERROR(VLOOKUP(B87,'[13]3 т'!$B$6:$C$1048576,2,0),0) | P87: =+IFERROR(VLOOKUP(B87,[14]Income!$B$6:$D$1048576,2,0),0) | Q87: =+IFERROR(VLOOKUP(B87,[15]Income!$B$6:$E$1048576,2,0),0) | R87: =+IFERROR(VLOOKUP(B87,'[16]3'!$B$5:$E$90,2,0),0) | S87: =+IFERROR(VLOOKUP(B87,'[17]3'!$B$6:$E$1048576,2,0),0) | T87: =+IFERROR(VLOOKUP(B87,'[18]2'!$B$5:$E$78,2,0),0) | U87: =+IFERROR(VLOOKUP(B87,[19]Income!$B$6:$D$1048576,2,0),0) | V87: =+IFERROR(VLOOKUP(B87,'[20]3'!$B$6:$E$1048576,2,0),0) | W87: =+IFERROR(VLOOKUP(B87,'[21]Income '!$B$6:$D$1048576,2,0),0) | X87: =+IFERROR(VLOOKUP(B87,'[22]3'!$B$6:$D$1048576,2,0),0) | Y87: =+IFERROR(VLOOKUP(B87,[23]Лист4!$B$5:$C$78,2,0),0) | Z87: =+IFERROR(VLOOKUP(B87,'[24]2'!$B$5:$C$78,2,0),0) | AA87: =+IFERROR(VLOOKUP(B87,[25]Income!$B$5:$C$78,2,0),0) | AB87: =+IFERROR(VLOOKUP(B87,'[26]3'!$B$6:$E$1048576,2,0),0) | AC87: =+IFERROR(VLOOKUP(B87,'[27]3'!$B$6:$E$1048576,2,0),0) | AD87: =+IFERROR(VLOOKUP(B87,'[28]3'!$B$6:$E$1048576,2,0),0) | AE87: =+IFERROR(VLOOKUP(B87,[29]Лист2!$B$6:$E$1048576,2,0),0) | AF87: =+IFERROR(VLOOKUP($B87,'[30]3'!$B$6:$E$1048576,2,0),0) | AG87: =+IFERROR(VLOOKUP(B87,'[31]3'!$B$6:$D$1048576,2,0),0) | AH87: =+IFERROR(VLOOKUP(B87,'[32]3-жадвал'!$B$6:$C$1048576,2,0),0) | AI87: =+IFERROR(VLOOKUP(B87,[33]Income!$B$5:$C$78,2,0),0) | AJ87: =+IFERROR(VLOOKUP(B87,[34]Income!$B$6:$D$1048576,2,0),0) | AK87: =+IFERROR(VLOOKUP($B87,'[35]3'!$B$6:$D$1048576,2,0),0)
A88: в. | B88: Минус: Инвестициялар бўйича кўрилиши мумкин бўлган зарарларни баҳолаш | C88: =+IFERROR(VLOOKUP(B88,[1]Лист2!$B$6:$E$1048576,2,0),0) | D88: =+IFERROR(VLOOKUP(B88,'[2]3'!$B$6:$D$1048576,2,0),0) | E88: =+IFERROR(VLOOKUP(B88,'[3]2'!$B$5:$C$77,2,0),0) | F88: =+IFERROR(VLOOKUP(B88,'[4]Income '!$B$5:$E$77,2,0),0) | G88: =+IFERROR(VLOOKUP(B88,'[5]3'!$B$6:$C$1048576,2,0),0) | H88: =+IFERROR(VLOOKUP(B88,[6]Income!$B$6:$D$1048576,2,0),0) | I88: =+IFERROR(VLOOKUP(B88,'[7]Income '!$B$6:$E$1048576,2,0),0) | J88: =+IFERROR(VLOOKUP(B88,'[8]3'!$B$5:$C$77,2,0),0) | K88: =+IFERROR(VLOOKUP(B88,'[9]3'!$B$6:$E$1048576,2,0),0) | L88: =+IFERROR(VLOOKUP(B88,'[10]3'!$B$6:$E$1048576,2,0),0) | M88: =+IFERROR(VLOOKUP(B88,'[11]3'!$B$6:$E$1048576,2,0),0) | N88: =+IFERROR(VLOOKUP(B88,[12]Income!$B$6:$D$1048576,2,0),0) | O88: =+IFERROR(VLOOKUP(B88,'[13]3 т'!$B$6:$C$1048576,2,0),0) | P88: =+IFERROR(VLOOKUP(B88,[14]Income!$B$6:$D$1048576,2,0),0) | Q88: =+IFERROR(VLOOKUP(B88,[15]Income!$B$6:$E$1048576,2,0),0) | R88: =+IFERROR(VLOOKUP(B88,'[16]3'!$B$5:$E$90,2,0),0) | S88: =+IFERROR(VLOOKUP(B88,'[17]3'!$B$6:$E$1048576,2,0),0) | T88: =+IFERROR(VLOOKUP(B88,'[18]2'!$B$5:$E$78,2,0),0) | U88: =+IFERROR(VLOOKUP(B88,[19]Income!$B$6:$D$1048576,2,0),0) | V88: =+IFERROR(VLOOKUP(B88,'[20]3'!$B$6:$E$1048576,2,0),0) | W88: =+IFERROR(VLOOKUP(B88,'[21]Income '!$B$6:$D$1048576,2,0),0) | X88: =+IFERROR(VLOOKUP(B88,'[22]3'!$B$6:$D$1048576,2,0),0) | Y88: =+IFERROR(VLOOKUP(B88,[23]Лист4!$B$5:$C$78,2,0),0) | Z88: =+IFERROR(VLOOKUP(B88,'[24]2'!$B$5:$C$78,2,0),0) | AA88: =+IFERROR(VLOOKUP(B88,[25]Income!$B$5:$C$78,2,0),0) | AB88: =+IFERROR(VLOOKUP(B88,'[26]3'!$B$6:$E$1048576,2,0),0) | AC88: =+IFERROR(VLOOKUP(B88,'[27]3'!$B$6:$E$1048576,2,0),0) | AD88: =+IFERROR(VLOOKUP(B88,'[28]3'!$B$6:$E$1048576,2,0),0) | AE88: =+IFERROR(VLOOKUP(B88,[29]Лист2!$B$6:$E$1048576,2,0),0) | AF88: =+IFERROR(VLOOKUP($B88,'[30]3'!$B$6:$E$1048576,2,0),0) | AG88: =+IFERROR(VLOOKUP(B88,'[31]3'!$B$6:$D$1048576,2,0),0) | AH88: =+IFERROR(VLOOKUP(B88,'[32]3-жадвал'!$B$6:$C$1048576,2,0),0) | AI88: =+IFERROR(VLOOKUP(B88,[33]Income!$B$5:$C$78,2,0),0) | AJ88: =+IFERROR(VLOOKUP(B88,[34]Income!$B$6:$D$1048576,2,0),0) | AK88: =+IFERROR(VLOOKUP($B88,'[35]3'!$B$6:$D$1048576,2,0),0)
A89: г. | B89: Минус: Бошқа активлар бўйича кўрилиши мумкин бўлган зарарларни баҳолаш | C89: =+IFERROR(VLOOKUP(B89,[1]Лист2!$B$6:$E$1048576,2,0),0) | D89: =+IFERROR(VLOOKUP(B89,'[2]3'!$B$6:$D$1048576,2,0),0) | E89: =+IFERROR(VLOOKUP(B89,'[3]2'!$B$5:$C$77,2,0),0) | F89: =+IFERROR(VLOOKUP(B89,'[4]Income '!$B$5:$E$77,2,0),0) | G89: =+IFERROR(VLOOKUP(B89,'[5]3'!$B$6:$C$1048576,2,0),0) | H89: =+IFERROR(VLOOKUP(B89,[6]Income!$B$6:$D$1048576,2,0),0) | I89: =+IFERROR(VLOOKUP(B89,'[7]Income '!$B$6:$E$1048576,2,0),0) | J89: =+IFERROR(VLOOKUP(B89,'[8]3'!$B$5:$C$77,2,0),0) | K89: =+IFERROR(VLOOKUP(B89,'[9]3'!$B$6:$E$1048576,2,0),0) | L89: =+IFERROR(VLOOKUP(B89,'[10]3'!$B$6:$E$1048576,2,0),0) | M89: =+IFERROR(VLOOKUP(B89,'[11]3'!$B$6:$E$1048576,2,0),0) | N89: =+IFERROR(VLOOKUP(B89,[12]Income!$B$6:$D$1048576,2,0),0) | O89: =+IFERROR(VLOOKUP(B89,'[13]3 т'!$B$6:$C$1048576,2,0),0) | P89: =+IFERROR(VLOOKUP(B89,[14]Income!$B$6:$D$1048576,2,0),0) | Q89: =+IFERROR(VLOOKUP(B89,[15]Income!$B$6:$E$1048576,2,0),0) | R89: =+IFERROR(VLOOKUP(B89,'[16]3'!$B$5:$E$90,2,0),0) | S89: =+IFERROR(VLOOKUP(B89,'[17]3'!$B$6:$E$1048576,2,0),0) | T89: =+IFERROR(VLOOKUP(B89,'[18]2'!$B$5:$E$78,2,0),0) | U89: =+IFERROR(VLOOKUP(B89,[19]Income!$B$6:$D$1048576,2,0),0) | V89: =+IFERROR(VLOOKUP(B89,'[20]3'!$B$6:$E$1048576,2,0),0) | W89: =+IFERROR(VLOOKUP(B89,'[21]Income '!$B$6:$D$1048576,2,0),0) | X89: =+IFERROR(VLOOKUP(B89,'[22]3'!$B$6:$D$1048576,2,0),0) | Y89: =+IFERROR(VLOOKUP(B89,[23]Лист4!$B$5:$C$78,2,0),0) | Z89: =+IFERROR(VLOOKUP(B89,'[24]2'!$B$5:$C$78,2,0),0) | AA89: =+IFERROR(VLOOKUP(B89,[25]Income!$B$5:$C$78,2,0),0) | AB89: =+IFERROR(VLOOKUP(B89,'[26]3'!$B$6:$E$1048576,2,0),0) | AC89: =+IFERROR(VLOOKUP(B89,'[27]3'!$B$6:$E$1048576,2,0),0) | AD89: =+IFERROR(VLOOKUP(B89,'[28]3'!$B$6:$E$1048576,2,0),0) | AE89: =+IFERROR(VLOOKUP(B89,[29]Лист2!$B$6:$E$1048576,2,0),0) | AF89: =+IFERROR(VLOOKUP($B89,'[30]3'!$B$6:$E$1048576,2,0),0) | AG89: =+IFERROR(VLOOKUP(B89,'[31]3'!$B$6:$D$1048576,2,0),0) | AH89: =+IFERROR(VLOOKUP(B89,'[32]3-жадвал'!$B$6:$C$1048576,2,0),0) | AI89: =+IFERROR(VLOOKUP(B89,[33]Income!$B$5:$C$78,2,0),0) | AJ89: =+IFERROR(VLOOKUP(B89,[34]Income!$B$6:$D$1048576,2,0),0) | AK89: =+IFERROR(VLOOKUP($B89,'[35]3'!$B$6:$D$1048576,2,0),0)
A90: 4 | B90: Жами фоизсиз даромадлар | C90: =+IFERROR(VLOOKUP(B90,[1]Лист2!$B$6:$E$1048576,2,0),0) | D90: =+IFERROR(VLOOKUP(B90,'[2]3'!$B$6:$D$1048576,2,0),0) | E90: =+IFERROR(VLOOKUP(B90,'[3]2'!$B$5:$C$77,2,0),0) | F90: =+IFERROR(VLOOKUP(B90,'[4]Income '!$B$5:$E$77,2,0),0) | G90: =+IFERROR(VLOOKUP(B90,'[5]3'!$B$6:$C$1048576,2,0),0) | H90: =+IFERROR(VLOOKUP(B90,[6]Income!$B$6:$D$1048576,2,0),0) | I90: =+IFERROR(VLOOKUP(B90,'[7]Income '!$B$6:$E$1048576,2,0),0) | J90: =+IFERROR(VLOOKUP(B90,'[8]3'!$B$5:$C$77,2,0),0) | K90: =+IFERROR(VLOOKUP(B90,'[9]3'!$B$6:$E$1048576,2,0),0) | L90: =+IFERROR(VLOOKUP(B90,'[10]3'!$B$6:$E$1048576,2,0),0) | M90: =+IFERROR(VLOOKUP(B90,'[11]3'!$B$6:$E$1048576,2,0),0) | N90: =+IFERROR(VLOOKUP(B90,[12]Income!$B$6:$D$1048576,2,0),0) | O90: =+IFERROR(VLOOKUP(B90,'[13]3 т'!$B$6:$C$1048576,2,0),0) | P90: =+IFERROR(VLOOKUP(B90,[14]Income!$B$6:$D$1048576,2,0),0) | Q90: =+IFERROR(VLOOKUP(B90,[15]Income!$B$6:$E$1048576,2,0),0) | R90: =+IFERROR(VLOOKUP(B90,'[16]3'!$B$5:$E$90,2,0),0) | S90: =+IFERROR(VLOOKUP(B90,'[17]3'!$B$6:$E$1048576,2,0),0) | T90: =+IFERROR(VLOOKUP(B90,'[18]2'!$B$5:$E$78,2,0),0) | U90: =+IFERROR(VLOOKUP(B90,[19]Income!$B$6:$D$1048576,2,0),0) | V90: =+IFERROR(VLOOKUP(B90,'[20]3'!$B$6:$E$1048576,2,0),0) | W90: =+IFERROR(VLOOKUP(B90,'[21]Income '!$B$6:$D$1048576,2,0),0) | X90: =+IFERROR(VLOOKUP(B90,'[22]3'!$B$6:$D$1048576,2,0),0) | Y90: =+IFERROR(VLOOKUP(B90,[23]Лист4!$B$5:$C$78,2,0),0) | Z90: =+IFERROR(VLOOKUP(B90,'[24]2'!$B$5:$C$78,2,0),0) | AA90: =+IFERROR(VLOOKUP(B90,[25]Income!$B$5:$C$78,2,0),0) | AB90: =+IFERROR(VLOOKUP(B90,'[26]3'!$B$6:$E$1048576,2,0),0) | AC90: =+IFERROR(VLOOKUP(B90,'[27]3'!$B$6:$E$1048576,2,0),0) | AD90: =+IFERROR(VLOOKUP(B90,'[28]3'!$B$6:$E$1048576,2,0),0) | AE90: =+IFERROR(VLOOKUP(B90,[29]Лист2!$B$6:$E$1048576,2,0),0) | AF90: =+IFERROR(VLOOKUP($B90,'[30]3'!$B$6:$E$1048576,2,0),0) | AG90: =+IFERROR(VLOOKUP(B90,'[31]3'!$B$6:$D$1048576,2,0),0) | AH90: =+IFERROR(VLOOKUP(B90,'[32]3-жадвал'!$B$6:$C$1048576,2,0),0) | AI90: =+IFERROR(VLOOKUP(B90,[33]Income!$B$5:$C$78,2,0),0) | AJ90: =+IFERROR(VLOOKUP(B90,[34]Income!$B$6:$D$1048576,2,0),0) | AK90: =+IFERROR(VLOOKUP($B90,'[35]3'!$B$6:$D$1048576,2,0),0)
A91: 5 | B91: Жами фоизсиз харажатлар | C91: =+IFERROR(VLOOKUP(B91,[1]Лист2!$B$6:$E$1048576,2,0),0) | D91: =+IFERROR(VLOOKUP(B91,'[2]3'!$B$6:$D$1048576,2,0),0) | E91: =+IFERROR(VLOOKUP(B91,'[3]2'!$B$5:$C$77,2,0),0) | F91: =+IFERROR(VLOOKUP(B91,'[4]Income '!$B$5:$E$77,2,0),0) | G91: =+IFERROR(VLOOKUP(B91,'[5]3'!$B$6:$C$1048576,2,0),0) | H91: =+IFERROR(VLOOKUP(B91,[6]Income!$B$6:$D$1048576,2,0),0) | I91: =+IFERROR(VLOOKUP(B91,'[7]Income '!$B$6:$E$1048576,2,0),0) | J91: =+IFERROR(VLOOKUP(B91,'[8]3'!$B$5:$C$77,2,0),0) | K91: =+IFERROR(VLOOKUP(B91,'[9]3'!$B$6:$E$1048576,2,0),0) | L91: =+IFERROR(VLOOKUP(B91,'[10]3'!$B$6:$E$1048576,2,0),0) | M91: =+IFERROR(VLOOKUP(B91,'[11]3'!$B$6:$E$1048576,2,0),0) | N91: =+IFERROR(VLOOKUP(B91,[12]Income!$B$6:$D$1048576,2,0),0) | O91: =+IFERROR(VLOOKUP(B91,'[13]3 т'!$B$6:$C$1048576,2,0),0) | P91: =+IFERROR(VLOOKUP(B91,[14]Income!$B$6:$D$1048576,2,0),0) | Q91: =+IFERROR(VLOOKUP(B91,[15]Income!$B$6:$E$1048576,2,0),0) | R91: =+IFERROR(VLOOKUP(B91,'[16]3'!$B$5:$E$90,2,0),0) | S91: =+IFERROR(VLOOKUP(B91,'[17]3'!$B$6:$E$1048576,2,0),0) | T91: =+IFERROR(VLOOKUP(B91,'[18]2'!$B$5:$E$78,2,0),0) | U91: =+IFERROR(VLOOKUP(B91,[19]Income!$B$6:$D$1048576,2,0),0) | V91: =+IFERROR(VLOOKUP(B91,'[20]3'!$B$6:$E$1048576,2,0),0) | W91: =+IFERROR(VLOOKUP(B91,'[21]Income '!$B$6:$D$1048576,2,0),0) | X91: =+IFERROR(VLOOKUP(B91,'[22]3'!$B$6:$D$1048576,2,0),0) | Y91: =+IFERROR(VLOOKUP(B91,[23]Лист4!$B$5:$C$78,2,0),0) | Z91: =+IFERROR(VLOOKUP(B91,'[24]2'!$B$5:$C$78,2,0),0) | AA91: =+IFERROR(VLOOKUP(B91,[25]Income!$B$5:$C$78,2,0),0) | AB91: =+IFERROR(VLOOKUP(B91,'[26]3'!$B$6:$E$1048576,2,0),0) | AC91: =+IFERROR(VLOOKUP(B91,'[27]3'!$B$6:$E$1048576,2,0),0) | AD91: =+IFERROR(VLOOKUP(B91,'[28]3'!$B$6:$E$1048576,2,0),0) | AE91: =+IFERROR(VLOOKUP(B91,[29]Лист2!$B$6:$E$1048576,2,0),0) | AF91: =+IFERROR(VLOOKUP($B91,'[30]3'!$B$6:$E$1048576,2,0),0) | AG91: =+IFERROR(VLOOKUP(B91,'[31]3'!$B$6:$D$1048576,2,0),0) | AH91: =+IFERROR(VLOOKUP(B91,'[32]3-жадвал'!$B$6:$C$1048576,2,0),0) | AI91: =+IFERROR(VLOOKUP(B91,[33]Income!$B$5:$C$78,2,0),0) | AJ91: =+IFERROR(VLOOKUP(B91,[34]Income!$B$6:$D$1048576,2,0),0) | AK91: =+IFERROR(VLOOKUP($B91,'[35]3'!$B$6:$D$1048576,2,0),0)
A92: 6 | B92: Жами операцион харажатлар | C92: =+IFERROR(VLOOKUP(B92,[1]Лист2!$B$6:$E$1048576,2,0),0) | D92: =+IFERROR(VLOOKUP(B92,'[2]3'!$B$6:$D$1048576,2,0),0) | E92: =+IFERROR(VLOOKUP(B92,'[3]2'!$B$5:$C$77,2,0),0) | F92: =+IFERROR(VLOOKUP(B92,'[4]Income '!$B$5:$E$77,2,0),0) | G92: =+IFERROR(VLOOKUP(B92,'[5]3'!$B$6:$C$1048576,2,0),0) | H92: =+IFERROR(VLOOKUP(B92,[6]Income!$B$6:$D$1048576,2,0),0) | I92: =+IFERROR(VLOOKUP(B92,'[7]Income '!$B$6:$E$1048576,2,0),0) | J92: =+IFERROR(VLOOKUP(B92,'[8]3'!$B$5:$C$77,2,0),0) | K92: =+IFERROR(VLOOKUP(B92,'[9]3'!$B$6:$E$1048576,2,0),0) | L92: =+IFERROR(VLOOKUP(B92,'[10]3'!$B$6:$E$1048576,2,0),0) | M92: =+IFERROR(VLOOKUP(B92,'[11]3'!$B$6:$E$1048576,2,0),0) | N92: =+IFERROR(VLOOKUP(B92,[12]Income!$B$6:$D$1048576,2,0),0) | O92: =+IFERROR(VLOOKUP(B92,'[13]3 т'!$B$6:$C$1048576,2,0),0) | P92: =+IFERROR(VLOOKUP(B92,[14]Income!$B$6:$D$1048576,2,0),0) | Q92: =+IFERROR(VLOOKUP(B92,[15]Income!$B$6:$E$1048576,2,0),0) | R92: =+IFERROR(VLOOKUP(B92,'[16]3'!$B$5:$E$90,2,0),0) | S92: =+IFERROR(VLOOKUP(B92,'[17]3'!$B$6:$E$1048576,2,0),0) | T92: =+IFERROR(VLOOKUP(B92,'[18]2'!$B$5:$E$78,2,0),0) | U92: =+IFERROR(VLOOKUP(B92,[19]Income!$B$6:$D$1048576,2,0),0) | V92: =+IFERROR(VLOOKUP(B92,'[20]3'!$B$6:$E$1048576,2,0),0) | W92: =+IFERROR(VLOOKUP(B92,'[21]Income '!$B$6:$D$1048576,2,0),0) | X92: =+IFERROR(VLOOKUP(B92,'[22]3'!$B$6:$D$1048576,2,0),0) | Y92: =+IFERROR(VLOOKUP(B92,[23]Лист4!$B$5:$C$78,2,0),0) | Z92: =+IFERROR(VLOOKUP(B92,'[24]2'!$B$5:$C$78,2,0),0) | AA92: =+IFERROR(VLOOKUP(B92,[25]Income!$B$5:$C$78,2,0),0) | AB92: =+IFERROR(VLOOKUP(B92,'[26]3'!$B$6:$E$1048576,2,0),0) | AC92: =+IFERROR(VLOOKUP(B92,'[27]3'!$B$6:$E$1048576,2,0),0) | AD92: =+IFERROR(VLOOKUP(B92,'[28]3'!$B$6:$E$1048576,2,0),0) | AE92: =+IFERROR(VLOOKUP(B92,[29]Лист2!$B$6:$E$1048576,2,0),0) | AF92: =+IFERROR(VLOOKUP($B92,'[30]3'!$B$6:$E$1048576,2,0),0) | AG92: =+IFERROR(VLOOKUP(B92,'[31]3'!$B$6:$D$1048576,2,0),0) | AH92: =+IFERROR(VLOOKUP(B92,'[32]3-жадвал'!$B$6:$C$1048576,2,0),0) | AI92: =+IFERROR(VLOOKUP(B92,[33]Income!$B$5:$C$78,2,0),0) | AJ92: =+IFERROR(VLOOKUP(B92,[34]Income!$B$6:$D$1048576,2,0),0) | AK92: =+IFERROR(VLOOKUP($B92,'[35]3'!$B$6:$D$1048576,2,0),0)
A93: 7 | B93: Фойда солиғини баҳолаш | C93: =+IFERROR(VLOOKUP(B93,[1]Лист2!$B$6:$E$1048576,2,0),0) | D93: =+IFERROR(VLOOKUP(B93,'[2]3'!$B$6:$D$1048576,2,0),0) | E93: =+IFERROR(VLOOKUP(B93,'[3]2'!$B$5:$C$77,2,0),0) | F93: =+IFERROR(VLOOKUP(B93,'[4]Income '!$B$5:$E$77,2,0),0) | G93: =+IFERROR(VLOOKUP(B93,'[5]3'!$B$6:$C$1048576,2,0),0) | H93: =+IFERROR(VLOOKUP(B93,[6]Income!$B$6:$D$1048576,2,0),0) | I93: =+IFERROR(VLOOKUP(B93,'[7]Income '!$B$6:$E$1048576,2,0),0) | J93: =+IFERROR(VLOOKUP(B93,'[8]3'!$B$5:$C$77,2,0),0) | K93: =+IFERROR(VLOOKUP(B93,'[9]3'!$B$6:$E$1048576,2,0),0) | L93: =+IFERROR(VLOOKUP(B93,'[10]3'!$B$6:$E$1048576,2,0),0) | M93: =+IFERROR(VLOOKUP(B93,'[11]3'!$B$6:$E$1048576,2,0),0) | N93: =+IFERROR(VLOOKUP(B93,[12]Income!$B$6:$D$1048576,2,0),0) | O93: =+IFERROR(VLOOKUP(B93,'[13]3 т'!$B$6:$C$1048576,2,0),0) | P93: =+IFERROR(VLOOKUP(B93,[14]Income!$B$6:$D$1048576,2,0),0) | Q93: =+IFERROR(VLOOKUP(B93,[15]Income!$B$6:$E$1048576,2,0),0) | R93: =+IFERROR(VLOOKUP(B93,'[16]3'!$B$5:$E$90,2,0),0) | S93: =+IFERROR(VLOOKUP(B93,'[17]3'!$B$6:$E$1048576,2,0),0) | T93: =+IFERROR(VLOOKUP(B93,'[18]2'!$B$5:$E$78,2,0),0) | U93: =+IFERROR(VLOOKUP(B93,[19]Income!$B$6:$D$1048576,2,0),0) | V93: =+IFERROR(VLOOKUP(B93,'[20]3'!$B$6:$E$1048576,2,0),0) | W93: =+IFERROR(VLOOKUP(B93,'[21]Income '!$B$6:$D$1048576,2,0),0) | X93: =+IFERROR(VLOOKUP(B93,'[22]3'!$B$6:$D$1048576,2,0),0) | Y93: =+IFERROR(VLOOKUP(B93,[23]Лист4!$B$5:$C$78,2,0),0) | Z93: =+IFERROR(VLOOKUP(B93,'[24]2'!$B$5:$C$78,2,0),0) | AA93: =+IFERROR(VLOOKUP(B93,[25]Income!$B$5:$C$78,2,0),0) | AB93: =+IFERROR(VLOOKUP(B93,'[26]3'!$B$6:$E$1048576,2,0),0) | AC93: =+IFERROR(VLOOKUP(B93,'[27]3'!$B$6:$E$1048576,2,0),0) | AD93: =+IFERROR(VLOOKUP(B93,'[28]3'!$B$6:$E$1048576,2,0),0) | AE93: =+IFERROR(VLOOKUP(B93,[29]Лист2!$B$6:$E$1048576,2,0),0) | AF93: =+IFERROR(VLOOKUP($B93,'[30]3'!$B$6:$E$1048576,2,0),0) | AG93: =+IFERROR(VLOOKUP(B93,'[31]3'!$B$6:$D$1048576,2,0),0) | AH93: =+IFERROR(VLOOKUP(B93,'[32]3-жадвал'!$B$6:$C$1048576,2,0),0) | AI93: =+IFERROR(VLOOKUP(B93,[33]Income!$B$5:$C$78,2,0),0) | AJ93: =+IFERROR(VLOOKUP(B93,[34]Income!$B$6:$D$1048576,2,0),0) | AK93: =+IFERROR(VLOOKUP($B93,'[35]3'!$B$6:$D$1048576,2,0),0)
A94: 8 | B94: ТУЗАТИШЛАР КИРИТИЛГУНГА ҚАДАР ДАРОМАД | C94: =+IFERROR(VLOOKUP(B94,[1]Лист2!$B$6:$E$1048576,2,0),0) | D94: =+IFERROR(VLOOKUP(B94,'[2]3'!$B$6:$D$1048576,2,0),0) | E94: =+IFERROR(VLOOKUP(B94,'[3]2'!$B$5:$C$77,2,0),0) | F94: =+IFERROR(VLOOKUP(B94,'[4]Income '!$B$5:$E$77,2,0),0) | G94: =+IFERROR(VLOOKUP(B94,'[5]3'!$B$6:$C$1048576,2,0),0) | H94: =+IFERROR(VLOOKUP(B94,[6]Income!$B$6:$D$1048576,2,0),0) | I94: =+IFERROR(VLOOKUP(B94,'[7]Income '!$B$6:$E$1048576,2,0),0) | J94: =+IFERROR(VLOOKUP(B94,'[8]3'!$B$5:$C$77,2,0),0) | K94: =+IFERROR(VLOOKUP(B94,'[9]3'!$B$6:$E$1048576,2,0),0) | L94: =+IFERROR(VLOOKUP(B94,'[10]3'!$B$6:$E$1048576,2,0),0) | M94: =+IFERROR(VLOOKUP(B94,'[11]3'!$B$6:$E$1048576,2,0),0) | N94: =+IFERROR(VLOOKUP(B94,[12]Income!$B$6:$D$1048576,2,0),0) | O94: =+IFERROR(VLOOKUP(B94,'[13]3 т'!$B$6:$C$1048576,2,0),0) | P94: =+IFERROR(VLOOKUP(B94,[14]Income!$B$6:$D$1048576,2,0),0) | Q94: =+IFERROR(VLOOKUP(B94,[15]Income!$B$6:$E$1048576,2,0),0) | R94: =+IFERROR(VLOOKUP(B94,'[16]3'!$B$5:$E$90,2,0),0) | S94: =+IFERROR(VLOOKUP(B94,'[17]3'!$B$6:$E$1048576,2,0),0) | T94: =+IFERROR(VLOOKUP(B94,'[18]2'!$B$5:$E$78,2,0),0) | U94: =+IFERROR(VLOOKUP(B94,[19]Income!$B$6:$D$1048576,2,0),0) | V94: =+IFERROR(VLOOKUP(B94,'[20]3'!$B$6:$E$1048576,2,0),0) | W94: =+IFERROR(VLOOKUP(B94,'[21]Income '!$B$6:$D$1048576,2,0),0) | X94: =+IFERROR(VLOOKUP(B94,'[22]3'!$B$6:$D$1048576,2,0),0) | Y94: =+IFERROR(VLOOKUP(B94,[23]Лист4!$B$5:$C$78,2,0),0) | Z94: =+IFERROR(VLOOKUP(B94,'[24]2'!$B$5:$C$78,2,0),0) | AA94: =+IFERROR(VLOOKUP(B94,[25]Income!$B$5:$C$78,2,0),0) | AB94: =+IFERROR(VLOOKUP(B94,'[26]3'!$B$6:$E$1048576,2,0),0) | AC94: =+IFERROR(VLOOKUP(B94,'[27]3'!$B$6:$E$1048576,2,0),0) | AD94: =+IFERROR(VLOOKUP(B94,'[28]3'!$B$6:$E$1048576,2,0),0) | AE94: =+IFERROR(VLOOKUP(B94,[29]Лист2!$B$6:$E$1048576,2,0),0) | AF94: =+IFERROR(VLOOKUP($B94,'[30]3'!$B$6:$E$1048576,2,0),0) | AG94: =+IFERROR(VLOOKUP(B94,'[31]3'!$B$6:$D$1048576,2,0),0) | AH94: =+IFERROR(VLOOKUP(B94,'[32]3-жадвал'!$B$6:$C$1048576,2,0),0) | AI94: =+IFERROR(VLOOKUP(B94,[33]Income!$B$5:$C$78,2,0),0) | AJ94: =+IFERROR(VLOOKUP(B94,[34]Income!$B$6:$D$1048576,2,0),0) | AK94: =+IFERROR(VLOOKUP($B94,'[35]3'!$B$6:$D$1048576,2,0),0)
A95: 9 | B95: СОФ ФОЙДА (ЗАРАР) | C95: =+IFERROR(VLOOKUP(B95,[1]Лист2!$B$6:$E$1048576,2,0),0) | D95: =+IFERROR(VLOOKUP(B95,'[2]3'!$B$6:$D$1048576,2,0),0) | E95: =+IFERROR(VLOOKUP(B95,'[3]2'!$B$5:$C$77,2,0),0) | F95: =+IFERROR(VLOOKUP(B95,'[4]Income '!$B$5:$E$77,2,0),0) | G95: =+IFERROR(VLOOKUP(B95,'[5]3'!$B$6:$C$1048576,2,0),0) | H95: =+IFERROR(VLOOKUP(B95,[6]Income!$B$6:$D$1048576,2,0),0) | I95: =+IFERROR(VLOOKUP(B95,'[7]Income '!$B$6:$E$1048576,2,0),0) | J95: =+IFERROR(VLOOKUP(B95,'[8]3'!$B$5:$C$77,2,0),0) | K95: =+IFERROR(VLOOKUP(B95,'[9]3'!$B$6:$E$1048576,2,0),0) | L95: =+IFERROR(VLOOKUP(B95,'[10]3'!$B$6:$E$1048576,2,0),0) | M95: =+IFERROR(VLOOKUP(B95,'[11]3'!$B$6:$E$1048576,2,0),0) | N95: =+IFERROR(VLOOKUP(B95,[12]Income!$B$6:$D$1048576,2,0),0) | O95: =+IFERROR(VLOOKUP(B95,'[13]3 т'!$B$6:$C$1048576,2,0),0) | P95: =+IFERROR(VLOOKUP(B95,[14]Income!$B$6:$D$1048576,2,0),0) | Q95: =+IFERROR(VLOOKUP(B95,[15]Income!$B$6:$E$1048576,2,0),0) | R95: =+IFERROR(VLOOKUP(B95,'[16]3'!$B$5:$E$90,2,0),0) | S95: =+IFERROR(VLOOKUP(B95,'[17]3'!$B$6:$E$1048576,2,0),0) | T95: =+IFERROR(VLOOKUP(B95,'[18]2'!$B$5:$E$78,2,0),0) | U95: =+IFERROR(VLOOKUP(B95,[19]Income!$B$6:$D$1048576,2,0),0) | V95: =+IFERROR(VLOOKUP(B95,'[20]3'!$B$6:$E$1048576,2,0),0) | W95: =+IFERROR(VLOOKUP(B95,'[21]Income '!$B$6:$D$1048576,2,0),0) | X95: =+IFERROR(VLOOKUP(B95,'[22]3'!$B$6:$D$1048576,2,0),0) | Y95: =+IFERROR(VLOOKUP(B95,[23]Лист4!$B$5:$C$78,2,0),0) | Z95: =+IFERROR(VLOOKUP(B95,'[24]2'!$B$5:$C$78,2,0),0) | AA95: =+IFERROR(VLOOKUP(B95,[25]Income!$B$5:$C$78,2,0),0) | AB95: =+IFERROR(VLOOKUP(B95,'[26]3'!$B$6:$E$1048576,2,0),0) | AC95: =+IFERROR(VLOOKUP(B95,'[27]3'!$B$6:$E$1048576,2,0),0) | AD95: =+IFERROR(VLOOKUP(B95,'[28]3'!$B$6:$E$1048576,2,0),0) | AE95: =+IFERROR(VLOOKUP(B95,[29]Лист2!$B$6:$E$1048576,2,0),0) | AF95: =+IFERROR(VLOOKUP($B95,'[30]3'!$B$6:$E$1048576,2,0),0) | AG95: =+IFERROR(VLOOKUP(B95,'[31]3'!$B$6:$D$1048576,2,0),0) | AH95: =+IFERROR(VLOOKUP(B95,'[32]3-жадвал'!$B$6:$C$1048576,2,0),0) | AI95: =+IFERROR(VLOOKUP(B95,[33]Income!$B$5:$C$78,2,0),0) | AJ95: =+IFERROR(VLOOKUP(B95,[34]Income!$B$6:$D$1048576,2,0),0) | AK95: =+IFERROR(VLOOKUP($B95,'[35]3'!$B$6:$D$1048576,2,0),0)
B96: Капитал монандлиги
A97: 1 | B97: Регулятив капиталнинг монандлик коэффициенти | C97: =+[1]Лист5!$I$7 | D97: =+'[2]22'!$I$7 | E97: =+'[3]5'!$I$7 | F97: =+'[4]Economic Normatives'!$I$7 | G97: =+'[5]22'!$I$7 | H97: =+'[6]Economic Normatives'!$I$7 | I97: =+'[7]Economic Normatives'!$I$7 | J97: =+'[8]22'!$I$7 | K97: =+'[9]22'!$I$7 | L97: =+'[10]22'!$I$7 | M97: =+'[11]22'!$I$7 | N97: =+'[12]Economic Normatives'!$I$7 | O97: =+'[13]22 т'!$I$7 | P97: =+'[14]Economic Normatives'!$I$7 | Q97: =+'[15]Economic Normatives'!$I$7 | R97: =+'[16]22'!$I$7 | S97: =+'[17]22'!$I$7 | T97: =+'[18]5'!$I$7 | U97: =+'[19]Economic normatives'!$I$7 | V97: =+'[20]22'!$I$7 | W97: =+'[21]Economic Normatives'!$I$7 | X97: =+'[22]22'!$I$7 | Y97: =+[23]Лист5!$I$7 | Z97: =+'[24]5'!$I$7 | AA97: =+'[25]Economic Normatives'!$I$7 | AB97: =+'[26]22'!$I$7 | AC97: =+'[27]22'!$I$7 | AD97: =+'[28]22'!$I$7 | AE97: =+[29]Лист5!$I$7 | AF97: =+'[30]22'!$I$7 | AG97: =+'[31]22'!$I$7 | AH97: =+'[32]22-жадвал'!$I$7 | AI97: =+[33]Normatives!$I$7 | AJ97: =+'[34]Economic Normatives'!$I$7 | AK97: =+'[35]22'!$I$7
A98: 2 | B98: I даражали капиталнинг монандлик коэффициенти | C98: =+[1]Лист5!$I$9 | D98: =+'[2]22'!$I$9 | E98: =+'[3]5'!$I$9 | F98: =+'[4]Economic Normatives'!$I$9 | G98: =+'[5]22'!$I$9 | H98: =+'[6]Economic Normatives'!$I$9 | I98: =+'[7]Economic Normatives'!$I$9 | J98: =+'[8]22'!$I$9 | K98: =+'[9]22'!$I$9 | L98: =+'[10]22'!$I$9 | M98: =+'[11]22'!$I$9 | N98: =+'[12]Economic Normatives'!$I$9 | O98: =+'[13]22 т'!$I$9 | P98: =+'[14]Economic Normatives'!$I$9 | Q98: =+'[15]Economic Normatives'!$I$9 | R98: =+'[16]22'!$I$9 | S98: =+'[17]22'!$I$9 | T98: =+'[18]5'!$I$9 | U98: =+'[19]Economic normatives'!$I$9 | V98: =+'[20]22'!$I$9 | W98: =+'[21]Economic Normatives'!$I$9 | X98: =+'[22]22'!$I$9 | Y98: =+[23]Лист5!$I$9 | Z98: =+'[24]5'!$I$9 | AA98: =+'[25]Economic Normatives'!$I$9 | AB98: =+'[26]22'!$I$9 | AC98: =+'[27]22'!$I$9 | AD98: =+'[28]22'!$I$9 | AE98: =+[29]Лист5!$I$9 | AF98: =+'[30]22'!$I$9 | AG98: =+'[31]22'!$I$9 | AH98: =+'[32]22-жадвал'!$I$9 | AI98: =+[33]Normatives!$I$9 | AJ98: =+'[34]Economic Normatives'!$I$9 | AK98: =+'[35]22'!$I$9
A99: 3 | B99: I даражали асосий капиталнинг монандлик коэффициенти | C99: =+[1]Лист5!$I$11 | D99: =+'[2]22'!$I$11 | E99: =+'[3]5'!$I$11 | F99: =+'[4]Economic Normatives'!$I$11 | G99: =+'[5]22'!$I$11 | H99: =+'[6]Economic Normatives'!$I$11 | I99: =+'[7]Economic Normatives'!$I$11 | J99: =+'[8]22'!$I$11 | K99: =+'[9]22'!$I$11 | L99: =+'[10]22'!$I$11 | M99: =+'[11]22'!$I$11 | N99: =+'[12]Economic Normatives'!$I$11 | O99: =+'[13]22 т'!$I$11 | P99: =+'[14]Economic Normatives'!$I$11 | Q99: =+'[15]Economic Normatives'!$I$11 | R99: =+'[16]22'!$I$11 | S99: =+'[17]22'!$I$11 | T99: =+'[18]5'!$I$11 | U99: =+'[19]Economic normatives'!$I$11 | V99: =+'[20]22'!$I$11 | W99: =+'[21]Economic Normatives'!$I$11 | X99: =+'[22]22'!$I$11 | Y99: =+[23]Лист5!$I$11 | Z99: =+'[24]5'!$I$11 | AA99: =+'[25]Economic Normatives'!$I$11 | AB99: =+'[26]22'!$I$11 | AC99: =+'[27]22'!$I$11 | AD99: =+'[28]22'!$I$11 | AE99: =+[29]Лист5!$I$11 | AF99: =+'[30]22'!$I$11 | AG99: =+'[31]22'!$I$11 | AH99: =+'[32]22-жадвал'!$I$11 | AI99: =+[33]Normatives!$I$11 | AJ99: =+'[34]Economic Normatives'!$I$11 | AK99: =+'[35]22'!$I$11
A100: 4 | B100: Левераж | C100: =+[1]Лист5!$I$13 | D100: =+'[2]22'!$I$13 | E100: =+'[3]5'!$I$13 | F100: =+'[4]Economic Normatives'!$I$13 | G100: =+'[5]22'!$I$13 | H100: =+'[6]Economic Normatives'!$I$13 | I100: =+'[7]Economic Normatives'!$I$13 | J100: =+'[8]22'!$I$13 | K100: =+'[9]22'!$I$13 | L100: =+'[10]22'!$I$13 | M100: =+'[11]22'!$I$13 | N100: =+'[12]Economic Normatives'!$I$13 | O100: =+'[13]22 т'!$I$13 | P100: =+'[14]Economic Normatives'!$I$13 | Q100: =+'[15]Economic Normatives'!$I$13 | R100: =+'[16]22'!$I$13 | S100: =+'[17]22'!$I$13 | T100: =+'[18]5'!$I$13 | U100: =+'[19]Economic normatives'!$I$13 | V100: =+'[20]22'!$I$13 | W100: =+'[21]Economic Normatives'!$I$13 | X100: =+'[22]22'!$I$13 | Y100: =+[23]Лист5!$I$13 | Z100: =+'[24]5'!$I$13 | AA100: =+'[25]Economic Normatives'!$I$13 | AB100: =+'[26]22'!$I$13 | AC100: =+'[27]22'!$I$13 | AD100: =+'[28]22'!$I$13 | AE100: =+[29]Лист5!$I$13 | AF100: =+'[30]22'!$I$13 | AG100: =+'[31]22'!$I$13 | AH100: =+'[32]22-жадвал'!$I$13 | AI100: =+[33]Normatives!$I$13 | AJ100: =+'[34]Economic Normatives'!$I$13 | AK100: =+'[35]22'!$I$13
B101: Ликвидлилик кўрсаткичлари
A102: 1 | B102: Юқори ликвидли активларнинг жами активлардаги улуши | C102: =+[1]Лист5!$I$16 | D102: =+'[2]22'!$I$16 | E102: =+'[3]5'!$I$16 | F102: =+'[4]Economic Normatives'!$I$16 | G102: =+'[5]22'!$I$16 | H102: =+'[6]Economic Normatives'!$I$16 | I102: =+'[7]Economic Normatives'!$I$16 | J102: =+'[8]22'!$I$16 | K102: =+'[9]22'!$I$16 | L102: =+'[10]22'!$I$16 | M102: =+'[11]22'!$I$16 | N102: =+'[12]Economic Normatives'!$I$16 | O102: =+'[13]22 т'!$I$16 | P102: =+'[14]Economic Normatives'!$I$16 | Q102: =+'[15]Economic Normatives'!$I$16 | R102: =+'[16]22'!$I$16 | S102: =+'[17]22'!$I$16 | T102: =+'[18]5'!$I$16 | U102: =+'[19]Economic normatives'!$I$16 | V102: =+'[20]22'!$I$16 | W102: =+'[21]Economic Normatives'!$I$16 | X102: =+'[22]22'!$I$16 | Y102: =+[23]Лист5!$I$16 | Z102: =+'[24]5'!$I$16 | AA102: =+'[25]Economic Normatives'!$I$16 | AB102: =+'[26]22'!$I$16 | AC102: =+'[27]22'!$I$16 | AD102: =+'[28]22'!$I$16 | AE102: =+[29]Лист5!$I$16 | AF102: =+'[30]22'!$I$16 | AG102: =+'[31]22'!$I$16 | AH102: =+'[32]22-жадвал'!$I$16 | AI102: =+[33]Normatives!$I$16 | AJ102: =+'[34]Economic Normatives'!$I$16 | AK102: =+'[35]22'!$I$16
A103: 2 | B103: Ликвидликни қоплаш меъёри | C103: =+[1]Лист5!$I$18 | D103: =+'[2]22'!$I$18 | E103: =+'[3]5'!$I$18 | F103: =+'[4]Economic Normatives'!$I$18 | G103: =+'[5]22'!$I$18 | H103: =+'[6]Economic Normatives'!$I$18 | I103: =+'[7]Economic Normatives'!$I$18 | J103: =+'[8]22'!$I$18 | K103: =+'[9]22'!$I$18 | L103: =+'[10]22'!$I$18 | M103: =+'[11]22'!$I$18 | N103: =+'[12]Economic Normatives'!$I$18 | O103: =+'[13]22 т'!$I$18 | P103: =+'[14]Economic Normatives'!$I$18 | Q103: =+'[15]Economic Normatives'!$I$18 | R103: =+'[16]22'!$I$18 | S103: =+'[17]22'!$I$18 | T103: =+'[18]5'!$I$18 | U103: =+'[19]Economic normatives'!$I$18 | V103: =+'[20]22'!$I$18 | W103: =+'[21]Economic Normatives'!$I$18 | X103: =+'[22]22'!$I$18 | Y103: =+[23]Лист5!$I$18 | Z103: =+'[24]5'!$I$18 | AA103: =+'[25]Economic Normatives'!$I$18 | AB103: =+'[26]22'!$I$18 | AC103: =+'[27]22'!$I$18 | AD103: =+'[28]22'!$I$18 | AE103: =+[29]Лист5!$I$18 | AF103: =+'[30]22'!$I$18 | AG103: =+'[31]22'!$I$18 | AH103: =+'[32]22-жадвал'!$I$18 | AI103: =+[33]Normatives!$I$18 | AJ103: =+'[34]Economic Normatives'!$I$18 | AK103: =+'[35]22'!$I$18
A104: 3 | B104: Соф барқарор молиялаштириш меъёри | C104: =+[1]Лист5!$I$21 | D104: =+'[2]22'!$I$21 | E104: =+'[3]5'!$I$21 | F104: =+'[4]Economic Normatives'!$I$21 | G104: =+'[5]22'!$I$18 | H104: =+'[6]Economic Normatives'!$I$21 | I104: =+'[7]Economic Normatives'!$I$21 | J104: =+'[8]22'!$I$21 | K104: =+'[9]22'!$I$21 | L104: =+'[10]22'!$I$21 | M104: =+'[11]22'!$I$21 | N104: =+'[12]Economic Normatives'!$I$21 | O104: =+'[13]22 т'!$I$21 | P104: =+'[14]Economic Normatives'!$I$21 | Q104: =+'[15]Economic Normatives'!$I$21 | R104: =+'[16]22'!$I$21 | S104: =+'[17]22'!$I$21 | T104: =+'[18]5'!$I$21 | U104: =+'[19]Economic normatives'!$I$21 | V104: =+'[20]22'!$I$21 | W104: =+'[21]Economic Normatives'!$I$21 | X104: =+'[22]22'!$I$21 | Y104: =+[23]Лист5!$I$21 | Z104: =+'[24]5'!$I$21 | AA104: =+'[25]Economic Normatives'!$I$21 | AB104: =+'[26]22'!$I$21 | AC104: =+'[27]22'!$I$21 | AD104: =+'[28]22'!$I$21 | AE104: =+[29]Лист5!$I$21 | AF104: =+'[30]22'!$I$21 | AG104: =+'[31]22'!$I$21 | AH104: =+'[32]22-жадвал'!$I$21 | AI104: =+[33]Normatives!$I$21 | AJ104: =+'[34]Economic Normatives'!$I$21 | AK104: =+'[35]22'!$I$21
...

Sheet Foreign banks
A1: Основные показатели
D2: 44378
A3: № | B3: Показатели баланса | C3: Sberbank | D3: АО Россельхозбанк | E3: ТКБ БАНК ПАО | F3: Asia Invest bank
A4: 1 | B4: Активы
A5: =+A4+1 | B5: Кредиты юридическим лицам
A6: =+A5+1 | B6: Кредиты физическим лицам
A7: =+A6+1 | B7: Резервы на возможные потери по кредитам клиентам
A8: =+A7+1 | B8: Вложения в ценные бумаги
A9: =+A8+1 | B9: Средства физических лиц
A10: =+A9+1 | B10: Средства юридических лиц
A11: =+A10+1 | B11: Собственные средства
A12: =+A11+1 | B12: Капитал базовый (Н1.1)*
A13: =+A12+1 | B13: Капитал основной (Н1.2)*
A14: =+A13+1 | B14: Капитал общий (Н1.0)*
A15: =+A14+1 | B15: Достаточность базового капитала Н1.1 (мин. 4,5%)*
A16: =+A15+1 | B16: Достаточность основного капитала Н1.2 (мин. 6,0%)*
A17: =+A16+1 | B17: Достаточность общего капитала Н1.0 (мин. 8,0%)*
B18: Показатели отчета о финансовых результата
A19: =+A17+1 | B19: Чистый процентный доход
A20: =+A19+1 | B20: Чистый комиссионный доход
A21: =+A20+1 | B21: Чистый доход от валютной переоценки и торговых операций
A22: =+A21+1 | B22: Операционные доходы до резервов
A23: =+A22+1 | B23: Расходы по совокупным резервам
A24: =+A23+1 | B24: Операционные расходы
A25: =+A24+1 | B25: Прибыль до налога на прибыль
A26: =+A25+1 | B26: Чистая прибыль
A27: =+A26+1 | B27: Совокупный финансовый результат
A28: =+A27+1 | B28: Качественные показатели (%)
A29: =+A28+1 | B29: Рентабельность активов
A30: =+A29+1 | B30: Рентабельность капитала
A31: =+A30+1 | B31: Отношение операционных расходов к доходам
A32: =+A31+1 | B32: Отношение расходов к средним активам за период

Sheet Хорижий банклар
B2: ming. so‘m | C2: 45839
B3: Банкнинг чет эл валютасидаги умумий активлар | C3: USD | D3: EUR | E3: RUB | F3: TRY | G3: GBP
B4: 7490288944 | C4: 12654.13 | D4: 14817.99 | E4: 161.18 | F4: 317.27 | G4: 17386.77
L6: 5000000
A7: № | B7: Мамлакат номи | C7: Халқаро рейтинг агентликларининг узоқ муддатли суверен кредит рейтинглари | F7: Мамлакат бўйича банк рейтинги | G7: Бир мамлакат учун мумкин бўлган максимал ҳисоб-китоб лимити (банкнинг чет эл валютасидаги умумий активларининг фоизи) | H7: Банкнинг чет эл валютасидаги умумий активлар | I7: Якуний лимит (UZS) | J7: Якуний лимит (USD) | L7: =+L6*18%/24 | Q7: Xalqaro reyting agentliklarining uzoq muddatli suveren kredit reytinglari | T7: Mamlakat va hamkor banklar boʻyicha reyting | U7: Bir mamlakat uchun mumkin boʻlgan maksimal hisob-kitob limiti | V7: Hamkor bank uchun mumkin boʻlgan maksimal hisob-kitob limiti
C8: Standard &Poor’s | D8: Moody’s | E8: Fitch Ratings | Q8: Standard &Poor’s | R8: Moody’s | S8: Fitch Ratings
A9: 1 | B9: Россия | C9: CCC+ ва ундан пастроқ | D9: B1, B2, B3 | E9: B+,B, B- | F9: A | G9: =+VLOOKUP(F9,$T$9:$U$15,2,0) | H9: =+B4*1000 | I9: =+H9*G9 | J9: =+I9/$C$4 | Q9: AAA, AA+ | R9: Aaa, Aa1 | S9: AAA, AA+ | T9: A+ | U9: 0.3 | V9: =+U9/2
